Workbook
Name _Toc126584005: Proyek!#REF!
Name _Toc126584005: 'Proyek PPT'!#REF!
Name _Toc126584005: #REF!
Name HariLibur2020: #REF!
Name TabelNA: #REF!
Name TargetHK: #REF!
Name Tkomoditi: #REF!

Sheet WG BI Wide 2026 (2)
A1: WG-1
A2: Surrounding BIFAST Multiyears
A3: JAN | B3: FEB | C3: MAR | D3: APR | E3: MEI | F3: JUN | G3: JUL | H3: AUG | I3: SEP | J3: OCT | K3: NOV | L3: DEC
A4: 0.08 | B4: 0.1 | C4: 0.12 | D4: 0.15 | E4: 0.175 | F4: 0.2 | G4: 0.215 | H4: 0.23 | I4: 0.245 | J4: 0.26 | K4: 0.275 | L4: 0.3
A5: Surrounding BIFAST 2026
A6: JAN | B6: FEB | C6: MAR | D6: APR | E6: MEI | F6: JUN | G6: JUL | H6: AUG | I6: SEP | J6: OCT | K6: NOV | L6: DEC
A7: =A4/$L$4 -> 0.26666667 | B7: =B4/$L$4 -> 0.33333333 | C7: =C4/$L$4 -> 0.4 | D7: =D4/$L$4 -> 0.5 | E7: =E4/$L$4 -> 0.58333333 | F7: =F4/$L$4 -> 0.66666667 | G7: =G4/$L$4 -> 0.71666667 | H7: =H4/$L$4 -> 0.76666667 | ... L7: =L4/$L$4 -> 1
A9: WG-2
A10: Surrounding BI-RTGS Gen III (Multiyears)
A11: JAN | B11: FEB | C11: MAR | D11: APR | E11: MEI | F11: JUN | G11: JUL | H11: AUG | I11: SEP | J11: OCT | K11: NOV | L11: DEC
A12: 0 | B12: 0 | C12: 0 | D12: 0 | E12: 0 | F12: 0 | G12: 0 | H12: 0 | I12: 0 | J12: 0.016 | K12: 0.03 | L12: 0.045
A13: Surrounding BI-RTGS Gen III 2026
A14: JAN | B14: FEB | C14: MAR | D14: APR | E14: MEI | F14: JUN | G14: JUL | H14: AUG | I14: SEP | J14: OCT | K14: NOV | L14: DEC
A15: =A12/$L$12 -> 0 | B15: =B12/$L$12 -> 0 | C15: =C12/$L$12 -> 0 | D15: =D12/$L$12 -> 0 | E15: =E12/$L$12 -> 0 | F15: =F12/$L$12 -> 0 | G15: =G12/$L$12 -> 0 | H15: =H12/$L$12 -> 0 | ... L15: =L12/$L$12 -> 1
A17: Transaksi Repo SVBI dan SUVBI valas (Tahap 1) 2026
A18: JAN | B18: FEB | C18: MAR | D18: APR | E18: MEI | F18: JUN | G18: JUL | H18: AUG | I18: SEP | J18: OCT | K18: NOV | L18: DEC
A19: 0.2 | B19: 0.45 | C19: 0.875 | D19: 1 | E19: 1 | F19: 1 | G19: 1 | H19: 1 | I19: 1 | J19: 1 | K19: 1 | L19: 1
A21: Transaksi Repo SVBI dan SUVBI Rupiah (CCR - Tahap 2) Multiyears
A22: JAN | B22: FEB | C22: MAR | D22: APR | E22: MEI | F22: JUN | G22: JUL | H22: AUG | I22: SEP | J22: OCT | K22: NOV | L22: DEC
A23: 0 | B23: 0 | C23: 0 | D23: 0 | E23: 0 | F23: 0 | G23: 0 | H23: 0 | I23: 0 | J23: 0.075 | K23: 0.15 | L23: 0.2
A24: Transaksi Repo SVBI dan SUVBI Rupiah (CCR - Tahap 2) 2026
A25: JAN | B25: FEB | C25: MAR | D25: APR | E25: MEI | F25: JUN | G25: JUL | H25: AUG | I25: SEP | J25: OCT | K25: NOV | L25: DEC
A26: =A23/$L$23 -> 0 | B26: =B23/$L$23 -> 0 | C26: =C23/$L$23 -> 0 | D26: =D23/$L$23 -> 0 | E26: =E23/$L$23 -> 0 | F26: =F23/$L$23 -> 0 | G26: =G23/$L$23 -> 0 | H26: =H23/$L$23 -> 0 | ... L26: =L23/$L$23 -> 1
A28: WG-2
A29: CBS Multiyears
A30: JAN | B30: FEB | C30: MAR | D30: APR | E30: MEI | F30: JUN | G30: JUL | H30: AUG | I30: SEP | J30: OCT | K30: NOV | L30: DEC
A31: 0.08 | B31: 0.1 | C31: 0.12 | D31: 0.15 | E31: 0.175 | F31: 0.2 | G31: 0.215 | H31: 0.23 | I31: 0.245 | J31: 0.26 | K31: 0.275 | L31: 0.3
A32: CBS 2026
A33: JAN | B33: FEB | C33: MAR | D33: APR | E33: MEI | F33: JUN | G33: JUL | H33: AUG | I33: SEP | J33: OCT | K33: NOV | L33: DEC
A34: =A31/$L$4 -> 0.26666667 | B34: =B31/$L$4 -> 0.33333333 | C34: =C31/$L$4 -> 0.4 | D34: =D31/$L$4 -> 0.5 | E34: =E31/$L$4 -> 0.58333333 | F34: =F31/$L$4 -> 0.66666667 | G34: =G31/$L$4 -> 0.71666667 | H34: =H31/$L$4 -> 0.76666667 | ... L34: =L31/$L$4 -> 1
K41: =35/8 -> 4.375 | L41: =K41*6 -> 26.25 | M41: =L41+26 -> 52.25
C47: Target
C48: Pengembangan Product OM Pro Market (Rupiah dan Valas) Multiyears
C49: JAN | D49: FEB | E49: MAR | F49: APR | G49: MEI | H49: JUN | I49: JUL | J49: AUG | K49: SEP | L49: OCT | M49: NOV | N49: DEC
B50: AVERAGE | C50: =AVERAGE(C52:C64) -> 0.069230769 | D50: =AVERAGE(D52:D64) -> 0.125 | E50: =AVERAGE(E52:E64) -> 0.15769231 | F50: =AVERAGE(F52:F64) -> 0.18230769 | G50: =AVERAGE(G52:G64) -> 0.23307692 | H50: =AVERAGE(H52:H64) -> 0.25384615 | I50: =AVERAGE(I52:I64) -> 0.29423077 | J50: =AVERAGE(J52:J64) -> 0.30769231 | ... N50: =AVERAGE(N52:N64) -> 0.40384615
E51: =E50/N50 -> 0.39047619 | H51: =H50/N50 -> 0.62857143 | K51: =K50/N50 -> 0.8047619 | N51: =N50/N50 -> 1
B52: Penambahan Portfolio SBN AC/HTM pada transaksi OM | C52: 0.45 | D52: 0.875 | E52: 1 | F52: 1 | G52: 1 | H52: 1 | I52: 1 | J52: 1 | K52: 1 | L52: 1 | M52: 1 | N52: 1
B53: Reopening SRBI - Tahap 2 (Searchable collateral) | C53: 0.15 | D53: 0.15 | E53: 0.15 | F53: 0.15 | G53: 0.3 | H53: 0.45 | I53: 0.8 | J53: 0.9 | K53: 0.95 | L53: 0.95 | M53: 1 | N53: 1
B54: Penerbitan Bank Indonesia Floating Rate Note (BI-FRN) | C54: 0.15 | D54: 0.3 | E54: 0.45 | F54: 0.57 | G54: 0.7 | H54: 0.8 | I54: 0.875 | J54: 0.9 | K54: 0.925 | L54: 0.95 | M54: 1 | N54: 1
B55: Integrasi dengan Market Operator untuk Transaksi OM dg Agent Bank | C55: 0 | D55: 0 | E55: 0 | F55: 0 | G55: 0 | H55: 0 | I55: 0 | J55: 0 | K55: 0 | L55: 0 | M55: 0 | N55: 0
B56: Perluasan investor SUKBI Non Bank | C56: 0 | D56: 0.15 | E56: 0.3 | F56: 0.5 | G56: 0.88 | H56: 0.9 | I56: 0.95 | J56: 0.95 | K56: 0.95 | L56: 1 | M56: 1 | N56: 1
B57: Transaksi Repo SVBI dan SUVBI valas (Tahap 1) | C57: 0 | D57: 0 | E57: 0 | F57: 0 | G57: 0 | H57: 0 | I57: 0 | J57: 0 | K57: 0 | L57: 0 | M57: 0.05 | N57: 0.1
B58: Transaksi Repo SVBI dan SUVBI Rupiah (CCR - Tahap 2) | C58: 0 | D58: 0 | E58: 0 | F58: 0 | G58: 0 | H58: 0 | I58: 0 | J58: 0 | K58: 0 | L58: 0 | M58: 0 | N58: 0
B59: Transaksi DNDF Syariah melalui PDs | C59: 0 | D59: 0 | E59: 0 | F59: 0 | G59: 0 | H59: 0 | I59: 0 | J59: 0 | K59: 0 | L59: 0 | M59: 0 | N59: 0
B60: Integrasi BI-ETP dan CMS-OM | C60: 0 | D60: 0 | E60: 0 | F60: 0 | G60: 0 | H60: 0 | I60: 0 | J60: 0 | K60: 0 | L60: 0 | M60: 0 | N60: 0
B61: Penerbitan Bank Indonesia Floating Rate Note (BI-FRN) pengembangan Alternate ETP | C61: 0.15 | D61: 0.15 | E61: 0.15 | F61: 0.15 | G61: 0.15 | H61: 0.15 | I61: 0.15 | J61: 0.15 | K61: 0.15 | L61: 0.15 | M61: 0.15 | N61: 0.15
B62: Pengembangan Infrastruktur Penguatan Pasar Obligasi Korporasi dan EBA Tahap 1 | C62: 0 | D62: 0 | E62: 0 | F62: 0 | G62: 0 | H62: 0 | I62: 0.05 | J62: 0.1 | K62: 0.25 | L62: 0.925 | M62: 1 | N62: 1
B63: Pengembangan Infrastruktur Penguatan Pasar Obligasi Korporasi dan EBA Tahap 2 | C63: 0 | D63: 0 | E63: 0 | F63: 0 | G63: 0 | H63: 0 | I63: 0 | J63: 0 | K63: 0 | L63: 0 | M63: 0 | N63: 0
B64: Securities Borrowing Lending BI | C64: 0 | D64: 0 | E64: 0 | F64: 0 | G64: 0 | H64: 0 | I64: 0 | J64: 0 | K64: 0 | L64: 0 | M64: 0 | N64: 0
C68: Pengembangan Product OM Pro Market (Rupiah dan Valas) Multiyears
C69: JAN | D69: FEB | E69: MAR | F69: APR | G69: MEI | H69: JUN | I69: JUL | J69: AUG | K69: SEP | L69: OCT | M69: NOV | N69: DEC
B70: AVERAGE | C70: =AVERAGE(C72:C74) -> 0.033333333 | D70: =AVERAGE(D72:D84) -> 0.056666667 | E70: =AVERAGE(E72:E84) -> 0.18333333 | F70: =AVERAGE(F72:F84) -> 0.31666667 | G70: =AVERAGE(G72:G84) -> 0.45 | H70: =AVERAGE(H72:H84) -> 0.54166667 | I70: =AVERAGE(I72:I84) -> 0.66666667 | J70: =AVERAGE(J72:J84) -> 0.76666667 | K70: =AVERAGE(K72:K84) -> 0.83333333 | ... N70: =AVERAGE(N72:N84) -> 1
E71: =E70/N70 -> 0.18333333 | H71: =H70/N70 -> 0.54166667 | K71: =K70/N70 -> 0.83333333 | N71: =N70/N70 -> 1
B72: Capturing Matchmaking OIS | C72: 0.05 | D72: 0.1 | E72: 0.45 | F72: 0.6 | G72: 0.8 | H72: 0.875 | I72: 0.9 | J72: 0.95 | K72: 1 | L72: 1 | M72: 1 | N72: 1
B73: EDP Capturing Pricing - Pricing Calculation & Dissemination: Perluasan kurs acuan non-USD/IDR (AED/IDR) | C73: 0.05 | D73: 0.07 | E73: 0.1 | F73: 0.3 | G73: 0.45 | H73: 0.6 | I73: 0.8 | J73: 0.9 | K73: 1 | L73: 1 | M73: 1 | N73: 1
B74: Penerbitan Bank Indonesia Floating Rate Note (BI-FRN) | C74: 0 | D74: 0 | E74: 0 | F74: 0.05 | G74: 0.1 | H74: 0.15 | I74: 0.3 | J74: 0.45 | K74: 0.5 | L74: 0.8 | M74: 0.875 | N74: 1

Sheet WG BI Wide 2026
A1: WG-1
A2: Surrounding BIFAST Multiyears
A3: JAN | B3: FEB | C3: MAR | D3: APR | E3: MEI | F3: JUN | G3: JUL | H3: AUG | I3: SEP | J3: OCT | K3: NOV | L3: DEC
A4: 0.135 | B4: 0.14 | C4: 0.15 | D4: 0.2 | E4: 0.225 | F4: 0.25 | G4: 0.26 | H4: 0.27 | I4: 0.28 | J4: 0.29 | K4: 0.295 | L4: 0.3
A5: Surrounding BIFAST 2026
A6: JAN | B6: FEB | C6: MAR | D6: APR | E6: MEI | F6: JUN | G6: JUL | H6: AUG | I6: SEP | J6: OCT | K6: NOV | L6: DEC
A7: =A4/$L$4 -> 0.45 | B7: =B4/$L$4 -> 0.46666667 | C7: =C4/$L$4 -> 0.5 | D7: =D4/$L$4 -> 0.66666667 | E7: =E4/$L$4 -> 0.75 | F7: =F4/$L$4 -> 0.83333333 | G7: =G4/$L$4 -> 0.86666667 | H7: =H4/$L$4 -> 0.9 | ... L7: =L4/$L$4 -> 1
A10: WG-2
A11: Surrounding BI-RTGS Gen III (Multiyears)
A12: JAN | B12: FEB | C12: MAR | D12: APR | E12: MEI | F12: JUN | G12: JUL | H12: AUG | I12: SEP | J12: OCT | K12: NOV | L12: DEC
A13: 0 | B13: 0 | C13: 0 | D13: 0 | E13: 0 | F13: 0 | G13: 0 | H13: 0 | I13: 0 | J13: 0.016 | K13: 0.03 | L13: 0.045
A14: Surrounding BI-RTGS Gen III 2026
A15: JAN | B15: FEB | C15: MAR | D15: APR | E15: MEI | F15: JUN | G15: JUL | H15: AUG | I15: SEP | J15: OCT | K15: NOV | L15: DEC
A16: =A13/$L$13 -> 0 | B16: =B13/$L$13 -> 0 | C16: =C13/$L$13 -> 0 | D16: =D13/$L$13 -> 0 | E16: =E13/$L$13 -> 0 | F16: =F13/$L$13 -> 0 | G16: =G13/$L$13 -> 0 | H16: =H13/$L$13 -> 0 | ... L16: =L13/$L$13 -> 1
A18: WG-2
A19: CBS Multiyears
A20: JAN | B20: FEB | C20: MAR | D20: APR | E20: MEI | F20: JUN | G20: JUL | H20: AUG | I20: SEP | J20: OCT | K20: NOV | L20: DEC | O20: =25/30 -> 0.83333333
A21: 0.08 | B21: 0.1 | C21: 0.15 | D21: 0.2 | E21: 0.21 | F21: 0.22 | G21: 0.23 | H21: 0.24 | I21: 0.25 | J21: 0.26 | K21: 0.27 | L21: 0.28 | O21: =28/30 -> 0.93333333
A22: CBS 2026
A23: JAN | B23: FEB | C23: MAR | D23: APR | E23: MEI | F23: JUN | G23: JUL | H23: AUG | I23: SEP | J23: OCT | K23: NOV | L23: DEC
A24: =A21/$L$21 -> 0.28571429 | B24: =B21/$L$21 -> 0.35714286 | C24: =C21/$L$21 -> 0.53571429 | D24: =D21/$L$21 -> 0.71428571 | E24: =E21/$L$21 -> 0.75 | F24: =F21/$L$21 -> 0.78571429 | G24: =G21/$L$21 -> 0.82142857 | H24: =H21/$L$21 -> 0.85714286 | ... L24: =L21/$L$21 -> 1
B26: Pengembangan Product OM Pro Market (Rupiah dan Valas) Multiyears
B28: JAN | C28: FEB | D28: MAR | E28: APR | F28: MEI | G28: JUN | H28: JUL | I28: AUG | J28: SEP | K28: OCT | L28: NOV | M28: DEC
A29: Multi | B29: =AVERAGE(B32:B35) -> 0.05 | C29: =AVERAGE(C32:C35) -> 0.1375 | D29: =AVERAGE(D32:D35) -> 0.1825 | E29: =AVERAGE(E32:E35) -> 0.235 | F29: =AVERAGE(F32:F35) -> 0.3875 | G29: =AVERAGE(G32:G35) -> 0.4675 | H29: =AVERAGE(H32:H35) -> 0.4875 | I29: =AVERAGE(I32:I35) -> 0.505 | ... M29: =AVERAGE(M32:M35) -> 0.5625
A30: 2026 | B30: =B29/$M$29 -> 0.088888889 | C30: =C29/$M$29 -> 0.24444444 | D30: =D29/$M$29 -> 0.32444444 | E30: =E29/$M$29 -> 0.41777778 | F30: =F29/$M$29 -> 0.68888889 | G30: =G29/$M$29 -> 0.83111111 | H30: =H29/$M$29 -> 0.86666667 | I30: =I29/$M$29 -> 0.89777778 | ... M30: =M29/$M$29 -> 1
A31: Integrasi dengan Market Operator untuk Transaksi OM dg Agent Bank | B31: 0 | C31: 0 | D31: 0 | E31: 0 | F31: 0 | G31: 0 | H31: 0 | I31: 0 | J31: 0 | K31: 0 | L31: 0 | M31: 0.03
A32: Transaksi Repo SVBI dan SUVBI valas (Tahap 1) | B32: 0.05 | C32: 0.1 | D32: 0.15 | E32: 0.2 | F32: 0.75 | G32: 1 | H32: 1 | I32: 1 | J32: 1 | K32: 1 | L32: 1 | M32: 1
A33: Transaksi Repo SVBI dan SUVBI Rupiah (CCR - Tahap 2) | B33: 0 | C33: 0 | D33: 0 | E33: 0 | F33: 0 | G33: 0 | H33: 0 | I33: 0 | J33: 0 | K33: 0.05 | L33: 0.1 | M33: 0.15
A34: Penerbitan Bank Indonesia Floating Rate Note (BI-FRN) pengembangan Alternate ETP | B34: 0.15 | C34: 0.45 | D34: 0.58 | E34: 0.74 | F34: 0.8 | G34: 0.87 | H34: 0.95 | I34: 1 | J34: 1 | K34: 1 | L34: 1 | M34: 1
A35: Pengembangan Infrastruktur Penguatan Pasar Obligasi Korporasi dan EBA Tahap 2 | B35: 0 | C35: 0 | D35: 0 | E35: 0 | F35: 0 | G35: 0 | H35: 0 | I35: 0.02 | J35: 0.04 | K35: 0.06 | L35: 0.08 | M35: 0.1
A36: Pengembangan Infrastruktur Penguatan Pasar Obligasi Korporasi dan EBA Tahap 1 | B36: 1 | C36: 1 | D36: 1 | E36: 1 | F36: 1 | G36: 1 | H36: 1 | I36: 1 | J36: 1 | K36: 1 | L36: 1 | M36: 1
A37: Penambahan Portfolio SBN AC/HTM pada transaksi OM | B37: 1 | C37: 1 | D37: 1 | E37: 1 | F37: 1 | G37: 1 | H37: 1 | I37: 1 | J37: 1 | K37: 1 | L37: 1 | M37: 1
A38: Reopening SRBI - Tahap 2 (Searchable collateral) | B38: 1 | C38: 1 | D38: 1 | E38: 1 | F38: 1 | G38: 1 | H38: 1 | I38: 1 | J38: 1 | K38: 1 | L38: 1 | M38: 1
A39: Penerbitan Bank Indonesia Floating Rate Note (BI-FRN) | B39: 1 | C39: 1 | D39: 1 | E39: 1 | F39: 1 | G39: 1 | H39: 1 | I39: 1 | J39: 1 | K39: 1 | L39: 1 | M39: 1
A40: Perluasan investor SUKBI Non Bank | B40: 1 | C40: 1 | D40: 1 | E40: 1 | F40: 1 | G40: 1 | H40: 1 | I40: 1 | J40: 1 | K40: 1 | L40: 1 | M40: 1
A41: Transaksi DNDF Syariah melalui PDs | B41: 0 | C41: 0 | D41: 0 | E41: 0 | F41: 0 | G41: 0 | H41: 0 | I41: 0 | J41: 0 | K41: 0 | L41: 0 | M41: 0
A42: Integrasi BI-ETP dan CMS-OM | B42: 0 | C42: 0 | D42: 0 | E42: 0 | F42: 0 | G42: 0 | H42: 0 | I42: 0 | J42: 0 | K42: 0 | L42: 0 | M42: 0
A43: Securities Borrowing Lending BI | B43: 0 | C43: 0 | D43: 0 | E43: 0 | F43: 0 | G43: 0 | H43: 0 | I43: 0 | J43: 0 | K43: 0 | L43: 0 | M43: 0
B46: BI_WEB
B47: JAN | C47: FEB | D47: MAR | E47: APR | F47: MEI | G47: JUN | H47: JUL | I47: AUG | J47: SEP | K47: OCT | L47: NOV | M47: DEC
A48: 2025 | B48: =AVERAGE(B50:B51) -> 0.475 | C48: =AVERAGE(C50:C51) -> 0.5 | D48: =AVERAGE(D50:D51) -> 0.525 | E48: =AVERAGE(E50:E51) -> 0.55 | F48: =AVERAGE(F50:F51) -> 0.575 | G48: =AVERAGE(G50:G51) -> 0.5875 | H48: =AVERAGE(H50:H51) -> 0.625 | I48: =AVERAGE(I50:I51) -> 0.6375 | ... M48: =AVERAGE(M50:M51) -> 0.75
A49: 2026 | B49: =B48/$M$48 -> 0.63333333 | C49: =C48/$M$48 -> 0.66666667 | D49: =D48/$M$48 -> 0.7 | E49: =E48/$M$48 -> 0.73333333 | F49: =F48/$M$48 -> 0.76666667 | G49: =G48/$M$48 -> 0.78333333 | H49: =H48/$M$48 -> 0.83333333 | I49: =I48/$M$48 -> 0.85 | ... M49: =M48/$M$48 -> 1
A50: BI-WEB | B50: 0.65 | C50: 0.7 | D50: 0.75 | E50: 0.8 | F50: 0.85 | G50: 0.875 | H50: 0.95 | I50: 0.975 | J50: 1 | K50: 1 | L50: 1 | M50: 1
A51: BIMA | B51: 0.3 | C51: 0.3 | D51: 0.3 | E51: 0.3 | F51: 0.3 | G51: 0.3 | H51: 0.3 | I51: 0.3 | J51: 0.3 | K51: 0.375 | L51: 0.45 | M51: 0.5
B54: MHE-IS
B55: JAN | C55: FEB | D55: MAR | E55: APR | F55: MEI | G55: JUN | H55: JUL | I55: AUG | J55: SEP | K55: OCT | L55: NOV | M55: DEC
A56: 2025 | B56: =AVERAGE(B58:B64) -> 0.38714286 | C56: =AVERAGE(C58:C64) -> 0.43142857 | D56: =AVERAGE(D58:D64) -> 0.49714286 | E56: =AVERAGE(E58:E64) -> 0.55714286 | F56: =AVERAGE(F58:F64) -> 0.62857143 | G56: =AVERAGE(G58:G64) -> 0.66 | H56: =AVERAGE(H58:H64) -> 0.69571429 | I56: =AVERAGE(I58:I64) -> 0.74 | ... M56: =AVERAGE(M58:M64) -> 0.91428571
A57: 2026 | B57: =B56/$M$56 -> 0.4234375 | C57: =C56/$M$56 -> 0.471875 | D57: =D56/$M$56 -> 0.54375 | E57: =E56/$M$56 -> 0.609375 | F57: =F56/$M$56 -> 0.6875 | G57: =G56/$M$56 -> 0.721875 | H57: =H56/$M$56 -> 0.7609375 | I57: =I56/$M$56 -> 0.809375 | ... M57: =M56/$M$56 -> 1
A58: Surrounding MHE-IS: BI-SILK SPU | B58: 0.34 | C58: 0.38 | D58: 0.42 | E58: 0.45 | F58: 0.5 | G58: 0.54 | H58: 0.58 | I58: 0.62 | J58: 0.68 | K58: 0.75 | L58: 0.82 | M58: 0.85
A59: Surrounding MHE-IS: ERP SPU | B59: 0.34 | C59: 0.38 | D59: 0.42 | E59: 0.45 | F59: 0.5 | G59: 0.54 | H59: 0.58 | I59: 0.62 | J59: 0.68 | K59: 0.75 | L59: 0.82 | M59: 0.85
A60: Surrounding MHE-IS: SOA SPU | B60: 0.34 | C60: 0.38 | D60: 0.42 | E60: 0.45 | F60: 0.5 | G60: 0.54 | H60: 0.58 | I60: 0.62 | J60: 0.68 | K60: 0.75 | L60: 0.82 | M60: 0.85
A61: Surrounding MHE-IS: CBS SPU | B61: 0.34 | C61: 0.38 | D61: 0.42 | E61: 0.45 | F61: 0.5 | G61: 0.54 | H61: 0.58 | I61: 0.62 | J61: 0.68 | K61: 0.75 | L61: 0.82 | M61: 0.85
A62: Surrounding MHE-IS: BI-SILK DKU | B62: 0.45 | C62: 0.5 | D62: 0.6 | E62: 0.7 | F62: 0.8 | G62: 0.82 | H62: 0.85 | I62: 0.9 | J62: 0.92 | K62: 0.95 | L62: 1 | M62: 1
A63: Surrounding MHE-IS: ERP DKU | B63: 0.45 | C63: 0.5 | D63: 0.6 | E63: 0.7 | F63: 0.8 | G63: 0.82 | H63: 0.85 | I63: 0.9 | J63: 0.92 | K63: 0.95 | L63: 1 | M63: 1
A64: Surrounding MHE-IS: SOA DKU | B64: 0.45 | C64: 0.5 | D64: 0.6 | E64: 0.7 | F64: 0.8 | G64: 0.82 | H64: 0.85 | I64: 0.9 | J64: 0.92 | K64: 0.95 | L64: 1 | M64: 1
B66: DCP HRM
B67: JAN | C67: FEB | D67: MAR | E67: APR | F67: MEI | G67: JUN | H67: JUL | I67: AUG | J67: SEP | K67: OCT | L67: NOV | M67: DEC
A68: Multi | B68: 0.02 | C68: 0.03 | D68: 0.05 | E68: 0.07 | F68: 0.08 | G68: 0.1 | H68: 0.12 | I68: 0.13 | J68: 0.15 | K68: 0.2 | L68: 0.215 | M68: 0.23
A69: 2026 | B69: =B68/$M$68 -> 0.086956522 | C69: =C68/$M$68 -> 0.13043478 | D69: =D68/$M$68 -> 0.2173913 | E69: =E68/$M$68 -> 0.30434783 | F69: =F68/$M$68 -> 0.34782609 | G69: =G68/$M$68 -> 0.43478261 | H69: =H68/$M$68 -> 0.52173913 | I69: =I68/$M$68 -> 0.56521739 | ... M69: =M68/$M$68 -> 1
B71: DCP DCP Integrasi HRM
B72: JAN | C72: FEB | D72: MAR | E72: APR | F72: MEI | G72: JUN | H72: JUL | I72: AUG | J72: SEP | K72: OCT | L72: NOV | M72: DEC
A73: Multi | B73: 0.02 | C73: 0.03 | D73: 0.05 | E73: 0.07 | F73: 0.08 | G73: 0.1 | H73: 0.12 | I73: 0.13 | J73: 0.15 | K73: 0.2 | L73: 0.215 | M73: 0.23
A74: 2026 | B74: =B73/$M$68 -> 0.086956522 | C74: =C73/$M$68 -> 0.13043478 | D74: =D73/$M$68 -> 0.2173913 | E74: =E73/$M$68 -> 0.30434783 | F74: =F73/$M$68 -> 0.34782609 | G74: =G73/$M$68 -> 0.43478261 | H74: =H73/$M$68 -> 0.52173913 | I74: =I73/$M$68 -> 0.56521739 | ... M74: =M73/$M$68 -> 1

Sheet SIT Deliverables
B1: ON PROGRESS DEVELOPMENT | F1: GOLIVE | I1: NEED TO DISCUSS | K1: PERLU DISKUSI
I2: TAKOUT BECAUSE MHE IS
A3: No | B3: Kode Proyek | C3: Nama Proyek | D3: Nama Deliverables | E3: Proyek (Sub Proyek) | F3: Fungsi DPPT/DPU/DKEU-DSDM | G3: WO | H3: Size Proyek | I3: Target Implementasi | J3: % Penyelesaian Per Tahap | K3: PIC | L3: PLAN-SOLUSI SI | N3: PLAN-DESAIN | P3: PLAN-PENGEMBANGAN | R3: PLAN-PENGUJIAN SIT | T3: PLAN-PENGUJIAN UAT | V3: PLAN-IMPLEMENTASI | X3: Keterangan detail progres | Y3: PIC USER
A4: 1 | B4: P-54 | C4: ERPHRIS | D4: Pengeloaan Uang BI INV WMS | E4: Fungsi Penyesuaian Laporan Posisi Emas [DPPT] | F4: Fungsi DPPT | G4: WO-6 | H4: PPA | I4: 05-Des-25 | J4: 1 | K4: Trees | N4: 45915 | O4: 45926 | P4: 45929 | Q4: 24-Okt-25 | R4: 27-Okt-25 | S4: 45968 | T4: 45971 | U4: 45982 | V4: 45985 | W4: 05-Des-25 | X4: Sudah GOLIVE 03 Desember 2025 | Y4: Herry Prabowo DPU, Mutia Salsabila DPPT, Iip Latipudin DPU
A5: 2 | E5: Fungsi Penambahan Tipe Transaksi Data Emas Batanga | F5: Fungsi DPPT | H5: PPA | I5: 46094 | K5: Trees | N5: 46027 | O5: 46041 | P5: 46042 | Q5: 46055 | R5: 46056 | S5: 46066 | T5: 46071 | U5: 46085 | V5: 46086 | W5: 46094 | X5: Di Setting oleh DLDS untuk tipe setup an (Tidak masuk WO) | Y5: Herry Prabowo DPU, Mutia Salsabila DPPT, Iip Latipudin DPU
A7: 3 | E7: Fungsi Verifikasi Data Emas Batangan Bank Indonesia (Diskusi dengan DPPT saat pembahasan RPP setelah WO terbit untuk membahas memo pengadaan perangkat ke DLDS) | F7: Fungsi DPPT | G7: WO-9 | H7: PPA | I7: 46136 | K7: Trees | N7: 46027 | O7: 46041 | P7: 46042 | Q7: 46080 | R7: 46083 | S7: 46094 | T7: 46111 | U7: 46122 | V7: 46125 | W7: 46136 | X7: Melihat kondisi ketersediaan perangkat | Y7: Herry Prabowo DPU, Mutia Salsabila DPPT, Iip Latipudin DPU
A10: 4 | E10: Laporan Kapasitas Khazanah [DPU] | F10: Fungsi DPU | G10: WO-6 | H10: PPA | I10: 19-Des-25 | J10: 100`% | K10: Trees | N10: 45901 | O10: 45919 | P10: 45922 | Q10: 45968 | R10: 45971 | S10: 45982 | T10: 45985 | U10: 46009 | V10: 19-Des-25 | W10: 19-Des-25 | X10: Sudah GOLIVE 19 Des 2025 | Y10: Herry Prabowo DPU, Mutia Salsabila DPPT, Iip Latipudin DPU
A11: 5 | E11: Pengiriman Data Inventory | F11: Fungsi DPU | G11: WO-6 | H11: PPA | I11: 24-Okt-25 | J11: 1 | K11: Trees | N11: 45901 | O11: 45912 | P11: 45908 | Q11: 45930 | R11: 45931 | S11: 07-Okt-25 | T11: 13-Okt-25 | U11: Plan 1: 17-Okt-25 | V11: Plan 1: 20-Okt-25 | W11: Plan 1 : 07/11/2025 | X11: Sudah GOLIVE M1 Nov 2025 | Y11: Herry Prabowo DPU, Mutia Salsabila DPPT, Iip Latipudin DPU
E12: Kas Harian dan Kas Titipan Ke BISILK Secara Periodik [DPU] | U12: Realisasi : 31-Okt-25 | V12: Plan 2: 13-Okt-25 | W12: Realisasi :
V13: Realisasi :
A14: 6 | E14: Penonaktifan Fitur Transact | F14: Fungsi DPU | G14: Dibuat WO-8 Karena 2026 Fokus ke MHE IS | H14: PPA | I14: 46234 | K14: Trees | N14: 46055 | O14: 46112 | P14: 46113 | Q14: 46142 | R14: 46143 | S14: 46171 | T14: 46174 | U14: 46203 | V14: 46204 | W14: 46234 | Y14: Herry Prabowo DPU, Mutia Salsabila DPPT, Iip Latipudin DPU
A18: 7 | E18: Proses Penyimpanan Uang Rupiah dan/atau Barang Titipan Ke Khazanah Bank Indonesia | F18: Fungsi DPU | G18: Dibuat WO-8 Karena 2026 Fokus ke MHE IS | H18: PPA | I18: 46234 | K18: Trees | N18: 46055 | O18: 46112 | P18: 46113 | Q18: 46142 | R18: 46143 | S18: 46171 | T18: 46174 | U18: 46203 | V18: 46204 | W18: 46234 | Y18: Herry Prabowo DPU, Mutia Salsabila DPPT, Iip Latipudin DPU
A22: 8 | E22: Fungsi Laporan Pada Proses Pengelolaan Uang Rupiah Di Khazanah Bank Indonesia yang menggunakan Sistem Informasi ASRS | F22: Fungsi DPU | G22: Dibuat WO-8 Karena 2026 Fokus ke MHE IS | H22: PPA | I22: 46295 | K22: Trees | N22: 46113 | O22: 46142 | P22: 46132 | Q22: 46203 | R22: 46204 | S22: 46234 | T22: 46237 | U22: 46265 | V22: 46266 | W22: 46295 | Y22: Herry Prabowo DPU, Mutia Salsabila DPPT, Iip Latipudin DPU
A26: 9 | E26: Proses Pengambilan atau Penyimpanan Uang dan/atau Barang Titipan Dalam Rangka Stok Opname | F26: Fungsi DPU | G26: Dibuat WO-8 Karena 2026 Fokus ke MHE IS | H26: PPA | I26: 46295 | K26: Trees | N26: 46113 | O26: 46142 | P26: 46132 | Q26: 46203 | R26: 46204 | S26: 46234 | T26: 46237 | U26: 46265 | V26: 46266 | W26: 46295 | Y26: Herry Prabowo DPU, Mutia Salsabila DPPT, Iip Latipudin DPU
A31: 1 | B31: P-54 | C31: ERPHRIS | D31: Pengelolaan Keuangan BI (Prioritas 1 Tahap 1) | E31: Skema Import Pelaporan XML (FUNC.01.001) | F31: Fungsi DKEU (Fungsi DSDM) | G31: WO-6 | H31: PPA | I31: 45989 | J31: 1 | K31: Trees | N31: 45901 | O31: 45912 | P31: 45915 | Q31: 45954 | R31: 45957 | S31: 45968 | T31: 45971 | U31: 45982 | V31: 45985 | W31: 45989 | X31: Sudah GOLIVE 27 Nov 2025 | Y31: Diona DKEU
E32: Penyesuaian Laporan anlias Akun dan Penyesuaian WEB ADI (FUNC.01.003) | F32: Fungsi DKEU | G32: WO-6 | H32: PPA | I32: 46003 | J32: 1 | K32: Trees | N32: 45915 | O32: 45926 | P32: 45929 | Q32: 45968 | R32: 45971 | S32: 45982 | T32: 45985 | U32: 45996 | V32: 45999 | W32: 46003 | X32: Sudah GOLIVE 10 Des 2025 | Y32: Diona DKEU
E33: Laporan Monitoring Rekening Antara – Laporan Pemantauan Detail Transaksi Utang kepada Pegawai/Non Pegawai 441202 (FUNC.01.004) | F33: Fungsi DKEU | G33: WO-6 | H33: PPA | I33: 46003 | J33: 1 | K33: Trees | N33: 45908 | O33: 45919 | P33: 45922 | Q33: 45968 | R33: 45971 | S33: 45982 | T33: 45985 | U33: 45996 | V33: 45999 | W33: 46003 | X33: Sudah GOLIVE 10 Des 2025 | Y33: Diona DKEU
E34: Laporan Natura (FUNC.01.005) | F34: Fungsi DKEU | G34: WO-6 | H34: PPA | I34: 45996 | J34: 1 | K34: Trees | N34: 45929 | O34: 45940 | P34: 45943 | Q34: 45989 | R34: 45992 | S34: 46001 | T34: 46002 | U34: 46010 | V34: 46013 | W34: 46022 | X34: Sudah GOLIVE 30 Des 2025 | Y34: Diona DKEU
E35: Validasi Reclass Modul FA (FUNC.01.006) | F35: Fungsi DKEU (Fungsi DPRN) | G35: WO-6 | H35: PPA | I35: 45989 | J35: 1 | K35: Trees | N35: 45915 | O35: 45926 | P35: 45929 | Q35: 45954 | R35: 45957 | S35: 45968 | T35: 45971 | U35: 45982 | V35: 45985 | W35: 45989 | X35: Sudah GOLIVE 26 Nov 2025 | Y35: Diona DKEU
A36: 2 | B36: P-54 | C36: ERPHRIS | D36: Laporan Remunerasi BI (Prioritas 1) | E36: Pemenuhan Internal | F36: Fungsi DSDM | G36: WO-6 | H36: PPA | I36: 05 Des 25 | J36: 1 | K36: Trees | N36: 45901 | O36: 45905 | P36: 45908 | Q36: 45961 | R36: 45964 | S36: 45975 | T36: 45978 | U36: 45989 | V36: 01 Des 25 | W36: 05 Des 25 | X36: Sudah GOLIVE 01 Des 2025 | Y36: Jihan DSDM
E37: (FUNC.PI.001, FUNC.PI.002, FUNC.PI.005, FUNC.PI.006, FUNC.PI.007, FUNC.PI.008, dan FUNC.PI.009)
E38: Penyesuaian Pembayaran Travel dan Gaji Melalui BI-FAST dan RTGS (FUNC.FAST.001) | F38: Fungsi DSDM | G38: WO-6 | H38: PPA | I38: 45954 | J38: 1 | K38: Trees | N38: 45901 | O38: 45905 | P38: 45908 | Q38: 45936 | R38: 45938 | S38: 45944 | T38: 45944 | U38: 45947 | V38: 45950 | W38: 45954 | X38: Sudah GOLIVE 24 Okt 2025 | Y38: Jihan DSDM
E39: Penyesuaian Perhitungan Pajak Penghasilan (PPh 21) Pegawai dan BSBI (FUNC.TAX.001, FUNC.TAX.002, FUNC.TAX.004) | F39: Fungsi DSDM | G39: WO-6 | H39: PPA | I39: 45996 | J39: 1 | K39: Trees | N39: 45901 | O39: 45905 | P39: 45908 | Q39: 45961 | R39: 45964 | S39: 45975 | T39: 45978 | U39: 45989 | V39: 45992 | W39: 45996 | X39: Sudah GOLIVE 05 Des 2025 | Y39: Jihan DSDM
A40: 3 | B40: P-61 | C40: LMS-BI | D40: Integrasi LMS | E40: Integrasi LMS dengan ERPHRIS | F40: Fungsi DSDM | G40: WO-6 | H40: PPA | I40: 45996 | J40: 1 | K40: Trees | N40: 45901 | O40: 45912 | P40: 45908 | Q40: Plan 1: 31/10/2025 | R40: Plan 1 : 03/11/2025 | S40: Plan 1 :14/11/2025 | T40: Plan 1: 17/11/2025 | U40: 45989 | V40: 45992 | W40: 45996 | X40: Sudah GOLIVE 11 Des 2025 | Y40: Jihan DSDM
Q41: Realisasi : 11/11/2025 | R41: Plan 2[Proposed by Hafizh] : 11/11/2025 | S41: Plan 2 [Proposed by Hafizh] : 21/11/2025 | T41: Plan 2 [Proposed by Hafizh] : 21/11/2025
A43: 1 | B43: P-54 | C43: ERPHRIS | D43: Pengelolaan Keuangan BI (Prioritas 1 Tahap 2) | E43: Pertanggungjawaban Uang Muka | F43: Fungsi DKEU | G43: WO-9 | H43: PPA | I43: 46129 | K43: Trees | N43: 45931 | O43: 45989 | P43: 45992 | Q43: 46073 | R43: 46076 | S43: 46087 | T43: 46090 | U43: 46114 | V43: 46118 | W43: 46129 | X43: Subject to discuss ke DKEU terkait | Y43: Diona DKEU
X44: fitur Cancellation VA sebelum
X45: Desain Selesai ;
X46: 1. Pembahasan internal dulu dengan CBS (Dalam minggu ini sebelum M4 Nov 2025)
X47: 2. Pembahasan dengan DKEU (Dalam minggu ini, sebelum M4 Nov 2025)
E49: Penyesuaian Laporan Detail Kesesuaian Natural Akun Penyusutan | F49: Fungsi DKEU | G49: WO-9 | H49: PPA | I49: 46129 | K49: Trees | N49: 46027 | O49: 46037 | P49: 46041 | Q49: 46073 | R49: 46076 | S49: 46087 | T49: 46090 | U49: 46114 | V49: 46118 | W49: 46129 | Y49: Diona DKEU
E50: Laporan Rekapitulasi Bulanan Aktiva Tetap yang Belum Dilakukan Penyusutan | F50: Fungsi DKEU | G50: WO-9 | H50: PPA | I50: 46122 | K50: Trees | N50: 46006 | O50: 46031 | P50: 46034 | Q50: 46066 | R50: 46069 | S50: 46080 | T50: 46083 | U50: 46108 | V50: 46111 | W50: 46122 | Y50: Diona DKEU
E51: Laporan monitoring Status Receipt | F51: Fungsi DKEU | G51: WO-9 | H51: PPA | I51: 46129 | K51: Trees | N51: 46027 | O51: 46037 | P51: 46041 | Q51: 46073 | R51: 46076 | S51: 46087 | T51: 46090 | U51: 46114 | V51: 46118 | W51: 46129 | Y51: Diona DKEU
E52: Laporan monitoring Account Receivable | F52: Fungsi DKEU | G52: WO-9 | H52: PPA | I52: 46122 | K52: Trees | N52: 46006 | O52: 46031 | P52: 46034 | Q52: 46066 | R52: 46069 | S52: 46080 | T52: 46083 | U52: 46108 | V52: 46111 | W52: 46122 | Y52: Diona DKEU
A53: 2 | B53: P-54 | C53: ERPHRIS | D53: Pengelolaan Keuangan BI (Prioritas 2) | E53: Pop Up Message untuk BI-FAST saat Pendaftaran Vendor | F53: Fungsi DKEU | G53: TBC | H53: PPA | I53: 46241 | K53: Trees | N53: 46125 | O53: 46136 | P53: 46139 | Q53: 46206 | R53: 46209 | S53: 46220 | T53: 46223 | U53: 46234 | V53: 46237 | W53: 46241 | Y53: Diona DKEU
E54: Upload PPN atas transaksi RTGS, BI-SSSS, BI-ETP, SKNBI dan BI-FAST | F54: Fungsi DKEU | G54: TBC | H54: PPA | I54: 46290 | K54: Trees | N54: 46153 | O54: 46171 | P54: 46175 | Q54: 46248 | R54: 46252 | S54: 46262 | T54: 46265 | U54: 46283 | V54: 46286 | W54: 46290 | Y54: Diona DKEU
E55: Laporan Pemantauan Pembukuan Jurnal Manual/Web ADI | F55: Fungsi DKEU | G55: TBC | H55: PPA | I55: 46241 | K55: Trees | N55: 46125 | O55: 46136 | P55: 46139 | Q55: 46206 | R55: 46209 | S55: 46220 | T55: 46223 | U55: 46234 | V55: 46237 | W55: 46241 | Y55: Diona DKEU
E56: Enhancement Jurnal Recurring | F56: Fungsi DKEU | G56: TBC | H56: PPA | I56: 46255 | K56: Trees | N56: 46139 | O56: 46150 | P56: 46153 | Q56: 46220 | R56: 46223 | S56: 46234 | T56: 46237 | U56: 46248 | V56: 46252 | W56: 46255 | Y56: Diona DKEU
E57: Enhancement Penyelesaian Transaksi Keuangan Terkait Validasi Debit Memo | F57: Fungsi DKEU | G57: TBC | H57: PPA | I57: 46290 | K57: Trees | N57: 46153 | O57: 46171 | P57: 46175 | Q57: 46248 | R57: 46252 | S57: 46262 | T57: 46265 | U57: 46283 | V57: 46286 | W57: 46290 | Y57: Diona DKEU
E58: Laporan Monitoring Detail Cadangan Tujuan dan Laporan Tidak Membuku | F58: Fungsi DKEU | G58: TBC | H58: PPA | I58: 46290 | K58: Trees | N58: 46153 | O58: 46171 | P58: 46175 | Q58: 46248 | R58: 46252 | S58: 46262 | T58: 46265 | U58: 46283 | V58: 46286 | W58: 46290 | Y58: Diona DKEU
E59: Filtering, Sorting, dan Searching Worklist untuk Perintah Bayar pada user approval | F59: Fungsi DKEU | G59: TBC | H59: PPA | I59: 46255 | K59: Trees | N59: 46139 | O59: 46150 | P59: 46153 | Q59: 46220 | R59: 46223 | S59: 46234 | T59: 46237 | U59: 46248 | V59: 46252 | W59: 46255 | Y59: Diona DKEU
E60: Laporan Realisasi Anggaran BI-Wide dan LRA Detail per Satker | F60: Fungsi DKEU | G60: TBC | H60: PPA | I60: 46269 | K60: Trees | N60: 46146 | O60: 46164 | P60: 46167 | Q60: 46234 | R60: 46237 | S60: 46248 | T60: 46252 | U60: 46262 | V60: 46265 | W60: 46269 | Y60: Diona DKEU
E61: Laporan Progres Penyelesaian Aset | F61: Fungsi DKEU | G61: TBC | H61: PPA | I61: 46269 | K61: Trees | N61: 46146 | O61: 46164 | P61: 46167 | Q61: 46234 | R61: 46237 | S61: 46248 | T61: 46252 | U61: 46262 | V61: 46265 | W61: 46269 | Y61: Diona DKEU
A62: 3 | B62: P-54 | C62: ERPHRIS | D62: Laporan Remunerasi BI (Prioritas 2) | E62: Pemenuhan Internal (Func 3-4) | F62: Fungsi DSDM | G62: WO-9 | H62: PPA | I62: 46087 | K62: Trees | N62: 45992 | O62: 46003 | P62: 45999 | Q62: 46052 | R62: 46055 | S62: 46066 | T62: 46069 | U62: 46080 | V62: 46083 | W62: 46087 | Y62: Jihan DSDM
E63: Kompetensi (Func 2-3) | F63: Fungsi DSDM | G63: WO-9 | H63: PPA | I63: 46087 | K63: Trees | N63: 46028 | O63: 46038 | P63: 46028 | Q63: 46052 | R63: 46055 | S63: 46066 | T63: 46069 | U63: 46080 | V63: 46084 | W63: 46087 | Y63: Jihan DSDM
E64: Uang Muka Travel | F64: Fungsi DSDM | G64: WO-9 | H64: PPA | I64: 46122 | K64: Trees | N64: 45931 | O64: 45989 | P64: 46041 | Q64: 46073 | R64: 46076 | S64: 46087 | T64: 46090 | U64: 46114 | V64: 46118 | W64: 46122 | Y64: Jihan DSDM
E65: Pajak BSBI (Func 3 dan 5-7) | F65: Fungsi DSDM | G65: WO-9 | H65: PPA | I65: 46073 | K65: Trees | N65: 46023 | O65: 46031 | P65: 46027 | Q65: 46052 | R65: 46055 | S65: 46059 | T65: 46062 | U65: 46066 | V65: 46069 | W65: 46073 | Y65: Jihan DSDM
E66: Payslip PHDP | F66: Fungsi DSDM | G66: WO-9 | H66: PPA | I66: 46112 | K66: Trees | N66: 46069 | O66: 46073 | P66: 46076 | Q66: 46087 | R66: 46090 | S66: 46098 | T66: 46111 | U66: 46122 | V66: 46125 | W66: 46127 | Y66: Jihan DSDM
A68: 1 | B68: P-54 | C68: ERPHRIS | D68: Pengelolaan Keuangan BI (Prioritas 3) | E68: Laporan Face RPCT dan Mutasi CT | F68: Fungsi DKEU | G68: TBC | H68: PPA | I68: 46535 | K68: Trees | N68: 46300 | O68: 46325 | P68: 46328 | Q68: 46444 | R68: 46447 | S68: 46479 | T68: 46482 | U68: 46507 | V68: 46510 | W68: 46535 | Y68: Diona DKEU
E69: Enhancement Laporan Status Pembayaran | F69: Fungsi DKEU | G69: TBC | H69: PPA | I69: 46535 | K69: Trees | N69: 46300 | O69: 46325 | P69: 46328 | Q69: 46444 | R69: 46447 | S69: 46479 | T69: 46482 | U69: 46507 | V69: 46510 | W69: 46535 | Y69: Diona DKEU
E70: Laporan Pemantauan Penyelesaian Transaksi Keuangan - Detil | F70: Fungsi DKEU | G70: TBC | H70: PPA | I70: 46535 | K70: Trees | N70: 46300 | O70: 46325 | P70: 46328 | Q70: 46444 | R70: 46447 | S70: 46479 | T70: 46482 | U70: 46507 | V70: 46510 | W70: 46535 | Y70: Diona DKEU
E71: Laporan Pemantauan Penyelesaian Transaksi Keuangan - Summary | F71: Fungsi DKEU | G71: TBC | H71: PPA | I71: 46535 | K71: Trees | N71: 46300 | O71: 46325 | P71: 46328 | Q71: 46444 | R71: 46447 | S71: 46479 | T71: 46482 | U71: 46507 | V71: 46510 | W71: 46535 | Y71: Diona DKEU
E72: Laporan Monitoring Invoice | F72: Fungsi DKEU | G72: TBC | H72: PPA | I72: 46535 | K72: Trees | N72: 46300 | O72: 46325 | P72: 46328 | Q72: 46444 | R72: 46447 | S72: 46479 | T72: 46482 | U72: 46507 | V72: 46510 | W72: 46535 | Y72: Diona DKEU
E73: Cetak Perintah Bayar | F73: Fungsi DKEU | G73: TBC | H73: PPA | I73: 46535 | K73: Trees | N73: 46300 | O73: 46325 | P73: 46328 | Q73: 46444 | R73: 46447 | S73: 46479 | T73: 46482 | U73: 46507 | V73: 46510 | W73: 46535 | Y73: Diona DKEU
E74: Pendaftaran Akun Anggaran oleh Satker Pemilik Akun Anggaran | F74: Fungsi DKEU | G74: TBC | H74: PPA | I74: 46535 | K74: Trees | N74: 46300 | O74: 46325 | P74: 46328 | Q74: 46444 | R74: 46447 | S74: 46479 | T74: 46482 | U74: 46507 | V74: 46510 | W74: 46535 | Y74: Diona DKEU
E75: Enhancement Bukti Advis Rekanan | F75: Fungsi DKEU | G75: TBC | H75: PPA | I75: 46535 | K75: Trees | N75: 46300 | O75: 46325 | P75: 46328 | Q75: 46444 | R75: 46447 | S75: 46479 | T75: 46482 | U75: 46507 | V75: 46510 | W75: 46535 | Y75: Diona DKEU
E76: Penguncian Postur ATBI PCTBI | F76: Fungsi DKEU | G76: TBC | H76: PPA | I76: 46387 | K76: Trees | N76: 46143 | O76: 46171 | P76: 46174 | Q76: 46295 | R76: 46296 | S76: 46325 | T76: 46328 | U76: 46356 | V76: 46357 | W76: 46387 | Y76: Diona DKEU
A77: 2 | B77: P-54 | C77: ERPHRIS | D77: Laporan Remunerasi BI (Prioritas 3) | E77: Kompetensi (Func 1, 4, dan 5) | F77: Fungsi DSDM | G77: TBC | H77: PPA | I77: 46213 | K77: Trees | N77: 46113 | O77: 46129 | P77: 46125 | Q77: 46178 | R77: 46181 | S77: 46192 | T77: 46195 | U77: 46206 | V77: 46209 | W77: 46213 | Y77: Jihan DSDM
E78: Uang Perpisahan PKWT | F78: Fungsi DSDM | G78: TBC | H78: PPA | I78: 46157 | K78: Trees | N78: 46113 | O78: 46122 | P78: 46125 | Q78: 46136 | R78: 46139 | S78: 46142 | T78: 46146 | U78: 46150 | V78: 46153 | W78: 46157 | Y78: Jihan DSDM
E79: Tunjangan Kacamata | F79: Fungsi DSDM | G79: TBC | H79: PPA | I79: 46234 | K79: Trees | N79: 46167 | O79: 46178 | P79: 46175 | Q79: 46199 | R79: 46202 | S79: 46213 | T79: 46216 | U79: 46227 | V79: 46230 | W79: 46234 | Y79: Jihan DSDM
E80: Time Management (WFH WFO) | F80: Fungsi DSDM | G80: TBC | H80: PPA | I80: 46265 | K80: Trees | N80: 46188 | O80: 46199 | P80: 45830 | Q80: 46227 | R80: 46230 | S80: 46241 | T80: 46244 | U80: 46255 | V80: 46258 | W80: 46265 | Y80: Jihan DSDM
E81: Hak dan Kewajiban | F81: Fungsi DSDM | G81: TBC | H81: PPA | I81: 46171 | K81: Trees | N81: 46118 | O81: 46129 | P81: 46125 | Q81: 46150 | R81: 46153 | S81: 46157 | T81: 46160 | U81: 46164 | V81: 46167 | W81: 46171 | Y81: Jihan DSDM
E82: CV | F82: Fungsi DSDM | G82: TBC | H82: PPA | I82: 46164 | K82: Trees | N82: 46113 | O82: 46122 | P82: 46118 | Q82: 46143 | R82: 46146 | S82: 46150 | T82: 46153 | U82: 46157 | V82: 46160 | W82: 46164 | Y82: Jihan DSDM
E83: Demosi | F83: Fungsi DSDM | G83: TBC | H83: PPA | I83: 46192 | K83: Trees | N83: 46146 | O83: 46150 | P83: 46153 | Q83: 46171 | R83: 46175 | S83: 46178 | T83: 46181 | U83: 46185 | V83: 46188 | W83: 46192 | Y83: Jihan DSDM
E84: Alter Date Cuti | F84: Fungsi DSDM | G84: TBC | H84: PPA | I84: 46269 | K84: Trees | N84: 46230 | O84: 46234 | P84: 46237 | Q84: 46248 | R84: 46252 | S84: 46255 | T84: 46258 | U84: 46262 | V84: 46234 | W84: 46269 | Y84: Jihan DSDM
A86: 1 | B86: P-49 | C86: SIMODIS | D86: Penyesuaian Revisi PP 8 Tahun 2025 | E86: Tahap 1a | N86: 46044 | O86: 46050 | P86: 46051 | Q86: 46066 | R86: 46071 | S86: 46077 | T86: 46072 | U86: 46078 | V86: 46079 | W86: 46080
E87: Tahap 1b | N87: 46044 | O87: 46050 | P87: 46083 | Q87: 46112 | R87: 46113 | S87: 46120 | T87: 46121 | U87: 46127 | V87: 46128 | W87: 46129

Sheet Sheet2
A1: Start Proyek | B1: (Multiple Items)
A2: End Proyek | B2: (Multiple Items)
A4: Row Labels | B4: Count of Deliverables (Sub Proyek)
A5: Market | B5: 16
A6: Market, SP | B6: 1
A7: Market, SSK | B7: 1
A8: MD | B8: 2
A9: MI | B9: 28
A10: MI, SP | B10: 1
A11: Moneter | B11: 14
A12: Moneter, Market | B12: 3
A13: Moneter, SSK | B13: 1
A14: SP | B14: 8
A15: SSK | B15: 11
A16: Grand Total | B16: 86

Sheet Proyek
A1: dashboard | B1: PT | C1: Pilar RIVIBI | D1: Kategori | E1: No | F1: No. Sub | G1: Nama Proyek | H1: Nama Proyek Baru | I1: Deliverables (Sub Proyek) | J1: Start Proyek | K1: End Proyek | L1: Stratifikasi Aset | M1: Leveling Aset TD | N1: DMP RBT | O1: PIC Satker | P1: Portofolio | Q1: Stream | R1: Aplikasi | S1: Tahapan | T1: Progress | U1: PM | V1: % Penyelesaian | W1: Target RBT | X1: Target Implementasi | Y1: KAK | Z1: Revisit | AA1: RBT | AC1: RPP | AE1: KAK/WO | AG1: PENGADAAN-DMAP | AI1: DESAIN | AK1: PENGEMBANGAN | AM1: PENGUJIAN-SIT | AO1: PENGUJIAN-UAT | AQ1: IMPLEMENTASI | AS1: Deskripsi target | BE1: Persen Target (JANGAN DI ISI) | BQ1: Deskripsi Realisasi | CC1: Persen Realisasi | CO1: Capaian | DA1: Status Proyek | DM1: Progres terhadap 2026 | DY1: % PROGRESS MILESTONE | EH1: Keterangan detail progres | EI1: Tanggal Real Implementasi | EJ1: Target Implementasi | EK1: Tanggal RBT | EL1: Tanggal Kick Off | EM1: Tanggal Project Closure | EN1: Lesson Learned | EO1: Penjelasan dan Isu | FA1: Rencana Tindak Lanjut | FM1: PIC KMBD | FN1: PIC PM | FO1: PIC KMPPD | FP1: PIC KPPA | FQ1: PIC PKLD | FR1: Metode Pengembangan | FS1: Vendor | FT1: Ket THOS | FU1: Total
A2: Column1 | B2: Column2 | C2: Column3 | D2: Column4 | E2: Column5 | F2: Column6 | G2: Column7 | I2: Column8 | J2: Column9 | K2: Column10 | L2: Column11 | M2: Column12 | N2: Column13 | O2: Column14 | P2: Column15 | Q2: Column16 | R2: Column17 | S2: Column18 | T2: Column19 | V2: Column20 | W2: Column21 | X2: Column22 | Y2: Column23 | AA2: Start | AB2: End | AC2: Start | AD2: End | AE2: Start | AF2: End | AG2: Start | AH2: End | AI2: Start | AJ2: End | AK2: Start | AL2: End | AM2: Start | AN2: End | AO2: Start | AP2: End | AQ2: Start | AR2: End | AS2: JAN | AT2: FEB | AU2: MAR | AV2: APR | AW2: MEI | AX2: JUN | AY2: JUL | AZ2: AUG | BA2: SEP | BB2: OCT | BC2: NOV | BD2: DEC | BE2: JAN | BF2: FEB | BG2: MAR | BH2: APR | BI2: MEI | BJ2: JUN | BK2: JUL | BL2: AUG | BM2: SEP | BN2: OCT | BO2: NOV | BP2: DEC | BQ2: JAN | BR2: FEB | BS2: MAR | BT2: APR | BU2: MEI | BV2: JUN | BW2: JUL | BX2: AUG | BY2: SEP | BZ2: OCT | CA2: NOV | CB2: DEC | CC2: JAN | CD2: FEB | CE2: MAR | CF2: APR | CG2: MEI | CH2: JUN | CI2: JUL | CJ2: AUG | CK2: SEP | CL2: OCT | CM2: NOV | CN2: DEC | CO2: JAN | CP2: FEB | CQ2: MAR | CR2: APR | CS2: MEI | CT2: JUN | CU2: JUL | CV2: AUG | CW2: SEP | CX2: OCT | CY2: NOV | CZ2: DEC | DA2: JAN | DB2: FEB | DC2: MAR | DD2: APR | DE2: MEI | DF2: JUN | DG2: JUL | DH2: AUG | DI2: SEP | DJ2: OCT | DK2: NOV | DL2: DEC | DM2: JAN | DN2: FEB | DO2: MAR | DP2: APR | DQ2: MEI | DR2: JUN | DS2: JUL | DT2: AUG | DU2: SEP | DV2: OCT | DW2: NOV | DX2: DEC | DY2: RBT | DZ2: RPP | EA2: KAK/WO | EB2: PENGADAAN | EC2: DESAIN | ED2: PENGEMBANGAN | EE2: SIT | EF2: UAT | EG2: IMP | EH2: 1 | EI2: Column139 | EJ2: Column140 | EL2: Column141 | EM2: Column142 | EN2: Column143 | EO2: Jan | EP2: Feb | EQ2: Mar | ER2: Apr | ES2: Mei | ET2: Jun | EU2: Jul | EV2: Ags | EW2: Sep | EX2: Okt | EY2: Nov | EZ2: Des | FA2: Jan | FB2: Feb | FC2: Mar | FD2: Apr | FE2: Mei | FF2: Jun | FG2: Jul | FH2: Ags | FI2: Sep | FJ2: Okt | FK2: Nov | FL2: Des | FM2: Column193 | FN2: Column194 | FO2: Column194 | FP2: Column195 | FR2: Column196 | FS2: Column197 | FT2: Column198 | FU2: Column198
B3: PT03 | C3: IDPS | E3: P-1 | F3: 3 | G3: BI-FAST | H3: New BI-FAST | I3: Enhancement Aplikasi Legacy New BI-FAST | J3: 2025 | K3: 2028 | L3: S | M3: K3 | N3: Pemimpin Satker | O3: DKeu, DKSP, DPSP, DLDS | P3: WG-1 | Q3: SP, MI | R3: ERPHRIS, SOA | S3: =BQ3 -> Proses RBT-RBB | T3: =IF(V3=0%,"Not Started",IF(V3<100%,"On Progress",IF(V3=100%,"DONE"))) -> On Progress | U3: =FN3 -> Aldo Fernanda | V3: =CC3 -> 0.015 | W3: TW II 2026 | X3: =AR3 -> 47026 | Z3: New | AA3: 45962 | AB3: 46142 | AC3: 46143 | AD3: 46203 | AE3: 46174 | AF3: 46203 | AG3: 46204 | AH3: 46387 | AI3: 46388 | AJ3: 46446 | AK3: 46447 | AL3: 46811 | AM3: 46813 | AN3: 46904 | AO3: 46905 | AP3: 46996 | AQ3: 46997 | AR3: 47026 | AS3: =IF(BE3=0%,"Not Started",IF(BE3<5%,"Proses RBT-RBB",IF(BE3=5%,"Selesai RBT-RBB",IF(BE3<10%,"Proses RBT-RBL",IF(BE3=10%,"Selesai RBT-RBL",IF(BE3<15%,"Proses RBT-RBTD",IF(BE3=15%,"Selesai RBT-RBTD",IF(BE3<20%,"Proses RPP",IF(BE3=20%,"Selesai RPP",IF(BE3<25%,"Proses KAK",IF(BE3=25%,"Selesai KAK",IF(BE3<30%,"Proses Pengadaan",IF(BE3=30%,"Selesai Pengadaan",IF(BE3<45%,"Proses Desain",IF(BE3=45%,"Selesai Desain",IF(BE3<80%,"Proses Pengembangan",IF(BE3=80%,"Selesai Pengembangan",IF(BE3<87.5%,"Proses SIT",IF(BE3=87.5%,"Selesai SIT",IF(BE3<95%,"Proses UAT",IF(BE3=95%,"Selesai UAT",IF(BE3<100%,"Proses Implementasi","Selesai Implementasi")))))))))))))))))))))) -> Proses RBT-RBL | AT3: =IF(BF3=0%,"Not Started",IF(BF3<5%,"Proses RBT-RBB",IF(BF3=5%,"Selesai RBT-RBB",IF(BF3<10%,"Proses RBT-RBL",IF(BF3=10%,"Selesai RBT-RBL",IF(BF3<15%,"Proses RBT-RBTD",IF(BF3=15%,"Selesai RBT-RBTD",IF(BF3<20%,"Proses RPP",IF(BF3=20%,"Selesai RPP",IF(BF3<25%,"Proses KAK",IF(BF3=25%,"Selesai KAK",IF(BF3<30%,"Proses Pengadaan",IF(BF3=30%,"Selesai Pengadaan",IF(BF3<45%,"Proses Desain",IF(BF3=45%,"Selesai Desain",IF(BF3<80%,"Proses Pengembangan",IF(BF3=80%,"Selesai Pengembangan",IF(BF3<87.5%,"Proses SIT",IF(BF3=87.5%,"Selesai SIT",IF(BF3<95%,"Proses UAT",IF(BF3=95%,"Selesai UAT",IF(BF3<100%,"Proses Implementasi","Selesai Implementasi")))))))))))))))))))))) -> Proses RBT-RBL | AU3: =IF(BG3=0%,"Not Started",IF(BG3<5%,"Proses RBT-RBB",IF(BG3=5%,"Selesai RBT-RBB",IF(BG3<10%,"Proses RBT-RBL",IF(BG3=10%,"Selesai RBT-RBL",IF(BG3<15%,"Proses RBT-RBTD",IF(BG3=15%,"Selesai RBT-RBTD",IF(BG3<20%,"Proses RPP",IF(BG3=20%,"Selesai RPP",IF(BG3<25%,"Proses KAK",IF(BG3=25%,"Selesai KAK",IF(BG3<30%,"Proses Pengadaan",IF(BG3=30%,"Selesai Pengadaan",IF(BG3<45%,"Proses Desain",IF(BG3=45%,"Selesai Desain",IF(BG3<80%,"Proses Pengembangan",IF(BG3=80%,"Selesai Pengembangan",IF(BG3<87.5%,"Proses SIT",IF(BG3=87.5%,"Selesai SIT",IF(BG3<95%,"Proses UAT",IF(BG3=95%,"Selesai UAT",IF(BG3<100%,"Proses Implementasi","Selesai Implementasi")))))))))))))))))))))) -> Proses RBT-RBTD | AV3: =IF(BH3=0%,"Not Started",IF(BH3<5%,"Proses RBT-RBB",IF(BH3=5%,"Selesai RBT-RBB",IF(BH3<10%,"Proses RBT-RBL",IF(BH3=10%,"Selesai RBT-RBL",IF(BH3<15%,"Proses RBT-RBTD",IF(BH3=15%,"Selesai RBT-RBTD",IF(BH3<20%,"Proses RPP",IF(BH3=20%,"Selesai RPP",IF(BH3<25%,"Proses KAK",IF(BH3=25%,"Selesai KAK",IF(BH3<30%,"Proses Pengadaan",IF(BH3=30%,"Selesai Pengadaan",IF(BH3<45%,"Proses Desain",IF(BH3=45%,"Selesai Desain",IF(BH3<80%,"Proses Pengembangan",IF(BH3=80%,"Selesai Pengembangan",IF(BH3<87.5%,"Proses SIT",IF(BH3=87.5%,"Selesai SIT",IF(BH3<95%,"Proses UAT",IF(BH3=95%,"Selesai UAT",IF(BH3<100%,"Proses Implementasi","Selesai Implementasi")))))))))))))))))))))) -> Selesai RBT-RBTD | AW3: =IF(BI3=0%,"Not Started",IF(BI3<5%,"Proses RBT-RBB",IF(BI3=5%,"Selesai RBT-RBB",IF(BI3<10%,"Proses RBT-RBL",IF(BI3=10%,"Selesai RBT-RBL",IF(BI3<15%,"Proses RBT-RBTD",IF(BI3=15%,"Selesai RBT-RBTD",IF(BI3<20%,"Proses RPP",IF(BI3=20%,"Selesai RPP",IF(BI3<25%,"Proses KAK",IF(BI3=25%,"Selesai KAK",IF(BI3<30%,"Proses Pengadaan",IF(BI3=30%,"Selesai Pengadaan",IF(BI3<45%,"Proses Desain",IF(BI3=45%,"Selesai Desain",IF(BI3<80%,"Proses Pengembangan",IF(BI3=80%,"Selesai Pengembangan",IF(BI3<87.5%,"Proses SIT",IF(BI3=87.5%,"Selesai SIT",IF(BI3<95%,"Proses UAT",IF(BI3=95%,"Selesai UAT",IF(BI3<100%,"Proses Implementasi","Selesai Implementasi")))))))))))))))))))))) -> Proses RPP | AX3: =IF(BJ3=0%,"Not Started",IF(BJ3<5%,"Proses RBT-RBB",IF(BJ3=5%,"Selesai RBT-RBB",IF(BJ3<10%,"Proses RBT-RBL",IF(BJ3=10%,"Selesai RBT-RBL",IF(BJ3<15%,"Proses RBT-RBTD",IF(BJ3=15%,"Selesai RBT-RBTD",IF(BJ3<20%,"Proses RPP",IF(BJ3=20%,"Selesai RPP",IF(BJ3<25%,"Proses KAK",IF(BJ3=25%,"Selesai KAK",IF(BJ3<30%,"Proses Pengadaan",IF(BJ3=30%,"Selesai Pengadaan",IF(BJ3<45%,"Proses Desain",IF(BJ3=45%,"Selesai Desain",IF(BJ3<80%,"Proses Pengembangan",IF(BJ3=80%,"Selesai Pengembangan",IF(BJ3<87.5%,"Proses SIT",IF(BJ3=87.5%,"Selesai SIT",IF(BJ3<95%,"Proses UAT",IF(BJ3=95%,"Selesai UAT",IF(BJ3<100%,"Proses Implementasi","Selesai Implementasi")))))))))))))))))))))) -> Selesai RPP | AY3: =IF(BK3=0%,"Not Started",IF(BK3<5%,"Proses RBT-RBB",IF(BK3=5%,"Selesai RBT-RBB",IF(BK3<10%,"Proses RBT-RBL",IF(BK3=10%,"Selesai RBT-RBL",IF(BK3<15%,"Proses RBT-RBTD",IF(BK3=15%,"Selesai RBT-RBTD",IF(BK3<20%,"Proses RPP",IF(BK3=20%,"Selesai RPP",IF(BK3<25%,"Proses KAK",IF(BK3=25%,"Selesai KAK",IF(BK3<30%,"Proses Pengadaan",IF(BK3=30%,"Selesai Pengadaan",IF(BK3<45%,"Proses Desain",IF(BK3=45%,"Selesai Desain",IF(BK3<80%,"Proses Pengembangan",IF(BK3=80%,"Selesai Pengembangan",IF(BK3<87.5%,"Proses SIT",IF(BK3=87.5%,"Selesai SIT",IF(BK3<95%,"Proses UAT",IF(BK3=95%,"Selesai UAT",IF(BK3<100%,"Proses Implementasi","Selesai Implementasi")))))))))))))))))))))) -> Selesai KAK | AZ3: =IF(BL3=0%,"Not Started",IF(BL3<5%,"Proses RBT-RBB",IF(BL3=5%,"Selesai RBT-RBB",IF(BL3<10%,"Proses RBT-RBL",IF(BL3=10%,"Selesai RBT-RBL",IF(BL3<15%,"Proses RBT-RBTD",IF(BL3=15%,"Selesai RBT-RBTD",IF(BL3<20%,"Proses RPP",IF(BL3=20%,"Selesai RPP",IF(BL3<25%,"Proses KAK",IF(BL3=25%,"Selesai KAK",IF(BL3<30%,"Proses Pengadaan",IF(BL3=30%,"Selesai Pengadaan",IF(BL3<45%,"Proses Desain",IF(BL3=45%,"Selesai Desain",IF(BL3<80%,"Proses Pengembangan",IF(BL3=80%,"Selesai Pengembangan",IF(BL3<87.5%,"Proses SIT",IF(BL3=87.5%,"Selesai SIT",IF(BL3<95%,"Proses UAT",IF(BL3=95%,"Selesai UAT",IF(BL3<100%,"Proses Implementasi","Selesai Implementasi")))))))))))))))))))))) -> Proses Pengadaan | ... BD3: =IF(BP3=0%,"Not Started",IF(BP3<5%,"Proses RBT-RBB",IF(BP3=5%,"Selesai RBT-RBB",IF(BP3<10%,"Proses RBT-RBL",IF(BP3=10%,"Selesai RBT-RBL",IF(BP3<15%,"Proses RBT-RBTD",IF(BP3=15%,"Selesai RBT-RBTD",IF(BP3<20%,"Proses RPP",IF(BP3=20%,"Selesai RPP",IF(BP3<25%,"Proses KAK",IF(BP3=25%,"Selesai KAK",IF(BP3<30%,"Proses Pengadaan",IF(BP3=30%,"Selesai Pengadaan",IF(BP3<45%,"Proses Desain",IF(BP3=45%,"Selesai Desain",IF(BP3<80%,"Proses Pengembangan",IF(BP3=80%,"Selesai Pengembangan",IF(BP3<87.5%,"Proses SIT",IF(BP3=87.5%,"Selesai SIT",IF(BP3<95%,"Proses UAT",IF(BP3=95%,"Selesai UAT",IF(BP3<100%,"Proses Implementasi","Selesai Implementasi")))))))))))))))))))))) -> Selesai Pengadaan | BE3: 0.06 | BF3: 0.09 | BG3: 0.12 | BH3: 0.15 | BI3: 0.175 | BJ3: 0.2 | BK3: 0.25 | BL3: 0.26 | BM3: 0.27 | BN3: 0.28 | BO3: 0.29 | BP3: 0.3 | BQ3: =IF(CC3=0%,"Not Started",IF(CC3<5%,"Proses RBT-RBB",IF(CC3=5%,"Selesai RBT-RBB",IF(CC3<10%,"Proses RBT-RBL",IF(CC3=10%,"Selesai RBT-RBL",IF(CC3<15%,"Proses RBT-RBTD",IF(CC3=15%,"Selesai RBT-RBTD",IF(CC3<20%,"Proses RPP",IF(CC3=20%,"Selesai RPP",IF(CC3<25%,"Proses KAK",IF(CC3=25%,"Selesai KAK",IF(CC3<30%,"Proses Pengadaan",IF(CC3=30%,"Selesai Pengadaan",IF(CC3<45%,"Proses Desain",IF(CC3=45%,"Selesai Desain",IF(CC3<80%,"Proses Pengembangan",IF(CC3=80%,"Selesai Pengembangan",IF(CC3<87.5%,"Proses SIT",IF(CC3=87.5%,"Selesai SIT",IF(CC3<95%,"Proses UAT",IF(CC3=95%,"Selesai UAT",IF(CC3<100%,"Proses Implementasi","Selesai Implementasi")))))))))))))))))))))) -> Proses RBT-RBB | BR3: =IF(CD3=0%,"Not Started",IF(CD3<5%,"Proses RBT-RBB",IF(CD3=5%,"Selesai RBT-RBB",IF(CD3<10%,"Proses RBT-RBL",IF(CD3=10%,"Selesai RBT-RBL",IF(CD3<15%,"Proses RBT-RBTD",IF(CD3=15%,"Selesai RBT-RBTD",IF(CD3<20%,"Proses RPP",IF(CD3=20%,"Selesai RPP",IF(CD3<25%,"Proses KAK",IF(CD3=25%,"Selesai KAK",IF(CD3<30%,"Proses Pengadaan",IF(CD3=30%,"Selesai Pengadaan",IF(CD3<45%,"Proses Desain",IF(CD3=45%,"Selesai Desain",IF(CD3<80%,"Proses Pengembangan",IF(CD3=80%,"Selesai Pengembangan",IF(CD3<87.5%,"Proses SIT",IF(CD3=87.5%,"Selesai SIT",IF(CD3<95%,"Proses UAT",IF(CD3=95%,"Selesai UAT",IF(CD3<100%,"Proses Implementasi","Selesai Implementasi")))))))))))))))))))))) -> Not Started | BS3: =IF(CE3=0%,"Not Started",IF(CE3<5%,"Proses RBT-RBB",IF(CE3=5%,"Selesai RBT-RBB",IF(CE3<10%,"Proses RBT-RBL",IF(CE3=10%,"Selesai RBT-RBL",IF(CE3<15%,"Proses RBT-RBTD",IF(CE3=15%,"Selesai RBT-RBTD",IF(CE3<20%,"Proses RPP",IF(CE3=20%,"Selesai RPP",IF(CE3<25%,"Proses KAK",IF(CE3=25%,"Selesai KAK",IF(CE3<30%,"Proses Pengadaan",IF(CE3=30%,"Selesai Pengadaan",IF(CE3<45%,"Proses Desain",IF(CE3=45%,"Selesai Desain",IF(CE3<80%,"Proses Pengembangan",IF(CE3=80%,"Selesai Pengembangan",IF(CE3<87.5%,"Proses SIT",IF(CE3=87.5%,"Selesai SIT",IF(CE3<95%,"Proses UAT",IF(CE3=95%,"Selesai UAT",IF(CE3<100%,"Proses Implementasi","Selesai Implementasi")))))))))))))))))))))) -> Not Started | BT3: =IF(CF3=0%,"Not Started",IF(CF3<5%,"Proses RBT-RBB",IF(CF3=5%,"Selesai RBT-RBB",IF(CF3<10%,"Proses RBT-RBL",IF(CF3=10%,"Selesai RBT-RBL",IF(CF3<15%,"Proses RBT-RBTD",IF(CF3=15%,"Selesai RBT-RBTD",IF(CF3<20%,"Proses RPP",IF(CF3=20%,"Selesai RPP",IF(CF3<25%,"Proses KAK",IF(CF3=25%,"Selesai KAK",IF(CF3<30%,"Proses Pengadaan",IF(CF3=30%,"Selesai Pengadaan",IF(CF3<45%,"Proses Desain",IF(CF3=45%,"Selesai Desain",IF(CF3<80%,"Proses Pengembangan",IF(CF3=80%,"Selesai Pengembangan",IF(CF3<87.5%,"Proses SIT",IF(CF3=87.5%,"Selesai SIT",IF(CF3<95%,"Proses UAT",IF(CF3=95%,"Selesai UAT",IF(CF3<100%,"Proses Implementasi","Selesai Implementasi")))))))))))))))))))))) -> Not Started | BU3: =IF(CG3=0%,"Not Started",IF(CG3<5%,"Proses RBT-RBB",IF(CG3=5%,"Selesai RBT-RBB",IF(CG3<10%,"Proses RBT-RBL",IF(CG3=10%,"Selesai RBT-RBL",IF(CG3<15%,"Proses RBT-RBTD",IF(CG3=15%,"Selesai RBT-RBTD",IF(CG3<20%,"Proses RPP",IF(CG3=20%,"Selesai RPP",IF(CG3<25%,"Proses KAK",IF(CG3=25%,"Selesai KAK",IF(CG3<30%,"Proses Pengadaan",IF(CG3=30%,"Selesai Pengadaan",IF(CG3<45%,"Proses Desain",IF(CG3=45%,"Selesai Desain",IF(CG3<80%,"Proses Pengembangan",IF(CG3=80%,"Selesai Pengembangan",IF(CG3<87.5%,"Proses SIT",IF(CG3=87.5%,"Selesai SIT",IF(CG3<95%,"Proses UAT",IF(CG3=95%,"Selesai UAT",IF(CG3<100%,"Proses Implementasi","Selesai Implementasi")))))))))))))))))))))) -> Not Started | BV3: =IF(CH3=0%,"Not Started",IF(CH3<5%,"Proses RBT-RBB",IF(CH3=5%,"Selesai RBT-RBB",IF(CH3<10%,"Proses RBT-RBL",IF(CH3=10%,"Selesai RBT-RBL",IF(CH3<15%,"Proses RBT-RBTD",IF(CH3=15%,"Selesai RBT-RBTD",IF(CH3<20%,"Proses RPP",IF(CH3=20%,"Selesai RPP",IF(CH3<25%,"Proses KAK",IF(CH3=25%,"Selesai KAK",IF(CH3<30%,"Proses Pengadaan",IF(CH3=30%,"Selesai Pengadaan",IF(CH3<45%,"Proses Desain",IF(CH3=45%,"Selesai Desain",IF(CH3<80%,"Proses Pengembangan",IF(CH3=80%,"Selesai Pengembangan",IF(CH3<87.5%,"Proses SIT",IF(CH3=87.5%,"Selesai SIT",IF(CH3<95%,"Proses UAT",IF(CH3=95%,"Selesai UAT",IF(CH3<100%,"Proses Implementasi","Selesai Implementasi")))))))))))))))))))))) -> Not Started | BW3: =IF(CI3=0%,"Not Started",IF(CI3<5%,"Proses RBT-RBB",IF(CI3=5%,"Selesai RBT-RBB",IF(CI3<10%,"Proses RBT-RBL",IF(CI3=10%,"Selesai RBT-RBL",IF(CI3<15%,"Proses RBT-RBTD",IF(CI3=15%,"Selesai RBT-RBTD",IF(CI3<20%,"Proses RPP",IF(CI3=20%,"Selesai RPP",IF(CI3<25%,"Proses KAK",IF(CI3=25%,"Selesai KAK",IF(CI3<30%,"Proses Pengadaan",IF(CI3=30%,"Selesai Pengadaan",IF(CI3<45%,"Proses Desain",IF(CI3=45%,"Selesai Desain",IF(CI3<80%,"Proses Pengembangan",IF(CI3=80%,"Selesai Pengembangan",IF(CI3<87.5%,"Proses SIT",IF(CI3=87.5%,"Selesai SIT",IF(CI3<95%,"Proses UAT",IF(CI3=95%,"Selesai UAT",IF(CI3<100%,"Proses Implementasi","Selesai Implementasi")))))))))))))))))))))) -> Not Started | BX3: =IF(CJ3=0%,"Not Started",IF(CJ3<5%,"Proses RBT-RBB",IF(CJ3=5%,"Selesai RBT-RBB",IF(CJ3<10%,"Proses RBT-RBL",IF(CJ3=10%,"Selesai RBT-RBL",IF(CJ3<15%,"Proses RBT-RBTD",IF(CJ3=15%,"Selesai RBT-RBTD",IF(CJ3<20%,"Proses RPP",IF(CJ3=20%,"Selesai RPP",IF(CJ3<25%,"Proses KAK",IF(CJ3=25%,"Selesai KAK",IF(CJ3<30%,"Proses Pengadaan",IF(CJ3=30%,"Selesai Pengadaan",IF(CJ3<45%,"Proses Desain",IF(CJ3=45%,"Selesai Desain",IF(CJ3<80%,"Proses Pengembangan",IF(CJ3=80%,"Selesai Pengembangan",IF(CJ3<87.5%,"Proses SIT",IF(CJ3=87.5%,"Selesai SIT",IF(CJ3<95%,"Proses UAT",IF(CJ3=95%,"Selesai UAT",IF(CJ3<100%,"Proses Implementasi","Selesai Implementasi")))))))))))))))))))))) -> Not Started | ... CB3: =IF(CN3=0%,"Not Started",IF(CN3<5%,"Proses RBT-RBB",IF(CN3=5%,"Selesai RBT-RBB",IF(CN3<10%,"Proses RBT-RBL",IF(CN3=10%,"Selesai RBT-RBL",IF(CN3<15%,"Proses RBT-RBTD",IF(CN3=15%,"Selesai RBT-RBTD",IF(CN3<20%,"Proses RPP",IF(CN3=20%,"Selesai RPP",IF(CN3<25%,"Proses KAK",IF(CN3=25%,"Selesai KAK",IF(CN3<30%,"Proses Pengadaan",IF(CN3=30%,"Selesai Pengadaan",IF(CN3<45%,"Proses Desain",IF(CN3=45%,"Selesai Desain",IF(CN3<80%,"Proses Pengembangan",IF(CN3=80%,"Selesai Pengembangan",IF(CN3<87.5%,"Proses SIT",IF(CN3=87.5%,"Selesai SIT",IF(CN3<95%,"Proses UAT",IF(CN3=95%,"Selesai UAT",IF(CN3<100%,"Proses Implementasi","Selesai Implementasi")))))))))))))))))))))) -> Not Started | CC3: =(($DY3/100%)*15%)+(($DZ3/100%)*5%)+(($EA3/100%)*5%)+(($EB3/100%)*5%)+(($EC3/100%)*15%)+(($ED3/100%)*35%)+(($EE3/100%)*7.5%)+(($EF3/100%)*7.5%)+(($EG3/100%)*5%) -> 0.015 | CO3: =IF(BE3=0%, 100%, (CC3/BE3)) -> 0.25 | CP3: =IF(BF3=0%, 100%, (CD3/BF3)) -> 0 | CQ3: =IF(BG3=0%, 100%, (CE3/BG3)) -> 0 | CR3: =IF(BH3=0%, 100%, (CF3/BH3)) -> 0 | CS3: =IF(BI3=0%, 100%, (CG3/BI3)) -> 0 | CT3: =IF(BJ3=0%, 100%, (CH3/BJ3)) -> 0 | CU3: =IF(BK3=0%, 100%, (CI3/BK3)) -> 0 | CV3: =IF(BL3=0%, 100%, (CJ3/BL3)) -> 0 | ... CY3: =IF(BO3=0%, 100%, (CM3/BO3)) -> 0 | DA3: =IF(BE3=0%,"NS",IF(CC3=100%,"DONE",IF(CO3>100%,"AS",IF(CO3<75%,"BS",IF(CO3<89.9%,"AR","OS"))))) -> BS | DB3: =IF(BF3=0%,"NS",IF(CD3=100%,"DONE",IF(CP3>100%,"AS",IF(CP3<75%,"BS",IF(CP3<89.9%,"AR","OS"))))) -> BS | DC3: =IF(BG3=0%,"NS",IF(CE3=100%,"DONE",IF(CQ3>100%,"AS",IF(CQ3<75%,"BS",IF(CQ3<89.9%,"AR","OS"))))) -> BS | DD3: =IF(BH3=0%,"NS",IF(CF3=100%,"DONE",IF(CR3>100%,"AS",IF(CR3<75%,"BS",IF(CR3<89.9%,"AR","OS"))))) -> BS | DE3: =IF(BI3=0%,"NS",IF(CG3=100%,"DONE",IF(CS3>100%,"AS",IF(CS3<75%,"BS",IF(CS3<89.9%,"AR","OS"))))) -> BS | DF3: =IF(BJ3=0%,"NS",IF(CH3=100%,"DONE",IF(CT3>100%,"AS",IF(CT3<75%,"BS",IF(CT3<89.9%,"AR","OS"))))) -> BS | DG3: =IF(BK3=0%,"NS",IF(CI3=100%,"DONE",IF(CU3>100%,"AS",IF(CU3<75%,"BS",IF(CU3<89.9%,"AR","OS"))))) -> BS | DH3: =IF(BL3=0%,"NS",IF(CJ3=100%,"DONE",IF(CV3>100%,"AS",IF(CV3<75%,"BS",IF(CV3<89.9%,"AR","OS"))))) -> BS | ... DL3: =IF(BP3=0%,"NS",IF(CN3=100%,"DONE",IF(CZ3>100%,"AS",IF(CZ3<75%,"BS",IF(CZ3<89.9%,"AR","OS"))))) -> BS | DM3: =CC3/$BP3 -> 0.05 | DN3: =CD3/$BP3 -> 0 | DO3: =CE3/$BP3 -> 0 | DP3: =CF3/$BP3 -> 0 | DQ3: =CG3/$BP3 -> 0 | DR3: =CH3/$BP3 -> 0 | DS3: =CI3/$BP3 -> 0 | DT3: =CJ3/$BP3 -> 0 | ... DX3: =CN3/$BP3 -> 0 | DY3: 0.1 | EH3: Tindaklanjut 1. RKP (cancel) 2. Cakupan surrounding sebagaimana diskusi tgl 1 Des 2025 pembahasan awal RBT dengan DPID untuk ERP, CBS dan RTGS 3. inisis enhc bifast surrounding tetap dilakukan, dengan minor update 4. Penyusunan RBT inisiasi dari satker bisnis DPSP, dari KMBD minggu lalu belum ada update info dari user 5. Timeline di rivibi untuk DLDS seharusnya sudah dimulai terkait RBT di TW 4 namun saat ini belum ada pembahasan RBT karena menunggu point 1 dan 2 Note DPID: - Dari sisi DPID diperlukan ketersediaan lisensi di DPMA. - Perlu konfirmasi terkait crossborder payment dengan New BI-FAST. (rbt crossborder dipisah) - satker user dari DKSP dan DPPT - PIC KMBD DPID (Pak Eka, Mas Marjon dan Mas Ijul) | EJ3: =AR3 -> 47026 | FN3: Aldo Fernanda | FO3: Among Rogo Wicaksono | FP3: 1. Welly Ramantika 2. Lie Tung Kiam 3. M. Anggasta Paramartha | FQ3: Dian | FR3: Outsource
B4: PT03 | C4: IDPS | E4: P-2 | F4: 3 | G4: BI-RTGS Gen III | H4: BI-RTGS Gen III | I4: Enhancement Aplikasi Legacy BI-RTGS Gen III | J4: 2026 | K4: 2029 | L4: S | M4: K3 | N4: Pemimpin Satker | O4: DKSP, DPSP, DPPT, DIDD, DPPK, DLDS | P4: WG-2 | Q4: SP | R4: SKNBI, BI-SSSS Gen II, CBS, FOMOBO, SWIFT, SOA | S4: =BQ4 -> Not Started | T4: =IF(V4=0%,"Not Started",IF(V4<100%,"On Progress",IF(V4=100%,"DONE"))) -> Not Started | U4: =FN4 -> Aldo Fernanda | V4: =CC4 -> 0 | W4: TW II 2027 | X4: =AR4 -> 47391 | Z4: New | AA4: 46296 | AB4: 46568 | AC4: 46569 | AD4: 46660 | AE4: 46631 | AF4: 46660 | AG4: 46661 | AH4: 46843 | AI4: 46844 | AJ4: 46873 | AK4: 46874 | AL4: 47177 | AM4: 47178 | AN4: 47269 | AO4: 47270 | AP4: 47361 | AQ4: 47362 | AR4: 47391 | AS4: =IF(BE4=0%,"Not Started",IF(BE4<5%,"Proses RBT-RBB",IF(BE4=5%,"Selesai RBT-RBB",IF(BE4<10%,"Proses RBT-RBL",IF(BE4=10%,"Selesai RBT-RBL",IF(BE4<15%,"Proses RBT-RBTD",IF(BE4=15%,"Selesai RBT-RBTD",IF(BE4<20%,"Proses RPP",IF(BE4=20%,"Selesai RPP",IF(BE4<25%,"Proses KAK",IF(BE4=25%,"Selesai KAK",IF(BE4<30%,"Proses Pengadaan",IF(BE4=30%,"Selesai Pengadaan",IF(BE4<45%,"Proses Desain",IF(BE4=45%,"Selesai Desain",IF(BE4<80%,"Proses Pengembangan",IF(BE4=80%,"Selesai Pengembangan",IF(BE4<87.5%,"Proses SIT",IF(BE4=87.5%,"Selesai SIT",IF(BE4<95%,"Proses UAT",IF(BE4=95%,"Selesai UAT",IF(BE4<100%,"Proses Implementasi","Selesai Implementasi")))))))))))))))))))))) -> Not Started | AT4: =IF(BF4=0%,"Not Started",IF(BF4<5%,"Proses RBT-RBB",IF(BF4=5%,"Selesai RBT-RBB",IF(BF4<10%,"Proses RBT-RBL",IF(BF4=10%,"Selesai RBT-RBL",IF(BF4<15%,"Proses RBT-RBTD",IF(BF4=15%,"Selesai RBT-RBTD",IF(BF4<20%,"Proses RPP",IF(BF4=20%,"Selesai RPP",IF(BF4<25%,"Proses KAK",IF(BF4=25%,"Selesai KAK",IF(BF4<30%,"Proses Pengadaan",IF(BF4=30%,"Selesai Pengadaan",IF(BF4<45%,"Proses Desain",IF(BF4=45%,"Selesai Desain",IF(BF4<80%,"Proses Pengembangan",IF(BF4=80%,"Selesai Pengembangan",IF(BF4<87.5%,"Proses SIT",IF(BF4=87.5%,"Selesai SIT",IF(BF4<95%,"Proses UAT",IF(BF4=95%,"Selesai UAT",IF(BF4<100%,"Proses Implementasi","Selesai Implementasi")))))))))))))))))))))) -> Not Started | AU4: =IF(BG4=0%,"Not Started",IF(BG4<5%,"Proses RBT-RBB",IF(BG4=5%,"Selesai RBT-RBB",IF(BG4<10%,"Proses RBT-RBL",IF(BG4=10%,"Selesai RBT-RBL",IF(BG4<15%,"Proses RBT-RBTD",IF(BG4=15%,"Selesai RBT-RBTD",IF(BG4<20%,"Proses RPP",IF(BG4=20%,"Selesai RPP",IF(BG4<25%,"Proses KAK",IF(BG4=25%,"Selesai KAK",IF(BG4<30%,"Proses Pengadaan",IF(BG4=30%,"Selesai Pengadaan",IF(BG4<45%,"Proses Desain",IF(BG4=45%,"Selesai Desain",IF(BG4<80%,"Proses Pengembangan",IF(BG4=80%,"Selesai Pengembangan",IF(BG4<87.5%,"Proses SIT",IF(BG4=87.5%,"Selesai SIT",IF(BG4<95%,"Proses UAT",IF(BG4=95%,"Selesai UAT",IF(BG4<100%,"Proses Implementasi","Selesai Implementasi")))))))))))))))))))))) -> Not Started | AV4: =IF(BH4=0%,"Not Started",IF(BH4<5%,"Proses RBT-RBB",IF(BH4=5%,"Selesai RBT-RBB",IF(BH4<10%,"Proses RBT-RBL",IF(BH4=10%,"Selesai RBT-RBL",IF(BH4<15%,"Proses RBT-RBTD",IF(BH4=15%,"Selesai RBT-RBTD",IF(BH4<20%,"Proses RPP",IF(BH4=20%,"Selesai RPP",IF(BH4<25%,"Proses KAK",IF(BH4=25%,"Selesai KAK",IF(BH4<30%,"Proses Pengadaan",IF(BH4=30%,"Selesai Pengadaan",IF(BH4<45%,"Proses Desain",IF(BH4=45%,"Selesai Desain",IF(BH4<80%,"Proses Pengembangan",IF(BH4=80%,"Selesai Pengembangan",IF(BH4<87.5%,"Proses SIT",IF(BH4=87.5%,"Selesai SIT",IF(BH4<95%,"Proses UAT",IF(BH4=95%,"Selesai UAT",IF(BH4<100%,"Proses Implementasi","Selesai Implementasi")))))))))))))))))))))) -> Not Started | AW4: =IF(BI4=0%,"Not Started",IF(BI4<5%,"Proses RBT-RBB",IF(BI4=5%,"Selesai RBT-RBB",IF(BI4<10%,"Proses RBT-RBL",IF(BI4=10%,"Selesai RBT-RBL",IF(BI4<15%,"Proses RBT-RBTD",IF(BI4=15%,"Selesai RBT-RBTD",IF(BI4<20%,"Proses RPP",IF(BI4=20%,"Selesai RPP",IF(BI4<25%,"Proses KAK",IF(BI4=25%,"Selesai KAK",IF(BI4<30%,"Proses Pengadaan",IF(BI4=30%,"Selesai Pengadaan",IF(BI4<45%,"Proses Desain",IF(BI4=45%,"Selesai Desain",IF(BI4<80%,"Proses Pengembangan",IF(BI4=80%,"Selesai Pengembangan",IF(BI4<87.5%,"Proses SIT",IF(BI4=87.5%,"Selesai SIT",IF(BI4<95%,"Proses UAT",IF(BI4=95%,"Selesai UAT",IF(BI4<100%,"Proses Implementasi","Selesai Implementasi")))))))))))))))))))))) -> Not Started | AX4: =IF(BJ4=0%,"Not Started",IF(BJ4<5%,"Proses RBT-RBB",IF(BJ4=5%,"Selesai RBT-RBB",IF(BJ4<10%,"Proses RBT-RBL",IF(BJ4=10%,"Selesai RBT-RBL",IF(BJ4<15%,"Proses RBT-RBTD",IF(BJ4=15%,"Selesai RBT-RBTD",IF(BJ4<20%,"Proses RPP",IF(BJ4=20%,"Selesai RPP",IF(BJ4<25%,"Proses KAK",IF(BJ4=25%,"Selesai KAK",IF(BJ4<30%,"Proses Pengadaan",IF(BJ4=30%,"Selesai Pengadaan",IF(BJ4<45%,"Proses Desain",IF(BJ4=45%,"Selesai Desain",IF(BJ4<80%,"Proses Pengembangan",IF(BJ4=80%,"Selesai Pengembangan",IF(BJ4<87.5%,"Proses SIT",IF(BJ4=87.5%,"Selesai SIT",IF(BJ4<95%,"Proses UAT",IF(BJ4=95%,"Selesai UAT",IF(BJ4<100%,"Proses Implementasi","Selesai Implementasi")))))))))))))))))))))) -> Not Started | AY4: =IF(BK4=0%,"Not Started",IF(BK4<5%,"Proses RBT-RBB",IF(BK4=5%,"Selesai RBT-RBB",IF(BK4<10%,"Proses RBT-RBL",IF(BK4=10%,"Selesai RBT-RBL",IF(BK4<15%,"Proses RBT-RBTD",IF(BK4=15%,"Selesai RBT-RBTD",IF(BK4<20%,"Proses RPP",IF(BK4=20%,"Selesai RPP",IF(BK4<25%,"Proses KAK",IF(BK4=25%,"Selesai KAK",IF(BK4<30%,"Proses Pengadaan",IF(BK4=30%,"Selesai Pengadaan",IF(BK4<45%,"Proses Desain",IF(BK4=45%,"Selesai Desain",IF(BK4<80%,"Proses Pengembangan",IF(BK4=80%,"Selesai Pengembangan",IF(BK4<87.5%,"Proses SIT",IF(BK4=87.5%,"Selesai SIT",IF(BK4<95%,"Proses UAT",IF(BK4=95%,"Selesai UAT",IF(BK4<100%,"Proses Implementasi","Selesai Implementasi")))))))))))))))))))))) -> Not Started | AZ4: =IF(BL4=0%,"Not Started",IF(BL4<5%,"Proses RBT-RBB",IF(BL4=5%,"Selesai RBT-RBB",IF(BL4<10%,"Proses RBT-RBL",IF(BL4=10%,"Selesai RBT-RBL",IF(BL4<15%,"Proses RBT-RBTD",IF(BL4=15%,"Selesai RBT-RBTD",IF(BL4<20%,"Proses RPP",IF(BL4=20%,"Selesai RPP",IF(BL4<25%,"Proses KAK",IF(BL4=25%,"Selesai KAK",IF(BL4<30%,"Proses Pengadaan",IF(BL4=30%,"Selesai Pengadaan",IF(BL4<45%,"Proses Desain",IF(BL4=45%,"Selesai Desain",IF(BL4<80%,"Proses Pengembangan",IF(BL4=80%,"Selesai Pengembangan",IF(BL4<87.5%,"Proses SIT",IF(BL4=87.5%,"Selesai SIT",IF(BL4<95%,"Proses UAT",IF(BL4=95%,"Selesai UAT",IF(BL4<100%,"Proses Implementasi","Selesai Implementasi")))))))))))))))))))))) -> Not Started | ... BD4: =IF(BP4=0%,"Not Started",IF(BP4<5%,"Proses RBT-RBB",IF(BP4=5%,"Selesai RBT-RBB",IF(BP4<10%,"Proses RBT-RBL",IF(BP4=10%,"Selesai RBT-RBL",IF(BP4<15%,"Proses RBT-RBTD",IF(BP4=15%,"Selesai RBT-RBTD",IF(BP4<20%,"Proses RPP",IF(BP4=20%,"Selesai RPP",IF(BP4<25%,"Proses KAK",IF(BP4=25%,"Selesai KAK",IF(BP4<30%,"Proses Pengadaan",IF(BP4=30%,"Selesai Pengadaan",IF(BP4<45%,"Proses Desain",IF(BP4=45%,"Selesai Desain",IF(BP4<80%,"Proses Pengembangan",IF(BP4=80%,"Selesai Pengembangan",IF(BP4<87.5%,"Proses SIT",IF(BP4=87.5%,"Selesai SIT",IF(BP4<95%,"Proses UAT",IF(BP4=95%,"Selesai UAT",IF(BP4<100%,"Proses Implementasi","Selesai Implementasi")))))))))))))))))))))) -> Proses RBT-RBB | BE4: 0 | BF4: 0 | BG4: 0 | BH4: 0 | BI4: 0 | BJ4: 0 | BK4: 0 | BL4: 0 | BM4: 0 | BN4: 0.01 | BO4: 0.02 | BP4: 0.03 | BQ4: =IF(CC4=0%,"Not Started",IF(CC4<5%,"Proses RBT-RBB",IF(CC4=5%,"Selesai RBT-RBB",IF(CC4<10%,"Proses RBT-RBL",IF(CC4=10%,"Selesai RBT-RBL",IF(CC4<15%,"Proses RBT-RBTD",IF(CC4=15%,"Selesai RBT-RBTD",IF(CC4<20%,"Proses RPP",IF(CC4=20%,"Selesai RPP",IF(CC4<25%,"Proses KAK",IF(CC4=25%,"Selesai KAK",IF(CC4<30%,"Proses Pengadaan",IF(CC4=30%,"Selesai Pengadaan",IF(CC4<45%,"Proses Desain",IF(CC4=45%,"Selesai Desain",IF(CC4<80%,"Proses Pengembangan",IF(CC4=80%,"Selesai Pengembangan",IF(CC4<87.5%,"Proses SIT",IF(CC4=87.5%,"Selesai SIT",IF(CC4<95%,"Proses UAT",IF(CC4=95%,"Selesai UAT",IF(CC4<100%,"Proses Implementasi","Selesai Implementasi")))))))))))))))))))))) -> Not Started | BR4: =IF(CD4=0%,"Not Started",IF(CD4<5%,"Proses RBT-RBB",IF(CD4=5%,"Selesai RBT-RBB",IF(CD4<10%,"Proses RBT-RBL",IF(CD4=10%,"Selesai RBT-RBL",IF(CD4<15%,"Proses RBT-RBTD",IF(CD4=15%,"Selesai RBT-RBTD",IF(CD4<20%,"Proses RPP",IF(CD4=20%,"Selesai RPP",IF(CD4<25%,"Proses KAK",IF(CD4=25%,"Selesai KAK",IF(CD4<30%,"Proses Pengadaan",IF(CD4=30%,"Selesai Pengadaan",IF(CD4<45%,"Proses Desain",IF(CD4=45%,"Selesai Desain",IF(CD4<80%,"Proses Pengembangan",IF(CD4=80%,"Selesai Pengembangan",IF(CD4<87.5%,"Proses SIT",IF(CD4=87.5%,"Selesai SIT",IF(CD4<95%,"Proses UAT",IF(CD4=95%,"Selesai UAT",IF(CD4<100%,"Proses Implementasi","Selesai Implementasi")))))))))))))))))))))) -> Not Started | BS4: =IF(CE4=0%,"Not Started",IF(CE4<5%,"Proses RBT-RBB",IF(CE4=5%,"Selesai RBT-RBB",IF(CE4<10%,"Proses RBT-RBL",IF(CE4=10%,"Selesai RBT-RBL",IF(CE4<15%,"Proses RBT-RBTD",IF(CE4=15%,"Selesai RBT-RBTD",IF(CE4<20%,"Proses RPP",IF(CE4=20%,"Selesai RPP",IF(CE4<25%,"Proses KAK",IF(CE4=25%,"Selesai KAK",IF(CE4<30%,"Proses Pengadaan",IF(CE4=30%,"Selesai Pengadaan",IF(CE4<45%,"Proses Desain",IF(CE4=45%,"Selesai Desain",IF(CE4<80%,"Proses Pengembangan",IF(CE4=80%,"Selesai Pengembangan",IF(CE4<87.5%,"Proses SIT",IF(CE4=87.5%,"Selesai SIT",IF(CE4<95%,"Proses UAT",IF(CE4=95%,"Selesai UAT",IF(CE4<100%,"Proses Implementasi","Selesai Implementasi")))))))))))))))))))))) -> Not Started | BT4: =IF(CF4=0%,"Not Started",IF(CF4<5%,"Proses RBT-RBB",IF(CF4=5%,"Selesai RBT-RBB",IF(CF4<10%,"Proses RBT-RBL",IF(CF4=10%,"Selesai RBT-RBL",IF(CF4<15%,"Proses RBT-RBTD",IF(CF4=15%,"Selesai RBT-RBTD",IF(CF4<20%,"Proses RPP",IF(CF4=20%,"Selesai RPP",IF(CF4<25%,"Proses KAK",IF(CF4=25%,"Selesai KAK",IF(CF4<30%,"Proses Pengadaan",IF(CF4=30%,"Selesai Pengadaan",IF(CF4<45%,"Proses Desain",IF(CF4=45%,"Selesai Desain",IF(CF4<80%,"Proses Pengembangan",IF(CF4=80%,"Selesai Pengembangan",IF(CF4<87.5%,"Proses SIT",IF(CF4=87.5%,"Selesai SIT",IF(CF4<95%,"Proses UAT",IF(CF4=95%,"Selesai UAT",IF(CF4<100%,"Proses Implementasi","Selesai Implementasi")))))))))))))))))))))) -> Not Started | BU4: =IF(CG4=0%,"Not Started",IF(CG4<5%,"Proses RBT-RBB",IF(CG4=5%,"Selesai RBT-RBB",IF(CG4<10%,"Proses RBT-RBL",IF(CG4=10%,"Selesai RBT-RBL",IF(CG4<15%,"Proses RBT-RBTD",IF(CG4=15%,"Selesai RBT-RBTD",IF(CG4<20%,"Proses RPP",IF(CG4=20%,"Selesai RPP",IF(CG4<25%,"Proses KAK",IF(CG4=25%,"Selesai KAK",IF(CG4<30%,"Proses Pengadaan",IF(CG4=30%,"Selesai Pengadaan",IF(CG4<45%,"Proses Desain",IF(CG4=45%,"Selesai Desain",IF(CG4<80%,"Proses Pengembangan",IF(CG4=80%,"Selesai Pengembangan",IF(CG4<87.5%,"Proses SIT",IF(CG4=87.5%,"Selesai SIT",IF(CG4<95%,"Proses UAT",IF(CG4=95%,"Selesai UAT",IF(CG4<100%,"Proses Implementasi","Selesai Implementasi")))))))))))))))))))))) -> Not Started | BV4: =IF(CH4=0%,"Not Started",IF(CH4<5%,"Proses RBT-RBB",IF(CH4=5%,"Selesai RBT-RBB",IF(CH4<10%,"Proses RBT-RBL",IF(CH4=10%,"Selesai RBT-RBL",IF(CH4<15%,"Proses RBT-RBTD",IF(CH4=15%,"Selesai RBT-RBTD",IF(CH4<20%,"Proses RPP",IF(CH4=20%,"Selesai RPP",IF(CH4<25%,"Proses KAK",IF(CH4=25%,"Selesai KAK",IF(CH4<30%,"Proses Pengadaan",IF(CH4=30%,"Selesai Pengadaan",IF(CH4<45%,"Proses Desain",IF(CH4=45%,"Selesai Desain",IF(CH4<80%,"Proses Pengembangan",IF(CH4=80%,"Selesai Pengembangan",IF(CH4<87.5%,"Proses SIT",IF(CH4=87.5%,"Selesai SIT",IF(CH4<95%,"Proses UAT",IF(CH4=95%,"Selesai UAT",IF(CH4<100%,"Proses Implementasi","Selesai Implementasi")))))))))))))))))))))) -> Not Started | BW4: =IF(CI4=0%,"Not Started",IF(CI4<5%,"Proses RBT-RBB",IF(CI4=5%,"Selesai RBT-RBB",IF(CI4<10%,"Proses RBT-RBL",IF(CI4=10%,"Selesai RBT-RBL",IF(CI4<15%,"Proses RBT-RBTD",IF(CI4=15%,"Selesai RBT-RBTD",IF(CI4<20%,"Proses RPP",IF(CI4=20%,"Selesai RPP",IF(CI4<25%,"Proses KAK",IF(CI4=25%,"Selesai KAK",IF(CI4<30%,"Proses Pengadaan",IF(CI4=30%,"Selesai Pengadaan",IF(CI4<45%,"Proses Desain",IF(CI4=45%,"Selesai Desain",IF(CI4<80%,"Proses Pengembangan",IF(CI4=80%,"Selesai Pengembangan",IF(CI4<87.5%,"Proses SIT",IF(CI4=87.5%,"Selesai SIT",IF(CI4<95%,"Proses UAT",IF(CI4=95%,"Selesai UAT",IF(CI4<100%,"Proses Implementasi","Selesai Implementasi")))))))))))))))))))))) -> Not Started | BX4: =IF(CJ4=0%,"Not Started",IF(CJ4<5%,"Proses RBT-RBB",IF(CJ4=5%,"Selesai RBT-RBB",IF(CJ4<10%,"Proses RBT-RBL",IF(CJ4=10%,"Selesai RBT-RBL",IF(CJ4<15%,"Proses RBT-RBTD",IF(CJ4=15%,"Selesai RBT-RBTD",IF(CJ4<20%,"Proses RPP",IF(CJ4=20%,"Selesai RPP",IF(CJ4<25%,"Proses KAK",IF(CJ4=25%,"Selesai KAK",IF(CJ4<30%,"Proses Pengadaan",IF(CJ4=30%,"Selesai Pengadaan",IF(CJ4<45%,"Proses Desain",IF(CJ4=45%,"Selesai Desain",IF(CJ4<80%,"Proses Pengembangan",IF(CJ4=80%,"Selesai Pengembangan",IF(CJ4<87.5%,"Proses SIT",IF(CJ4=87.5%,"Selesai SIT",IF(CJ4<95%,"Proses UAT",IF(CJ4=95%,"Selesai UAT",IF(CJ4<100%,"Proses Implementasi","Selesai Implementasi")))))))))))))))))))))) -> Not Started | ... CB4: =IF(CN4=0%,"Not Started",IF(CN4<5%,"Proses RBT-RBB",IF(CN4=5%,"Selesai RBT-RBB",IF(CN4<10%,"Proses RBT-RBL",IF(CN4=10%,"Selesai RBT-RBL",IF(CN4<15%,"Proses RBT-RBTD",IF(CN4=15%,"Selesai RBT-RBTD",IF(CN4<20%,"Proses RPP",IF(CN4=20%,"Selesai RPP",IF(CN4<25%,"Proses KAK",IF(CN4=25%,"Selesai KAK",IF(CN4<30%,"Proses Pengadaan",IF(CN4=30%,"Selesai Pengadaan",IF(CN4<45%,"Proses Desain",IF(CN4=45%,"Selesai Desain",IF(CN4<80%,"Proses Pengembangan",IF(CN4=80%,"Selesai Pengembangan",IF(CN4<87.5%,"Proses SIT",IF(CN4=87.5%,"Selesai SIT",IF(CN4<95%,"Proses UAT",IF(CN4=95%,"Selesai UAT",IF(CN4<100%,"Proses Implementasi","Selesai Implementasi")))))))))))))))))))))) -> Not Started | CC4: =(($DY4/100%)*15%)+(($DZ4/100%)*5%)+(($EA4/100%)*5%)+(($EB4/100%)*5%)+(($EC4/100%)*15%)+(($ED4/100%)*35%)+(($EE4/100%)*7.5%)+(($EF4/100%)*7.5%)+(($EG4/100%)*5%) -> 0 | CO4: =IF(BE4=0%, 100%, (CC4/BE4)) -> 1 | CP4: =IF(BF4=0%, 100%, (CD4/BF4)) -> 1 | CQ4: =IF(BG4=0%, 100%, (CE4/BG4)) -> 1 | CR4: =IF(BH4=0%, 100%, (CF4/BH4)) -> 1 | CS4: =IF(BI4=0%, 100%, (CG4/BI4)) -> 1 | CT4: =IF(BJ4=0%, 100%, (CH4/BJ4)) -> 1 | CU4: =IF(BK4=0%, 100%, (CI4/BK4)) -> 1 | CV4: =IF(BL4=0%, 100%, (CJ4/BL4)) -> 1 | ... CY4: =IF(BO4=0%, 100%, (CM4/BO4)) -> 0 | DA4: =IF(BE4=0%,"NS",IF(CC4=100%,"DONE",IF(CO4>100%,"AS",IF(CO4<75%,"BS",IF(CO4<89.9%,"AR","OS"))))) -> NS | DB4: =IF(BF4=0%,"NS",IF(CD4=100%,"DONE",IF(CP4>100%,"AS",IF(CP4<75%,"BS",IF(CP4<89.9%,"AR","OS"))))) -> NS | DC4: =IF(BG4=0%,"NS",IF(CE4=100%,"DONE",IF(CQ4>100%,"AS",IF(CQ4<75%,"BS",IF(CQ4<89.9%,"AR","OS"))))) -> NS | DD4: =IF(BH4=0%,"NS",IF(CF4=100%,"DONE",IF(CR4>100%,"AS",IF(CR4<75%,"BS",IF(CR4<89.9%,"AR","OS"))))) -> NS | DE4: =IF(BI4=0%,"NS",IF(CG4=100%,"DONE",IF(CS4>100%,"AS",IF(CS4<75%,"BS",IF(CS4<89.9%,"AR","OS"))))) -> NS | DF4: =IF(BJ4=0%,"NS",IF(CH4=100%,"DONE",IF(CT4>100%,"AS",IF(CT4<75%,"BS",IF(CT4<89.9%,"AR","OS"))))) -> NS | DG4: =IF(BK4=0%,"NS",IF(CI4=100%,"DONE",IF(CU4>100%,"AS",IF(CU4<75%,"BS",IF(CU4<89.9%,"AR","OS"))))) -> NS | DH4: =IF(BL4=0%,"NS",IF(CJ4=100%,"DONE",IF(CV4>100%,"AS",IF(CV4<75%,"BS",IF(CV4<89.9%,"AR","OS"))))) -> NS | ... DL4: =IF(BP4=0%,"NS",IF(CN4=100%,"DONE",IF(CZ4>100%,"AS",IF(CZ4<75%,"BS",IF(CZ4<89.9%,"AR","OS"))))) -> BS | DM4: =CC4/$BP4 -> 0 | DN4: =CD4/$BP4 -> 0 | DO4: =CE4/$BP4 -> 0 | DP4: =CF4/$BP4 -> 0 | DQ4: =CG4/$BP4 -> 0 | DR4: =CH4/$BP4 -> 0 | DS4: =CI4/$BP4 -> 0 | DT4: =CJ4/$BP4 -> 0 | ... DX4: =CN4/$BP4 -> 0 | EH4: tindaklanjut: 1. perlu konfirmasi ke User DPSP dan DPPT terkait jadwal pembahasan RBT (to do) Note: pembahasan konsinyering Bandung 1-2 Des 2025 1. pembahasan RBT baru akan dilanjutkan kembali dari sisi user karena sebelum nya sempat pending dikarenakan prioritas proyek lainnya 2. terdapat konfirmasi dari sisi User ke DLDS untuk pengembangan RMB pada RTGS Gen 2 namun hambatan nya pada kesediaan aplikasi surrounding, waktu persiapan dan masa pakai sampai Gen 3 mulai beroperasi 3. konfirmasi dampak RTGS Gen 3 ke surrounding seperti TMSX, CBS dan timeline surrounding dengan RTGS Gen 3 | EJ4: =AR4 -> 47391 | FM4: Faradilla Anggun S. | FN4: Aldo Fernanda | FO4: Among Rogo Wicaksono | FP4: 1. Welly Ramantika 2. Lie Tung Kiam 3. Elsameinar | FQ4: Dian | FR4: Outsource
B5: PT02 | C5: IDPS | E5: P-3 | F5: 3 | G5: BI-SSSS Gen III | H5: BI-SSSS Gen III | I5: Enhancement Aplikasi Legacy BI-SSSS Gen III | J5: 2027 | K5: 2029 | L5: S | M5: K3 | N5: Pemimpin Satker | O5: DPPK, DPSP | P5: WG-2 | Q5: Market | R5: BI-ETP, FOMOBO, CBS, Bloomberg, SI BI-SSSS | S5: =BQ5 -> Not Started | T5: =IF(V5=0%,"Not Started",IF(V5<100%,"On Progress",IF(V5=100%,"DONE"))) -> Not Started | U5: =FN5 -> Rizky Arga | V5: =CC5 -> 0 | W5: TW II 2027 | X5: =AR5 -> 47391 | Z5: New | AA5: 46388 | AB5: 46568 | AC5: 46569 | AD5: 46660 | AE5: 46631 | AF5: 46660 | AG5: 46661 | AH5: 46843 | AI5: 46844 | AJ5: 46873 | AK5: 46874 | AL5: 47177 | AM5: 47178 | AN5: 47269 | AO5: 47270 | AP5: 47361 | AQ5: 47362 | AR5: 47391 | AS5: =IF(BE5=0%,"Not Started",IF(BE5<5%,"Proses RBT-RBB",IF(BE5=5%,"Selesai RBT-RBB",IF(BE5<10%,"Proses RBT-RBL",IF(BE5=10%,"Selesai RBT-RBL",IF(BE5<15%,"Proses RBT-RBTD",IF(BE5=15%,"Selesai RBT-RBTD",IF(BE5<20%,"Proses RPP",IF(BE5=20%,"Selesai RPP",IF(BE5<25%,"Proses KAK",IF(BE5=25%,"Selesai KAK",IF(BE5<30%,"Proses Pengadaan",IF(BE5=30%,"Selesai Pengadaan",IF(BE5<45%,"Proses Desain",IF(BE5=45%,"Selesai Desain",IF(BE5<80%,"Proses Pengembangan",IF(BE5=80%,"Selesai Pengembangan",IF(BE5<87.5%,"Proses SIT",IF(BE5=87.5%,"Selesai SIT",IF(BE5<95%,"Proses UAT",IF(BE5=95%,"Selesai UAT",IF(BE5<100%,"Proses Implementasi","Selesai Implementasi")))))))))))))))))))))) -> Not Started | AT5: =IF(BF5=0%,"Not Started",IF(BF5<5%,"Proses RBT-RBB",IF(BF5=5%,"Selesai RBT-RBB",IF(BF5<10%,"Proses RBT-RBL",IF(BF5=10%,"Selesai RBT-RBL",IF(BF5<15%,"Proses RBT-RBTD",IF(BF5=15%,"Selesai RBT-RBTD",IF(BF5<20%,"Proses RPP",IF(BF5=20%,"Selesai RPP",IF(BF5<25%,"Proses KAK",IF(BF5=25%,"Selesai KAK",IF(BF5<30%,"Proses Pengadaan",IF(BF5=30%,"Selesai Pengadaan",IF(BF5<45%,"Proses Desain",IF(BF5=45%,"Selesai Desain",IF(BF5<80%,"Proses Pengembangan",IF(BF5=80%,"Selesai Pengembangan",IF(BF5<87.5%,"Proses SIT",IF(BF5=87.5%,"Selesai SIT",IF(BF5<95%,"Proses UAT",IF(BF5=95%,"Selesai UAT",IF(BF5<100%,"Proses Implementasi","Selesai Implementasi")))))))))))))))))))))) -> Not Started | AU5: =IF(BG5=0%,"Not Started",IF(BG5<5%,"Proses RBT-RBB",IF(BG5=5%,"Selesai RBT-RBB",IF(BG5<10%,"Proses RBT-RBL",IF(BG5=10%,"Selesai RBT-RBL",IF(BG5<15%,"Proses RBT-RBTD",IF(BG5=15%,"Selesai RBT-RBTD",IF(BG5<20%,"Proses RPP",IF(BG5=20%,"Selesai RPP",IF(BG5<25%,"Proses KAK",IF(BG5=25%,"Selesai KAK",IF(BG5<30%,"Proses Pengadaan",IF(BG5=30%,"Selesai Pengadaan",IF(BG5<45%,"Proses Desain",IF(BG5=45%,"Selesai Desain",IF(BG5<80%,"Proses Pengembangan",IF(BG5=80%,"Selesai Pengembangan",IF(BG5<87.5%,"Proses SIT",IF(BG5=87.5%,"Selesai SIT",IF(BG5<95%,"Proses UAT",IF(BG5=95%,"Selesai UAT",IF(BG5<100%,"Proses Implementasi","Selesai Implementasi")))))))))))))))))))))) -> Not Started | AV5: =IF(BH5=0%,"Not Started",IF(BH5<5%,"Proses RBT-RBB",IF(BH5=5%,"Selesai RBT-RBB",IF(BH5<10%,"Proses RBT-RBL",IF(BH5=10%,"Selesai RBT-RBL",IF(BH5<15%,"Proses RBT-RBTD",IF(BH5=15%,"Selesai RBT-RBTD",IF(BH5<20%,"Proses RPP",IF(BH5=20%,"Selesai RPP",IF(BH5<25%,"Proses KAK",IF(BH5=25%,"Selesai KAK",IF(BH5<30%,"Proses Pengadaan",IF(BH5=30%,"Selesai Pengadaan",IF(BH5<45%,"Proses Desain",IF(BH5=45%,"Selesai Desain",IF(BH5<80%,"Proses Pengembangan",IF(BH5=80%,"Selesai Pengembangan",IF(BH5<87.5%,"Proses SIT",IF(BH5=87.5%,"Selesai SIT",IF(BH5<95%,"Proses UAT",IF(BH5=95%,"Selesai UAT",IF(BH5<100%,"Proses Implementasi","Selesai Implementasi")))))))))))))))))))))) -> Not Started | AW5: =IF(BI5=0%,"Not Started",IF(BI5<5%,"Proses RBT-RBB",IF(BI5=5%,"Selesai RBT-RBB",IF(BI5<10%,"Proses RBT-RBL",IF(BI5=10%,"Selesai RBT-RBL",IF(BI5<15%,"Proses RBT-RBTD",IF(BI5=15%,"Selesai RBT-RBTD",IF(BI5<20%,"Proses RPP",IF(BI5=20%,"Selesai RPP",IF(BI5<25%,"Proses KAK",IF(BI5=25%,"Selesai KAK",IF(BI5<30%,"Proses Pengadaan",IF(BI5=30%,"Selesai Pengadaan",IF(BI5<45%,"Proses Desain",IF(BI5=45%,"Selesai Desain",IF(BI5<80%,"Proses Pengembangan",IF(BI5=80%,"Selesai Pengembangan",IF(BI5<87.5%,"Proses SIT",IF(BI5=87.5%,"Selesai SIT",IF(BI5<95%,"Proses UAT",IF(BI5=95%,"Selesai UAT",IF(BI5<100%,"Proses Implementasi","Selesai Implementasi")))))))))))))))))))))) -> Not Started | AX5: =IF(BJ5=0%,"Not Started",IF(BJ5<5%,"Proses RBT-RBB",IF(BJ5=5%,"Selesai RBT-RBB",IF(BJ5<10%,"Proses RBT-RBL",IF(BJ5=10%,"Selesai RBT-RBL",IF(BJ5<15%,"Proses RBT-RBTD",IF(BJ5=15%,"Selesai RBT-RBTD",IF(BJ5<20%,"Proses RPP",IF(BJ5=20%,"Selesai RPP",IF(BJ5<25%,"Proses KAK",IF(BJ5=25%,"Selesai KAK",IF(BJ5<30%,"Proses Pengadaan",IF(BJ5=30%,"Selesai Pengadaan",IF(BJ5<45%,"Proses Desain",IF(BJ5=45%,"Selesai Desain",IF(BJ5<80%,"Proses Pengembangan",IF(BJ5=80%,"Selesai Pengembangan",IF(BJ5<87.5%,"Proses SIT",IF(BJ5=87.5%,"Selesai SIT",IF(BJ5<95%,"Proses UAT",IF(BJ5=95%,"Selesai UAT",IF(BJ5<100%,"Proses Implementasi","Selesai Implementasi")))))))))))))))))))))) -> Not Started | AY5: =IF(BK5=0%,"Not Started",IF(BK5<5%,"Proses RBT-RBB",IF(BK5=5%,"Selesai RBT-RBB",IF(BK5<10%,"Proses RBT-RBL",IF(BK5=10%,"Selesai RBT-RBL",IF(BK5<15%,"Proses RBT-RBTD",IF(BK5=15%,"Selesai RBT-RBTD",IF(BK5<20%,"Proses RPP",IF(BK5=20%,"Selesai RPP",IF(BK5<25%,"Proses KAK",IF(BK5=25%,"Selesai KAK",IF(BK5<30%,"Proses Pengadaan",IF(BK5=30%,"Selesai Pengadaan",IF(BK5<45%,"Proses Desain",IF(BK5=45%,"Selesai Desain",IF(BK5<80%,"Proses Pengembangan",IF(BK5=80%,"Selesai Pengembangan",IF(BK5<87.5%,"Proses SIT",IF(BK5=87.5%,"Selesai SIT",IF(BK5<95%,"Proses UAT",IF(BK5=95%,"Selesai UAT",IF(BK5<100%,"Proses Implementasi","Selesai Implementasi")))))))))))))))))))))) -> Not Started | AZ5: =IF(BL5=0%,"Not Started",IF(BL5<5%,"Proses RBT-RBB",IF(BL5=5%,"Selesai RBT-RBB",IF(BL5<10%,"Proses RBT-RBL",IF(BL5=10%,"Selesai RBT-RBL",IF(BL5<15%,"Proses RBT-RBTD",IF(BL5=15%,"Selesai RBT-RBTD",IF(BL5<20%,"Proses RPP",IF(BL5=20%,"Selesai RPP",IF(BL5<25%,"Proses KAK",IF(BL5=25%,"Selesai KAK",IF(BL5<30%,"Proses Pengadaan",IF(BL5=30%,"Selesai Pengadaan",IF(BL5<45%,"Proses Desain",IF(BL5=45%,"Selesai Desain",IF(BL5<80%,"Proses Pengembangan",IF(BL5=80%,"Selesai Pengembangan",IF(BL5<87.5%,"Proses SIT",IF(BL5=87.5%,"Selesai SIT",IF(BL5<95%,"Proses UAT",IF(BL5=95%,"Selesai UAT",IF(BL5<100%,"Proses Implementasi","Selesai Implementasi")))))))))))))))))))))) -> Not Started | ... BD5: =IF(BP5=0%,"Not Started",IF(BP5<5%,"Proses RBT-RBB",IF(BP5=5%,"Selesai RBT-RBB",IF(BP5<10%,"Proses RBT-RBL",IF(BP5=10%,"Selesai RBT-RBL",IF(BP5<15%,"Proses RBT-RBTD",IF(BP5=15%,"Selesai RBT-RBTD",IF(BP5<20%,"Proses RPP",IF(BP5=20%,"Selesai RPP",IF(BP5<25%,"Proses KAK",IF(BP5=25%,"Selesai KAK",IF(BP5<30%,"Proses Pengadaan",IF(BP5=30%,"Selesai Pengadaan",IF(BP5<45%,"Proses Desain",IF(BP5=45%,"Selesai Desain",IF(BP5<80%,"Proses Pengembangan",IF(BP5=80%,"Selesai Pengembangan",IF(BP5<87.5%,"Proses SIT",IF(BP5=87.5%,"Selesai SIT",IF(BP5<95%,"Proses UAT",IF(BP5=95%,"Selesai UAT",IF(BP5<100%,"Proses Implementasi","Selesai Implementasi")))))))))))))))))))))) -> Not Started | BE5: 0 | BF5: 0 | BG5: 0 | BH5: 0 | BI5: 0 | BJ5: 0 | BK5: 0 | BL5: 0 | BM5: 0 | BN5: 0 | BO5: 0 | BP5: 0 | BQ5: =IF(CC5=0%,"Not Started",IF(CC5<5%,"Proses RBT-RBB",IF(CC5=5%,"Selesai RBT-RBB",IF(CC5<10%,"Proses RBT-RBL",IF(CC5=10%,"Selesai RBT-RBL",IF(CC5<15%,"Proses RBT-RBTD",IF(CC5=15%,"Selesai RBT-RBTD",IF(CC5<20%,"Proses RPP",IF(CC5=20%,"Selesai RPP",IF(CC5<25%,"Proses KAK",IF(CC5=25%,"Selesai KAK",IF(CC5<30%,"Proses Pengadaan",IF(CC5=30%,"Selesai Pengadaan",IF(CC5<45%,"Proses Desain",IF(CC5=45%,"Selesai Desain",IF(CC5<80%,"Proses Pengembangan",IF(CC5=80%,"Selesai Pengembangan",IF(CC5<87.5%,"Proses SIT",IF(CC5=87.5%,"Selesai SIT",IF(CC5<95%,"Proses UAT",IF(CC5=95%,"Selesai UAT",IF(CC5<100%,"Proses Implementasi","Selesai Implementasi")))))))))))))))))))))) -> Not Started | BR5: =IF(CD5=0%,"Not Started",IF(CD5<5%,"Proses RBT-RBB",IF(CD5=5%,"Selesai RBT-RBB",IF(CD5<10%,"Proses RBT-RBL",IF(CD5=10%,"Selesai RBT-RBL",IF(CD5<15%,"Proses RBT-RBTD",IF(CD5=15%,"Selesai RBT-RBTD",IF(CD5<20%,"Proses RPP",IF(CD5=20%,"Selesai RPP",IF(CD5<25%,"Proses KAK",IF(CD5=25%,"Selesai KAK",IF(CD5<30%,"Proses Pengadaan",IF(CD5=30%,"Selesai Pengadaan",IF(CD5<45%,"Proses Desain",IF(CD5=45%,"Selesai Desain",IF(CD5<80%,"Proses Pengembangan",IF(CD5=80%,"Selesai Pengembangan",IF(CD5<87.5%,"Proses SIT",IF(CD5=87.5%,"Selesai SIT",IF(CD5<95%,"Proses UAT",IF(CD5=95%,"Selesai UAT",IF(CD5<100%,"Proses Implementasi","Selesai Implementasi")))))))))))))))))))))) -> Not Started | BS5: =IF(CE5=0%,"Not Started",IF(CE5<5%,"Proses RBT-RBB",IF(CE5=5%,"Selesai RBT-RBB",IF(CE5<10%,"Proses RBT-RBL",IF(CE5=10%,"Selesai RBT-RBL",IF(CE5<15%,"Proses RBT-RBTD",IF(CE5=15%,"Selesai RBT-RBTD",IF(CE5<20%,"Proses RPP",IF(CE5=20%,"Selesai RPP",IF(CE5<25%,"Proses KAK",IF(CE5=25%,"Selesai KAK",IF(CE5<30%,"Proses Pengadaan",IF(CE5=30%,"Selesai Pengadaan",IF(CE5<45%,"Proses Desain",IF(CE5=45%,"Selesai Desain",IF(CE5<80%,"Proses Pengembangan",IF(CE5=80%,"Selesai Pengembangan",IF(CE5<87.5%,"Proses SIT",IF(CE5=87.5%,"Selesai SIT",IF(CE5<95%,"Proses UAT",IF(CE5=95%,"Selesai UAT",IF(CE5<100%,"Proses Implementasi","Selesai Implementasi")))))))))))))))))))))) -> Not Started | BT5: =IF(CF5=0%,"Not Started",IF(CF5<5%,"Proses RBT-RBB",IF(CF5=5%,"Selesai RBT-RBB",IF(CF5<10%,"Proses RBT-RBL",IF(CF5=10%,"Selesai RBT-RBL",IF(CF5<15%,"Proses RBT-RBTD",IF(CF5=15%,"Selesai RBT-RBTD",IF(CF5<20%,"Proses RPP",IF(CF5=20%,"Selesai RPP",IF(CF5<25%,"Proses KAK",IF(CF5=25%,"Selesai KAK",IF(CF5<30%,"Proses Pengadaan",IF(CF5=30%,"Selesai Pengadaan",IF(CF5<45%,"Proses Desain",IF(CF5=45%,"Selesai Desain",IF(CF5<80%,"Proses Pengembangan",IF(CF5=80%,"Selesai Pengembangan",IF(CF5<87.5%,"Proses SIT",IF(CF5=87.5%,"Selesai SIT",IF(CF5<95%,"Proses UAT",IF(CF5=95%,"Selesai UAT",IF(CF5<100%,"Proses Implementasi","Selesai Implementasi")))))))))))))))))))))) -> Not Started | BU5: =IF(CG5=0%,"Not Started",IF(CG5<5%,"Proses RBT-RBB",IF(CG5=5%,"Selesai RBT-RBB",IF(CG5<10%,"Proses RBT-RBL",IF(CG5=10%,"Selesai RBT-RBL",IF(CG5<15%,"Proses RBT-RBTD",IF(CG5=15%,"Selesai RBT-RBTD",IF(CG5<20%,"Proses RPP",IF(CG5=20%,"Selesai RPP",IF(CG5<25%,"Proses KAK",IF(CG5=25%,"Selesai KAK",IF(CG5<30%,"Proses Pengadaan",IF(CG5=30%,"Selesai Pengadaan",IF(CG5<45%,"Proses Desain",IF(CG5=45%,"Selesai Desain",IF(CG5<80%,"Proses Pengembangan",IF(CG5=80%,"Selesai Pengembangan",IF(CG5<87.5%,"Proses SIT",IF(CG5=87.5%,"Selesai SIT",IF(CG5<95%,"Proses UAT",IF(CG5=95%,"Selesai UAT",IF(CG5<100%,"Proses Implementasi","Selesai Implementasi")))))))))))))))))))))) -> Not Started | BV5: =IF(CH5=0%,"Not Started",IF(CH5<5%,"Proses RBT-RBB",IF(CH5=5%,"Selesai RBT-RBB",IF(CH5<10%,"Proses RBT-RBL",IF(CH5=10%,"Selesai RBT-RBL",IF(CH5<15%,"Proses RBT-RBTD",IF(CH5=15%,"Selesai RBT-RBTD",IF(CH5<20%,"Proses RPP",IF(CH5=20%,"Selesai RPP",IF(CH5<25%,"Proses KAK",IF(CH5=25%,"Selesai KAK",IF(CH5<30%,"Proses Pengadaan",IF(CH5=30%,"Selesai Pengadaan",IF(CH5<45%,"Proses Desain",IF(CH5=45%,"Selesai Desain",IF(CH5<80%,"Proses Pengembangan",IF(CH5=80%,"Selesai Pengembangan",IF(CH5<87.5%,"Proses SIT",IF(CH5=87.5%,"Selesai SIT",IF(CH5<95%,"Proses UAT",IF(CH5=95%,"Selesai UAT",IF(CH5<100%,"Proses Implementasi","Selesai Implementasi")))))))))))))))))))))) -> Not Started | BW5: =IF(CI5=0%,"Not Started",IF(CI5<5%,"Proses RBT-RBB",IF(CI5=5%,"Selesai RBT-RBB",IF(CI5<10%,"Proses RBT-RBL",IF(CI5=10%,"Selesai RBT-RBL",IF(CI5<15%,"Proses RBT-RBTD",IF(CI5=15%,"Selesai RBT-RBTD",IF(CI5<20%,"Proses RPP",IF(CI5=20%,"Selesai RPP",IF(CI5<25%,"Proses KAK",IF(CI5=25%,"Selesai KAK",IF(CI5<30%,"Proses Pengadaan",IF(CI5=30%,"Selesai Pengadaan",IF(CI5<45%,"Proses Desain",IF(CI5=45%,"Selesai Desain",IF(CI5<80%,"Proses Pengembangan",IF(CI5=80%,"Selesai Pengembangan",IF(CI5<87.5%,"Proses SIT",IF(CI5=87.5%,"Selesai SIT",IF(CI5<95%,"Proses UAT",IF(CI5=95%,"Selesai UAT",IF(CI5<100%,"Proses Implementasi","Selesai Implementasi")))))))))))))))))))))) -> Not Started | BX5: =IF(CJ5=0%,"Not Started",IF(CJ5<5%,"Proses RBT-RBB",IF(CJ5=5%,"Selesai RBT-RBB",IF(CJ5<10%,"Proses RBT-RBL",IF(CJ5=10%,"Selesai RBT-RBL",IF(CJ5<15%,"Proses RBT-RBTD",IF(CJ5=15%,"Selesai RBT-RBTD",IF(CJ5<20%,"Proses RPP",IF(CJ5=20%,"Selesai RPP",IF(CJ5<25%,"Proses KAK",IF(CJ5=25%,"Selesai KAK",IF(CJ5<30%,"Proses Pengadaan",IF(CJ5=30%,"Selesai Pengadaan",IF(CJ5<45%,"Proses Desain",IF(CJ5=45%,"Selesai Desain",IF(CJ5<80%,"Proses Pengembangan",IF(CJ5=80%,"Selesai Pengembangan",IF(CJ5<87.5%,"Proses SIT",IF(CJ5=87.5%,"Selesai SIT",IF(CJ5<95%,"Proses UAT",IF(CJ5=95%,"Selesai UAT",IF(CJ5<100%,"Proses Implementasi","Selesai Implementasi")))))))))))))))))))))) -> Not Started | ... CB5: =IF(CN5=0%,"Not Started",IF(CN5<5%,"Proses RBT-RBB",IF(CN5=5%,"Selesai RBT-RBB",IF(CN5<10%,"Proses RBT-RBL",IF(CN5=10%,"Selesai RBT-RBL",IF(CN5<15%,"Proses RBT-RBTD",IF(CN5=15%,"Selesai RBT-RBTD",IF(CN5<20%,"Proses RPP",IF(CN5=20%,"Selesai RPP",IF(CN5<25%,"Proses KAK",IF(CN5=25%,"Selesai KAK",IF(CN5<30%,"Proses Pengadaan",IF(CN5=30%,"Selesai Pengadaan",IF(CN5<45%,"Proses Desain",IF(CN5=45%,"Selesai Desain",IF(CN5<80%,"Proses Pengembangan",IF(CN5=80%,"Selesai Pengembangan",IF(CN5<87.5%,"Proses SIT",IF(CN5=87.5%,"Selesai SIT",IF(CN5<95%,"Proses UAT",IF(CN5=95%,"Selesai UAT",IF(CN5<100%,"Proses Implementasi","Selesai Implementasi")))))))))))))))))))))) -> Not Started | CL5: 0 | CM5: =(($DY5/100%)*15%)+(($DZ5/100%)*5%)+(($EA5/100%)*5%)+(($EB5/100%)*5%)+(($EC5/100%)*15%)+(($ED5/100%)*35%)+(($EE5/100%)*7.5%)+(($EF5/100%)*7.5%)+(($EG5/100%)*5%) -> 0 | CN5: =(($DY5/100%)*15%)+(($DZ5/100%)*5%)+(($EA5/100%)*5%)+(($EB5/100%)*5%)+(($EC5/100%)*15%)+(($ED5/100%)*35%)+(($EE5/100%)*7.5%)+(($EF5/100%)*7.5%)+(($EG5/100%)*5%) -> 0 | CO5: =IF(BE5=0%, 100%, (CC5/BE5)) -> 1 | CP5: =IF(BF5=0%, 100%, (CD5/BF5)) -> 1 | CQ5: =IF(BG5=0%, 100%, (CE5/BG5)) -> 1 | CR5: =IF(BH5=0%, 100%, (CF5/BH5)) -> 1 | CS5: =IF(BI5=0%, 100%, (CG5/BI5)) -> 1 | CT5: =IF(BJ5=0%, 100%, (CH5/BJ5)) -> 1 | CU5: =IF(BK5=0%, 100%, (CI5/BK5)) -> 1 | CV5: =IF(BL5=0%, 100%, (CJ5/BL5)) -> 1 | ... CY5: =IF(BO5=0%, 100%, (CM5/BO5)) -> 1 | DA5: =IF(BE5=0%,"NS",IF(CC5=100%,"DONE",IF(CO5>100%,"AS",IF(CO5<75%,"BS",IF(CO5<89.9%,"AR","OS"))))) -> NS | DB5: =IF(BF5=0%,"NS",IF(CD5=100%,"DONE",IF(CP5>100%,"AS",IF(CP5<75%,"BS",IF(CP5<89.9%,"AR","OS"))))) -> NS | DC5: =IF(BG5=0%,"NS",IF(CE5=100%,"DONE",IF(CQ5>100%,"AS",IF(CQ5<75%,"BS",IF(CQ5<89.9%,"AR","OS"))))) -> NS | DD5: =IF(BH5=0%,"NS",IF(CF5=100%,"DONE",IF(CR5>100%,"AS",IF(CR5<75%,"BS",IF(CR5<89.9%,"AR","OS"))))) -> NS | DE5: =IF(BI5=0%,"NS",IF(CG5=100%,"DONE",IF(CS5>100%,"AS",IF(CS5<75%,"BS",IF(CS5<89.9%,"AR","OS"))))) -> NS | DF5: =IF(BJ5=0%,"NS",IF(CH5=100%,"DONE",IF(CT5>100%,"AS",IF(CT5<75%,"BS",IF(CT5<89.9%,"AR","OS"))))) -> NS | DG5: =IF(BK5=0%,"NS",IF(CI5=100%,"DONE",IF(CU5>100%,"AS",IF(CU5<75%,"BS",IF(CU5<89.9%,"AR","OS"))))) -> NS | DH5: =IF(BL5=0%,"NS",IF(CJ5=100%,"DONE",IF(CV5>100%,"AS",IF(CV5<75%,"BS",IF(CV5<89.9%,"AR","OS"))))) -> NS | ... DL5: =IF(BP5=0%,"NS",IF(CN5=100%,"DONE",IF(CZ5>100%,"AS",IF(CZ5<75%,"BS",IF(CZ5<89.9%,"AR","OS"))))) -> NS | DM5: =CC5/$BP5 -> #DIV/0! | DN5: =CD5/$BP5 -> #DIV/0! | DO5: =CE5/$BP5 -> #DIV/0! | DP5: =CF5/$BP5 -> #DIV/0! | DQ5: =CG5/$BP5 -> #DIV/0! | DR5: =CH5/$BP5 -> #DIV/0! | DS5: =CI5/$BP5 -> #DIV/0! | DT5: =CJ5/$BP5 -> #DIV/0! | ... DX5: =CN5/$BP5 -> #DIV/0! | EJ5: =AR5 -> 47391 | FM5: 1. Faradilla Anggun S. 2. Muhammad Daffa Alfarizqi | FN5: Rizky Arga | FO5: Among Rogo Wicaksono | FP5: TBC | FQ5: Dian | FR5: Outsource
A6: RIVIBI-PPA-P5-3-DLDS | B6: PT2, BPPU | C6: IDT | D6: Continuity Technology | E6: P-4 | F6: 1 | G6: Pengembangan Product PUVA dan Penerbitan SBN | H6: Infrastruktur Data PUVA | I6: Capturing Matchmaking OIS | J6: 2025 | K6: 2025 | L6: S | M6: K3 | N6: Pemimpin Satker | O6: DPPK, DSTA, DPKL | P6: PPLBI | Q6: Moneter | R6: ANTASENA | S6: =BQ6 -> Selesai Implementasi | T6: =IF(V6=0%,"Not Started",IF(V6<100%,"On Progress",IF(V6=100%,"DONE"))) -> DONE | U6: =FN6 -> Rifanda Yulio | V6: =CC6 -> 1 | W6: TW I 2025 | X6: =AR6 -> 45899 | Y6: 0 | AA6: 45658 | AB6: 45688 | AC6: 45689 | AD6: 45709 | AI6: 45719 | AJ6: 45744 | AK6: 45754 | AL6: 45807 | AM6: 45810 | AN6: 45838 | AO6: 45839 | AP6: 45883 | AQ6: 45884 | AR6: 45899 | AS6: =IF(BE6=0%,"Not Started",IF(BE6<5%,"Proses RBT-RBB",IF(BE6=5%,"Selesai RBT-RBB",IF(BE6<10%,"Proses RBT-RBL",IF(BE6=10%,"Selesai RBT-RBL",IF(BE6<15%,"Proses RBT-RBTD",IF(BE6=15%,"Selesai RBT-RBTD",IF(BE6<20%,"Proses RPP",IF(BE6=20%,"Selesai RPP",IF(BE6<25%,"Proses KAK",IF(BE6=25%,"Selesai KAK",IF(BE6<30%,"Proses Pengadaan",IF(BE6=30%,"Selesai Pengadaan",IF(BE6<45%,"Proses Desain",IF(BE6=45%,"Selesai Desain",IF(BE6<80%,"Proses Pengembangan",IF(BE6=80%,"Selesai Pengembangan",IF(BE6<87.5%,"Proses SIT",IF(BE6=87.5%,"Selesai SIT",IF(BE6<95%,"Proses UAT",IF(BE6=95%,"Selesai UAT",IF(BE6<100%,"Proses Implementasi","Selesai Implementasi")))))))))))))))))))))) -> Selesai Implementasi | AT6: =IF(BF6=0%,"Not Started",IF(BF6<5%,"Proses RBT-RBB",IF(BF6=5%,"Selesai RBT-RBB",IF(BF6<10%,"Proses RBT-RBL",IF(BF6=10%,"Selesai RBT-RBL",IF(BF6<15%,"Proses RBT-RBTD",IF(BF6=15%,"Selesai RBT-RBTD",IF(BF6<20%,"Proses RPP",IF(BF6=20%,"Selesai RPP",IF(BF6<25%,"Proses KAK",IF(BF6=25%,"Selesai KAK",IF(BF6<30%,"Proses Pengadaan",IF(BF6=30%,"Selesai Pengadaan",IF(BF6<45%,"Proses Desain",IF(BF6=45%,"Selesai Desain",IF(BF6<80%,"Proses Pengembangan",IF(BF6=80%,"Selesai Pengembangan",IF(BF6<87.5%,"Proses SIT",IF(BF6=87.5%,"Selesai SIT",IF(BF6<95%,"Proses UAT",IF(BF6=95%,"Selesai UAT",IF(BF6<100%,"Proses Implementasi","Selesai Implementasi")))))))))))))))))))))) -> Selesai Implementasi | AU6: =IF(BG6=0%,"Not Started",IF(BG6<5%,"Proses RBT-RBB",IF(BG6=5%,"Selesai RBT-RBB",IF(BG6<10%,"Proses RBT-RBL",IF(BG6=10%,"Selesai RBT-RBL",IF(BG6<15%,"Proses RBT-RBTD",IF(BG6=15%,"Selesai RBT-RBTD",IF(BG6<20%,"Proses RPP",IF(BG6=20%,"Selesai RPP",IF(BG6<25%,"Proses KAK",IF(BG6=25%,"Selesai KAK",IF(BG6<30%,"Proses Pengadaan",IF(BG6=30%,"Selesai Pengadaan",IF(BG6<45%,"Proses Desain",IF(BG6=45%,"Selesai Desain",IF(BG6<80%,"Proses Pengembangan",IF(BG6=80%,"Selesai Pengembangan",IF(BG6<87.5%,"Proses SIT",IF(BG6=87.5%,"Selesai SIT",IF(BG6<95%,"Proses UAT",IF(BG6=95%,"Selesai UAT",IF(BG6<100%,"Proses Implementasi","Selesai Implementasi")))))))))))))))))))))) -> Selesai Implementasi | AV6: =IF(BH6=0%,"Not Started",IF(BH6<5%,"Proses RBT-RBB",IF(BH6=5%,"Selesai RBT-RBB",IF(BH6<10%,"Proses RBT-RBL",IF(BH6=10%,"Selesai RBT-RBL",IF(BH6<15%,"Proses RBT-RBTD",IF(BH6=15%,"Selesai RBT-RBTD",IF(BH6<20%,"Proses RPP",IF(BH6=20%,"Selesai RPP",IF(BH6<25%,"Proses KAK",IF(BH6=25%,"Selesai KAK",IF(BH6<30%,"Proses Pengadaan",IF(BH6=30%,"Selesai Pengadaan",IF(BH6<45%,"Proses Desain",IF(BH6=45%,"Selesai Desain",IF(BH6<80%,"Proses Pengembangan",IF(BH6=80%,"Selesai Pengembangan",IF(BH6<87.5%,"Proses SIT",IF(BH6=87.5%,"Selesai SIT",IF(BH6<95%,"Proses UAT",IF(BH6=95%,"Selesai UAT",IF(BH6<100%,"Proses Implementasi","Selesai Implementasi")))))))))))))))))))))) -> Selesai Implementasi | AW6: =IF(BI6=0%,"Not Started",IF(BI6<5%,"Proses RBT-RBB",IF(BI6=5%,"Selesai RBT-RBB",IF(BI6<10%,"Proses RBT-RBL",IF(BI6=10%,"Selesai RBT-RBL",IF(BI6<15%,"Proses RBT-RBTD",IF(BI6=15%,"Selesai RBT-RBTD",IF(BI6<20%,"Proses RPP",IF(BI6=20%,"Selesai RPP",IF(BI6<25%,"Proses KAK",IF(BI6=25%,"Selesai KAK",IF(BI6<30%,"Proses Pengadaan",IF(BI6=30%,"Selesai Pengadaan",IF(BI6<45%,"Proses Desain",IF(BI6=45%,"Selesai Desain",IF(BI6<80%,"Proses Pengembangan",IF(BI6=80%,"Selesai Pengembangan",IF(BI6<87.5%,"Proses SIT",IF(BI6=87.5%,"Selesai SIT",IF(BI6<95%,"Proses UAT",IF(BI6=95%,"Selesai UAT",IF(BI6<100%,"Proses Implementasi","Selesai Implementasi")))))))))))))))))))))) -> Selesai Implementasi | AX6: =IF(BJ6=0%,"Not Started",IF(BJ6<5%,"Proses RBT-RBB",IF(BJ6=5%,"Selesai RBT-RBB",IF(BJ6<10%,"Proses RBT-RBL",IF(BJ6=10%,"Selesai RBT-RBL",IF(BJ6<15%,"Proses RBT-RBTD",IF(BJ6=15%,"Selesai RBT-RBTD",IF(BJ6<20%,"Proses RPP",IF(BJ6=20%,"Selesai RPP",IF(BJ6<25%,"Proses KAK",IF(BJ6=25%,"Selesai KAK",IF(BJ6<30%,"Proses Pengadaan",IF(BJ6=30%,"Selesai Pengadaan",IF(BJ6<45%,"Proses Desain",IF(BJ6=45%,"Selesai Desain",IF(BJ6<80%,"Proses Pengembangan",IF(BJ6=80%,"Selesai Pengembangan",IF(BJ6<87.5%,"Proses SIT",IF(BJ6=87.5%,"Selesai SIT",IF(BJ6<95%,"Proses UAT",IF(BJ6=95%,"Selesai UAT",IF(BJ6<100%,"Proses Implementasi","Selesai Implementasi")))))))))))))))))))))) -> Selesai Implementasi | AY6: =IF(BK6=0%,"Not Started",IF(BK6<5%,"Proses RBT-RBB",IF(BK6=5%,"Selesai RBT-RBB",IF(BK6<10%,"Proses RBT-RBL",IF(BK6=10%,"Selesai RBT-RBL",IF(BK6<15%,"Proses RBT-RBTD",IF(BK6=15%,"Selesai RBT-RBTD",IF(BK6<20%,"Proses RPP",IF(BK6=20%,"Selesai RPP",IF(BK6<25%,"Proses KAK",IF(BK6=25%,"Selesai KAK",IF(BK6<30%,"Proses Pengadaan",IF(BK6=30%,"Selesai Pengadaan",IF(BK6<45%,"Proses Desain",IF(BK6=45%,"Selesai Desain",IF(BK6<80%,"Proses Pengembangan",IF(BK6=80%,"Selesai Pengembangan",IF(BK6<87.5%,"Proses SIT",IF(BK6=87.5%,"Selesai SIT",IF(BK6<95%,"Proses UAT",IF(BK6=95%,"Selesai UAT",IF(BK6<100%,"Proses Implementasi","Selesai Implementasi")))))))))))))))))))))) -> Selesai Implementasi | AZ6: =IF(BL6=0%,"Not Started",IF(BL6<5%,"Proses RBT-RBB",IF(BL6=5%,"Selesai RBT-RBB",IF(BL6<10%,"Proses RBT-RBL",IF(BL6=10%,"Selesai RBT-RBL",IF(BL6<15%,"Proses RBT-RBTD",IF(BL6=15%,"Selesai RBT-RBTD",IF(BL6<20%,"Proses RPP",IF(BL6=20%,"Selesai RPP",IF(BL6<25%,"Proses KAK",IF(BL6=25%,"Selesai KAK",IF(BL6<30%,"Proses Pengadaan",IF(BL6=30%,"Selesai Pengadaan",IF(BL6<45%,"Proses Desain",IF(BL6=45%,"Selesai Desain",IF(BL6<80%,"Proses Pengembangan",IF(BL6=80%,"Selesai Pengembangan",IF(BL6<87.5%,"Proses SIT",IF(BL6=87.5%,"Selesai SIT",IF(BL6<95%,"Proses UAT",IF(BL6=95%,"Selesai UAT",IF(BL6<100%,"Proses Implementasi","Selesai Implementasi")))))))))))))))))))))) -> Selesai Implementasi | ... BD6: =IF(BP6=0%,"Not Started",IF(BP6<5%,"Proses RBT-RBB",IF(BP6=5%,"Selesai RBT-RBB",IF(BP6<10%,"Proses RBT-RBL",IF(BP6=10%,"Selesai RBT-RBL",IF(BP6<15%,"Proses RBT-RBTD",IF(BP6=15%,"Selesai RBT-RBTD",IF(BP6<20%,"Proses RPP",IF(BP6=20%,"Selesai RPP",IF(BP6<25%,"Proses KAK",IF(BP6=25%,"Selesai KAK",IF(BP6<30%,"Proses Pengadaan",IF(BP6=30%,"Selesai Pengadaan",IF(BP6<45%,"Proses Desain",IF(BP6=45%,"Selesai Desain",IF(BP6<80%,"Proses Pengembangan",IF(BP6=80%,"Selesai Pengembangan",IF(BP6<87.5%,"Proses SIT",IF(BP6=87.5%,"Selesai SIT",IF(BP6<95%,"Proses UAT",IF(BP6=95%,"Selesai UAT",IF(BP6<100%,"Proses Implementasi","Selesai Implementasi")))))))))))))))))))))) -> Selesai Implementasi | BE6: 1 | BF6: 1 | BG6: 1 | BH6: 1 | BI6: 1 | BJ6: 1 | BK6: 1 | BL6: 1 | BM6: 1 | BN6: 1 | BO6: 1 | BP6: 1 | BQ6: =IF(CC6=0%,"Not Started",IF(CC6<5%,"Proses RBT-RBB",IF(CC6=5%,"Selesai RBT-RBB",IF(CC6<10%,"Proses RBT-RBL",IF(CC6=10%,"Selesai RBT-RBL",IF(CC6<15%,"Proses RBT-RBTD",IF(CC6=15%,"Selesai RBT-RBTD",IF(CC6<20%,"Proses RPP",IF(CC6=20%,"Selesai RPP",IF(CC6<25%,"Proses KAK",IF(CC6=25%,"Selesai KAK",IF(CC6<30%,"Proses Pengadaan",IF(CC6=30%,"Selesai Pengadaan",IF(CC6<45%,"Proses Desain",IF(CC6=45%,"Selesai Desain",IF(CC6<80%,"Proses Pengembangan",IF(CC6=80%,"Selesai Pengembangan",IF(CC6<87.5%,"Proses SIT",IF(CC6=87.5%,"Selesai SIT",IF(CC6<95%,"Proses UAT",IF(CC6=95%,"Selesai UAT",IF(CC6<100%,"Proses Implementasi","Selesai Implementasi")))))))))))))))))))))) -> Selesai Implementasi | BR6: =IF(CD6=0%,"Not Started",IF(CD6<5%,"Proses RBT-RBB",IF(CD6=5%,"Selesai RBT-RBB",IF(CD6<10%,"Proses RBT-RBL",IF(CD6=10%,"Selesai RBT-RBL",IF(CD6<15%,"Proses RBT-RBTD",IF(CD6=15%,"Selesai RBT-RBTD",IF(CD6<20%,"Proses RPP",IF(CD6=20%,"Selesai RPP",IF(CD6<25%,"Proses KAK",IF(CD6=25%,"Selesai KAK",IF(CD6<30%,"Proses Pengadaan",IF(CD6=30%,"Selesai Pengadaan",IF(CD6<45%,"Proses Desain",IF(CD6=45%,"Selesai Desain",IF(CD6<80%,"Proses Pengembangan",IF(CD6=80%,"Selesai Pengembangan",IF(CD6<87.5%,"Proses SIT",IF(CD6=87.5%,"Selesai SIT",IF(CD6<95%,"Proses UAT",IF(CD6=95%,"Selesai UAT",IF(CD6<100%,"Proses Implementasi","Selesai Implementasi")))))))))))))))))))))) -> Not Started | BS6: =IF(CE6=0%,"Not Started",IF(CE6<5%,"Proses RBT-RBB",IF(CE6=5%,"Selesai RBT-RBB",IF(CE6<10%,"Proses RBT-RBL",IF(CE6=10%,"Selesai RBT-RBL",IF(CE6<15%,"Proses RBT-RBTD",IF(CE6=15%,"Selesai RBT-RBTD",IF(CE6<20%,"Proses RPP",IF(CE6=20%,"Selesai RPP",IF(CE6<25%,"Proses KAK",IF(CE6=25%,"Selesai KAK",IF(CE6<30%,"Proses Pengadaan",IF(CE6=30%,"Selesai Pengadaan",IF(CE6<45%,"Proses Desain",IF(CE6=45%,"Selesai Desain",IF(CE6<80%,"Proses Pengembangan",IF(CE6=80%,"Selesai Pengembangan",IF(CE6<87.5%,"Proses SIT",IF(CE6=87.5%,"Selesai SIT",IF(CE6<95%,"Proses UAT",IF(CE6=95%,"Selesai UAT",IF(CE6<100%,"Proses Implementasi","Selesai Implementasi")))))))))))))))))))))) -> Not Started | BT6: =IF(CF6=0%,"Not Started",IF(CF6<5%,"Proses RBT-RBB",IF(CF6=5%,"Selesai RBT-RBB",IF(CF6<10%,"Proses RBT-RBL",IF(CF6=10%,"Selesai RBT-RBL",IF(CF6<15%,"Proses RBT-RBTD",IF(CF6=15%,"Selesai RBT-RBTD",IF(CF6<20%,"Proses RPP",IF(CF6=20%,"Selesai RPP",IF(CF6<25%,"Proses KAK",IF(CF6=25%,"Selesai KAK",IF(CF6<30%,"Proses Pengadaan",IF(CF6=30%,"Selesai Pengadaan",IF(CF6<45%,"Proses Desain",IF(CF6=45%,"Selesai Desain",IF(CF6<80%,"Proses Pengembangan",IF(CF6=80%,"Selesai Pengembangan",IF(CF6<87.5%,"Proses SIT",IF(CF6=87.5%,"Selesai SIT",IF(CF6<95%,"Proses UAT",IF(CF6=95%,"Selesai UAT",IF(CF6<100%,"Proses Implementasi","Selesai Implementasi")))))))))))))))))))))) -> Not Started | BU6: =IF(CG6=0%,"Not Started",IF(CG6<5%,"Proses RBT-RBB",IF(CG6=5%,"Selesai RBT-RBB",IF(CG6<10%,"Proses RBT-RBL",IF(CG6=10%,"Selesai RBT-RBL",IF(CG6<15%,"Proses RBT-RBTD",IF(CG6=15%,"Selesai RBT-RBTD",IF(CG6<20%,"Proses RPP",IF(CG6=20%,"Selesai RPP",IF(CG6<25%,"Proses KAK",IF(CG6=25%,"Selesai KAK",IF(CG6<30%,"Proses Pengadaan",IF(CG6=30%,"Selesai Pengadaan",IF(CG6<45%,"Proses Desain",IF(CG6=45%,"Selesai Desain",IF(CG6<80%,"Proses Pengembangan",IF(CG6=80%,"Selesai Pengembangan",IF(CG6<87.5%,"Proses SIT",IF(CG6=87.5%,"Selesai SIT",IF(CG6<95%,"Proses UAT",IF(CG6=95%,"Selesai UAT",IF(CG6<100%,"Proses Implementasi","Selesai Implementasi")))))))))))))))))))))) -> Not Started | BV6: =IF(CH6=0%,"Not Started",IF(CH6<5%,"Proses RBT-RBB",IF(CH6=5%,"Selesai RBT-RBB",IF(CH6<10%,"Proses RBT-RBL",IF(CH6=10%,"Selesai RBT-RBL",IF(CH6<15%,"Proses RBT-RBTD",IF(CH6=15%,"Selesai RBT-RBTD",IF(CH6<20%,"Proses RPP",IF(CH6=20%,"Selesai RPP",IF(CH6<25%,"Proses KAK",IF(CH6=25%,"Selesai KAK",IF(CH6<30%,"Proses Pengadaan",IF(CH6=30%,"Selesai Pengadaan",IF(CH6<45%,"Proses Desain",IF(CH6=45%,"Selesai Desain",IF(CH6<80%,"Proses Pengembangan",IF(CH6=80%,"Selesai Pengembangan",IF(CH6<87.5%,"Proses SIT",IF(CH6=87.5%,"Selesai SIT",IF(CH6<95%,"Proses UAT",IF(CH6=95%,"Selesai UAT",IF(CH6<100%,"Proses Implementasi","Selesai Implementasi")))))))))))))))))))))) -> Not Started | BW6: =IF(CI6=0%,"Not Started",IF(CI6<5%,"Proses RBT-RBB",IF(CI6=5%,"Selesai RBT-RBB",IF(CI6<10%,"Proses RBT-RBL",IF(CI6=10%,"Selesai RBT-RBL",IF(CI6<15%,"Proses RBT-RBTD",IF(CI6=15%,"Selesai RBT-RBTD",IF(CI6<20%,"Proses RPP",IF(CI6=20%,"Selesai RPP",IF(CI6<25%,"Proses KAK",IF(CI6=25%,"Selesai KAK",IF(CI6<30%,"Proses Pengadaan",IF(CI6=30%,"Selesai Pengadaan",IF(CI6<45%,"Proses Desain",IF(CI6=45%,"Selesai Desain",IF(CI6<80%,"Proses Pengembangan",IF(CI6=80%,"Selesai Pengembangan",IF(CI6<87.5%,"Proses SIT",IF(CI6=87.5%,"Selesai SIT",IF(CI6<95%,"Proses UAT",IF(CI6=95%,"Selesai UAT",IF(CI6<100%,"Proses Implementasi","Selesai Implementasi")))))))))))))))))))))) -> Not Started | BX6: =IF(CJ6=0%,"Not Started",IF(CJ6<5%,"Proses RBT-RBB",IF(CJ6=5%,"Selesai RBT-RBB",IF(CJ6<10%,"Proses RBT-RBL",IF(CJ6=10%,"Selesai RBT-RBL",IF(CJ6<15%,"Proses RBT-RBTD",IF(CJ6=15%,"Selesai RBT-RBTD",IF(CJ6<20%,"Proses RPP",IF(CJ6=20%,"Selesai RPP",IF(CJ6<25%,"Proses KAK",IF(CJ6=25%,"Selesai KAK",IF(CJ6<30%,"Proses Pengadaan",IF(CJ6=30%,"Selesai Pengadaan",IF(CJ6<45%,"Proses Desain",IF(CJ6=45%,"Selesai Desain",IF(CJ6<80%,"Proses Pengembangan",IF(CJ6=80%,"Selesai Pengembangan",IF(CJ6<87.5%,"Proses SIT",IF(CJ6=87.5%,"Selesai SIT",IF(CJ6<95%,"Proses UAT",IF(CJ6=95%,"Selesai UAT",IF(CJ6<100%,"Proses Implementasi","Selesai Implementasi")))))))))))))))))))))) -> Not Started | ... CB6: =IF(CN6=0%,"Not Started",IF(CN6<5%,"Proses RBT-RBB",IF(CN6=5%,"Selesai RBT-RBB",IF(CN6<10%,"Proses RBT-RBL",IF(CN6=10%,"Selesai RBT-RBL",IF(CN6<15%,"Proses RBT-RBTD",IF(CN6=15%,"Selesai RBT-RBTD",IF(CN6<20%,"Proses RPP",IF(CN6=20%,"Selesai RPP",IF(CN6<25%,"Proses KAK",IF(CN6=25%,"Selesai KAK",IF(CN6<30%,"Proses Pengadaan",IF(CN6=30%,"Selesai Pengadaan",IF(CN6<45%,"Proses Desain",IF(CN6=45%,"Selesai Desain",IF(CN6<80%,"Proses Pengembangan",IF(CN6=80%,"Selesai Pengembangan",IF(CN6<87.5%,"Proses SIT",IF(CN6=87.5%,"Selesai SIT",IF(CN6<95%,"Proses UAT",IF(CN6=95%,"Selesai UAT",IF(CN6<100%,"Proses Implementasi","Selesai Implementasi")))))))))))))))))))))) -> Not Started | CC6: =(($DY6/100%)*15%)+(($DZ6/100%)*5%)+(($EA6/100%)*5%)+(($EB6/100%)*5%)+(($EC6/100%)*15%)+(($ED6/100%)*35%)+(($EE6/100%)*7.5%)+(($EF6/100%)*7.5%)+(($EG6/100%)*5%) -> 1 | CO6: =IF(BE6=0%, 100%, (CC6/BE6)) -> 1 | CP6: =IF(BF6=0%, 100%, (CD6/BF6)) -> 0 | CQ6: =IF(BG6=0%, 100%, (CE6/BG6)) -> 0 | CR6: =IF(BH6=0%, 100%, (CF6/BH6)) -> 0 | CS6: =IF(BI6=0%, 100%, (CG6/BI6)) -> 0 | CT6: =IF(BJ6=0%, 100%, (CH6/BJ6)) -> 0 | CU6: =IF(BK6=0%, 100%, (CI6/BK6)) -> 0 | CV6: =IF(BL6=0%, 100%, (CJ6/BL6)) -> 0 | ... CY6: =IF(BO6=0%, 100%, (CM6/BO6)) -> 0 | DA6: =IF(BE6=0%,"NS",IF(CC6=100%,"DONE",IF(CO6>100%,"AS",IF(CO6<75%,"BS",IF(CO6<89.9%,"AR","OS"))))) -> DONE | DB6: =IF(BF6=0%,"NS",IF(CD6=100%,"DONE",IF(CP6>100%,"AS",IF(CP6<75%,"BS",IF(CP6<89.9%,"AR","OS"))))) -> BS | DC6: =IF(BG6=0%,"NS",IF(CE6=100%,"DONE",IF(CQ6>100%,"AS",IF(CQ6<75%,"BS",IF(CQ6<89.9%,"AR","OS"))))) -> BS | DD6: =IF(BH6=0%,"NS",IF(CF6=100%,"DONE",IF(CR6>100%,"AS",IF(CR6<75%,"BS",IF(CR6<89.9%,"AR","OS"))))) -> BS | DE6: =IF(BI6=0%,"NS",IF(CG6=100%,"DONE",IF(CS6>100%,"AS",IF(CS6<75%,"BS",IF(CS6<89.9%,"AR","OS"))))) -> BS | DF6: =IF(BJ6=0%,"NS",IF(CH6=100%,"DONE",IF(CT6>100%,"AS",IF(CT6<75%,"BS",IF(CT6<89.9%,"AR","OS"))))) -> BS | DG6: =IF(BK6=0%,"NS",IF(CI6=100%,"DONE",IF(CU6>100%,"AS",IF(CU6<75%,"BS",IF(CU6<89.9%,"AR","OS"))))) -> BS | DH6: =IF(BL6=0%,"NS",IF(CJ6=100%,"DONE",IF(CV6>100%,"AS",IF(CV6<75%,"BS",IF(CV6<89.9%,"AR","OS"))))) -> BS | ... DL6: =IF(BP6=0%,"NS",IF(CN6=100%,"DONE",IF(CZ6>100%,"AS",IF(CZ6<75%,"BS",IF(CZ6<89.9%,"AR","OS"))))) -> BS | DM6: =CC6/$BP6 -> 1 | DN6: =CD6/$BP6 -> 0 | DO6: =CE6/$BP6 -> 0 | DP6: =CF6/$BP6 -> 0 | DQ6: =CG6/$BP6 -> 0 | DR6: =CH6/$BP6 -> 0 | DS6: =CI6/$BP6 -> 0 | DT6: =CJ6/$BP6 -> 0 | ... DX6: =CN6/$BP6 -> 0 | DY6: 1 | DZ6: 1 | EA6: 1 | EB6: 1 | EC6: 1 | ED6: 1 | EE6: 1 | EF6: 1 | EG6: 1 | EH6: - Telah deploy pada 16 Agustus 2025 - Telah dilakukan penandatanganan perjanjian induk derivatif dan launching matchmaking OIS pada 26 September 2025 - Akan diimplementasikan setelah implementasi BI-FRN, dan menunggu informasi lebih lanjut dari DPPK | EI6: 45926 | EJ6: =AR6 -> 45899 | EO6: RPP masih dalam bentuk draf, mandays di sisi LBUT masih dalam diskusi karena ada perubahan pengembang dari ext vendor menjadi inhouse | FA6: Segera melakukan diskusi internal dengan KPPA, KMBD dan Opda | FM6: 1. Regi Wibowo 2. Titik Rahayu | FN6: Rifanda Yulio | FO6: Adinda Tri Wulandari | FP6: 1. Haryani Diah 2. Alamsyah 3. Luluk Mukarromah | FQ6: Agung | FR6: Inhouse | FT6: Fajri (KPPA) Teo (KPPA) Timo (KPPA) Risda (KPPA) Diah (KMBD) | FU6: 7
B7: PT2, BPPU | C7: IDT | D7: Continuity Technology | E7: P-4 | F7: =F6+1 -> 2 | G7: Pengembangan Product PUVA dan Penerbitan SBN | H7: Infrastruktur Data PUVA | I7: DEP Capturing Product -Capturing transaksi Repo, OIS, DNDF dari ETP-MO | J7: 2026 | K7: 2027 | L7: S | M7: K3 | N7: Pemimpin Satker | O7: DPPK | P7: WG-2 | Q7: Moneter, Market | R7: TBD | S7: =BQ7 -> Not Started | T7: =IF(V7=0%,"Not Started",IF(V7<100%,"On Progress",IF(V7=100%,"DONE"))) -> Not Started | U7: =FN7 -> Helen Desyani | V7: =CC7 -> 0 | W7: TW II 2026 | X7: =AR7 -> 46568 | Z7: New | AA7: 46113 | AB7: 46203 | AC7: 46204 | AD7: 46234 | AE7: 46204 | AF7: 46234 | AI7: 46235 | AJ7: 46264 | AK7: 46266 | AL7: 46446 | AM7: 46447 | AN7: 46492 | AO7: 46493 | AP7: 46538 | AQ7: 46539 | AR7: 46568 | AS7: =IF(BE7=0%,"Not Started",IF(BE7<5%,"Proses RBT-RBB",IF(BE7=5%,"Selesai RBT-RBB",IF(BE7<10%,"Proses RBT-RBL",IF(BE7=10%,"Selesai RBT-RBL",IF(BE7<15%,"Proses RBT-RBTD",IF(BE7=15%,"Selesai RBT-RBTD",IF(BE7<20%,"Proses RPP",IF(BE7=20%,"Selesai RPP",IF(BE7<25%,"Proses KAK",IF(BE7=25%,"Selesai KAK",IF(BE7<30%,"Proses Pengadaan",IF(BE7=30%,"Selesai Pengadaan",IF(BE7<45%,"Proses Desain",IF(BE7=45%,"Selesai Desain",IF(BE7<80%,"Proses Pengembangan",IF(BE7=80%,"Selesai Pengembangan",IF(BE7<87.5%,"Proses SIT",IF(BE7=87.5%,"Selesai SIT",IF(BE7<95%,"Proses UAT",IF(BE7=95%,"Selesai UAT",IF(BE7<100%,"Proses Implementasi","Selesai Implementasi")))))))))))))))))))))) -> Not Started | AT7: =IF(BF7=0%,"Not Started",IF(BF7<5%,"Proses RBT-RBB",IF(BF7=5%,"Selesai RBT-RBB",IF(BF7<10%,"Proses RBT-RBL",IF(BF7=10%,"Selesai RBT-RBL",IF(BF7<15%,"Proses RBT-RBTD",IF(BF7=15%,"Selesai RBT-RBTD",IF(BF7<20%,"Proses RPP",IF(BF7=20%,"Selesai RPP",IF(BF7<25%,"Proses KAK",IF(BF7=25%,"Selesai KAK",IF(BF7<30%,"Proses Pengadaan",IF(BF7=30%,"Selesai Pengadaan",IF(BF7<45%,"Proses Desain",IF(BF7=45%,"Selesai Desain",IF(BF7<80%,"Proses Pengembangan",IF(BF7=80%,"Selesai Pengembangan",IF(BF7<87.5%,"Proses SIT",IF(BF7=87.5%,"Selesai SIT",IF(BF7<95%,"Proses UAT",IF(BF7=95%,"Selesai UAT",IF(BF7<100%,"Proses Implementasi","Selesai Implementasi")))))))))))))))))))))) -> Not Started | AU7: =IF(BG7=0%,"Not Started",IF(BG7<5%,"Proses RBT-RBB",IF(BG7=5%,"Selesai RBT-RBB",IF(BG7<10%,"Proses RBT-RBL",IF(BG7=10%,"Selesai RBT-RBL",IF(BG7<15%,"Proses RBT-RBTD",IF(BG7=15%,"Selesai RBT-RBTD",IF(BG7<20%,"Proses RPP",IF(BG7=20%,"Selesai RPP",IF(BG7<25%,"Proses KAK",IF(BG7=25%,"Selesai KAK",IF(BG7<30%,"Proses Pengadaan",IF(BG7=30%,"Selesai Pengadaan",IF(BG7<45%,"Proses Desain",IF(BG7=45%,"Selesai Desain",IF(BG7<80%,"Proses Pengembangan",IF(BG7=80%,"Selesai Pengembangan",IF(BG7<87.5%,"Proses SIT",IF(BG7=87.5%,"Selesai SIT",IF(BG7<95%,"Proses UAT",IF(BG7=95%,"Selesai UAT",IF(BG7<100%,"Proses Implementasi","Selesai Implementasi")))))))))))))))))))))) -> Not Started | AV7: =IF(BH7=0%,"Not Started",IF(BH7<5%,"Proses RBT-RBB",IF(BH7=5%,"Selesai RBT-RBB",IF(BH7<10%,"Proses RBT-RBL",IF(BH7=10%,"Selesai RBT-RBL",IF(BH7<15%,"Proses RBT-RBTD",IF(BH7=15%,"Selesai RBT-RBTD",IF(BH7<20%,"Proses RPP",IF(BH7=20%,"Selesai RPP",IF(BH7<25%,"Proses KAK",IF(BH7=25%,"Selesai KAK",IF(BH7<30%,"Proses Pengadaan",IF(BH7=30%,"Selesai Pengadaan",IF(BH7<45%,"Proses Desain",IF(BH7=45%,"Selesai Desain",IF(BH7<80%,"Proses Pengembangan",IF(BH7=80%,"Selesai Pengembangan",IF(BH7<87.5%,"Proses SIT",IF(BH7=87.5%,"Selesai SIT",IF(BH7<95%,"Proses UAT",IF(BH7=95%,"Selesai UAT",IF(BH7<100%,"Proses Implementasi","Selesai Implementasi")))))))))))))))))))))) -> Selesai RBT-RBB | AW7: =IF(BI7=0%,"Not Started",IF(BI7<5%,"Proses RBT-RBB",IF(BI7=5%,"Selesai RBT-RBB",IF(BI7<10%,"Proses RBT-RBL",IF(BI7=10%,"Selesai RBT-RBL",IF(BI7<15%,"Proses RBT-RBTD",IF(BI7=15%,"Selesai RBT-RBTD",IF(BI7<20%,"Proses RPP",IF(BI7=20%,"Selesai RPP",IF(BI7<25%,"Proses KAK",IF(BI7=25%,"Selesai KAK",IF(BI7<30%,"Proses Pengadaan",IF(BI7=30%,"Selesai Pengadaan",IF(BI7<45%,"Proses Desain",IF(BI7=45%,"Selesai Desain",IF(BI7<80%,"Proses Pengembangan",IF(BI7=80%,"Selesai Pengembangan",IF(BI7<87.5%,"Proses SIT",IF(BI7=87.5%,"Selesai SIT",IF(BI7<95%,"Proses UAT",IF(BI7=95%,"Selesai UAT",IF(BI7<100%,"Proses Implementasi","Selesai Implementasi")))))))))))))))))))))) -> Selesai RBT-RBL | AX7: =IF(BJ7=0%,"Not Started",IF(BJ7<5%,"Proses RBT-RBB",IF(BJ7=5%,"Selesai RBT-RBB",IF(BJ7<10%,"Proses RBT-RBL",IF(BJ7=10%,"Selesai RBT-RBL",IF(BJ7<15%,"Proses RBT-RBTD",IF(BJ7=15%,"Selesai RBT-RBTD",IF(BJ7<20%,"Proses RPP",IF(BJ7=20%,"Selesai RPP",IF(BJ7<25%,"Proses KAK",IF(BJ7=25%,"Selesai KAK",IF(BJ7<30%,"Proses Pengadaan",IF(BJ7=30%,"Selesai Pengadaan",IF(BJ7<45%,"Proses Desain",IF(BJ7=45%,"Selesai Desain",IF(BJ7<80%,"Proses Pengembangan",IF(BJ7=80%,"Selesai Pengembangan",IF(BJ7<87.5%,"Proses SIT",IF(BJ7=87.5%,"Selesai SIT",IF(BJ7<95%,"Proses UAT",IF(BJ7=95%,"Selesai UAT",IF(BJ7<100%,"Proses Implementasi","Selesai Implementasi")))))))))))))))))))))) -> Selesai RBT-RBTD | AY7: =IF(BK7=0%,"Not Started",IF(BK7<5%,"Proses RBT-RBB",IF(BK7=5%,"Selesai RBT-RBB",IF(BK7<10%,"Proses RBT-RBL",IF(BK7=10%,"Selesai RBT-RBL",IF(BK7<15%,"Proses RBT-RBTD",IF(BK7=15%,"Selesai RBT-RBTD",IF(BK7<20%,"Proses RPP",IF(BK7=20%,"Selesai RPP",IF(BK7<25%,"Proses KAK",IF(BK7=25%,"Selesai KAK",IF(BK7<30%,"Proses Pengadaan",IF(BK7=30%,"Selesai Pengadaan",IF(BK7<45%,"Proses Desain",IF(BK7=45%,"Selesai Desain",IF(BK7<80%,"Proses Pengembangan",IF(BK7=80%,"Selesai Pengembangan",IF(BK7<87.5%,"Proses SIT",IF(BK7=87.5%,"Selesai SIT",IF(BK7<95%,"Proses UAT",IF(BK7=95%,"Selesai UAT",IF(BK7<100%,"Proses Implementasi","Selesai Implementasi")))))))))))))))))))))) -> Selesai Pengadaan | AZ7: =IF(BL7=0%,"Not Started",IF(BL7<5%,"Proses RBT-RBB",IF(BL7=5%,"Selesai RBT-RBB",IF(BL7<10%,"Proses RBT-RBL",IF(BL7=10%,"Selesai RBT-RBL",IF(BL7<15%,"Proses RBT-RBTD",IF(BL7=15%,"Selesai RBT-RBTD",IF(BL7<20%,"Proses RPP",IF(BL7=20%,"Selesai RPP",IF(BL7<25%,"Proses KAK",IF(BL7=25%,"Selesai KAK",IF(BL7<30%,"Proses Pengadaan",IF(BL7=30%,"Selesai Pengadaan",IF(BL7<45%,"Proses Desain",IF(BL7=45%,"Selesai Desain",IF(BL7<80%,"Proses Pengembangan",IF(BL7=80%,"Selesai Pengembangan",IF(BL7<87.5%,"Proses SIT",IF(BL7=87.5%,"Selesai SIT",IF(BL7<95%,"Proses UAT",IF(BL7=95%,"Selesai UAT",IF(BL7<100%,"Proses Implementasi","Selesai Implementasi")))))))))))))))))))))) -> Proses Desain | ... BD7: =IF(BP7=0%,"Not Started",IF(BP7<5%,"Proses RBT-RBB",IF(BP7=5%,"Selesai RBT-RBB",IF(BP7<10%,"Proses RBT-RBL",IF(BP7=10%,"Selesai RBT-RBL",IF(BP7<15%,"Proses RBT-RBTD",IF(BP7=15%,"Selesai RBT-RBTD",IF(BP7<20%,"Proses RPP",IF(BP7=20%,"Selesai RPP",IF(BP7<25%,"Proses KAK",IF(BP7=25%,"Selesai KAK",IF(BP7<30%,"Proses Pengadaan",IF(BP7=30%,"Selesai Pengadaan",IF(BP7<45%,"Proses Desain",IF(BP7=45%,"Selesai Desain",IF(BP7<80%,"Proses Pengembangan",IF(BP7=80%,"Selesai Pengembangan",IF(BP7<87.5%,"Proses SIT",IF(BP7=87.5%,"Selesai SIT",IF(BP7<95%,"Proses UAT",IF(BP7=95%,"Selesai UAT",IF(BP7<100%,"Proses Implementasi","Selesai Implementasi")))))))))))))))))))))) -> Proses Pengembangan | BE7: 0 | BF7: 0 | BG7: 0 | BH7: 0.05 | BI7: 0.1 | BJ7: 0.15 | BK7: 0.3 | BL7: 0.4 | BM7: 0.46 | BN7: 0.52 | BO7: 0.58 | BP7: 0.64 | BQ7: =IF(CC7=0%,"Not Started",IF(CC7<5%,"Proses RBT-RBB",IF(CC7=5%,"Selesai RBT-RBB",IF(CC7<10%,"Proses RBT-RBL",IF(CC7=10%,"Selesai RBT-RBL",IF(CC7<15%,"Proses RBT-RBTD",IF(CC7=15%,"Selesai RBT-RBTD",IF(CC7<20%,"Proses RPP",IF(CC7=20%,"Selesai RPP",IF(CC7<25%,"Proses KAK",IF(CC7=25%,"Selesai KAK",IF(CC7<30%,"Proses Pengadaan",IF(CC7=30%,"Selesai Pengadaan",IF(CC7<45%,"Proses Desain",IF(CC7=45%,"Selesai Desain",IF(CC7<80%,"Proses Pengembangan",IF(CC7=80%,"Selesai Pengembangan",IF(CC7<87.5%,"Proses SIT",IF(CC7=87.5%,"Selesai SIT",IF(CC7<95%,"Proses UAT",IF(CC7=95%,"Selesai UAT",IF(CC7<100%,"Proses Implementasi","Selesai Implementasi")))))))))))))))))))))) -> Not Started | BR7: =IF(CD7=0%,"Not Started",IF(CD7<5%,"Proses RBT-RBB",IF(CD7=5%,"Selesai RBT-RBB",IF(CD7<10%,"Proses RBT-RBL",IF(CD7=10%,"Selesai RBT-RBL",IF(CD7<15%,"Proses RBT-RBTD",IF(CD7=15%,"Selesai RBT-RBTD",IF(CD7<20%,"Proses RPP",IF(CD7=20%,"Selesai RPP",IF(CD7<25%,"Proses KAK",IF(CD7=25%,"Selesai KAK",IF(CD7<30%,"Proses Pengadaan",IF(CD7=30%,"Selesai Pengadaan",IF(CD7<45%,"Proses Desain",IF(CD7=45%,"Selesai Desain",IF(CD7<80%,"Proses Pengembangan",IF(CD7=80%,"Selesai Pengembangan",IF(CD7<87.5%,"Proses SIT",IF(CD7=87.5%,"Selesai SIT",IF(CD7<95%,"Proses UAT",IF(CD7=95%,"Selesai UAT",IF(CD7<100%,"Proses Implementasi","Selesai Implementasi")))))))))))))))))))))) -> Not Started | BS7: =IF(CE7=0%,"Not Started",IF(CE7<5%,"Proses RBT-RBB",IF(CE7=5%,"Selesai RBT-RBB",IF(CE7<10%,"Proses RBT-RBL",IF(CE7=10%,"Selesai RBT-RBL",IF(CE7<15%,"Proses RBT-RBTD",IF(CE7=15%,"Selesai RBT-RBTD",IF(CE7<20%,"Proses RPP",IF(CE7=20%,"Selesai RPP",IF(CE7<25%,"Proses KAK",IF(CE7=25%,"Selesai KAK",IF(CE7<30%,"Proses Pengadaan",IF(CE7=30%,"Selesai Pengadaan",IF(CE7<45%,"Proses Desain",IF(CE7=45%,"Selesai Desain",IF(CE7<80%,"Proses Pengembangan",IF(CE7=80%,"Selesai Pengembangan",IF(CE7<87.5%,"Proses SIT",IF(CE7=87.5%,"Selesai SIT",IF(CE7<95%,"Proses UAT",IF(CE7=95%,"Selesai UAT",IF(CE7<100%,"Proses Implementasi","Selesai Implementasi")))))))))))))))))))))) -> Not Started | BT7: =IF(CF7=0%,"Not Started",IF(CF7<5%,"Proses RBT-RBB",IF(CF7=5%,"Selesai RBT-RBB",IF(CF7<10%,"Proses RBT-RBL",IF(CF7=10%,"Selesai RBT-RBL",IF(CF7<15%,"Proses RBT-RBTD",IF(CF7=15%,"Selesai RBT-RBTD",IF(CF7<20%,"Proses RPP",IF(CF7=20%,"Selesai RPP",IF(CF7<25%,"Proses KAK",IF(CF7=25%,"Selesai KAK",IF(CF7<30%,"Proses Pengadaan",IF(CF7=30%,"Selesai Pengadaan",IF(CF7<45%,"Proses Desain",IF(CF7=45%,"Selesai Desain",IF(CF7<80%,"Proses Pengembangan",IF(CF7=80%,"Selesai Pengembangan",IF(CF7<87.5%,"Proses SIT",IF(CF7=87.5%,"Selesai SIT",IF(CF7<95%,"Proses UAT",IF(CF7=95%,"Selesai UAT",IF(CF7<100%,"Proses Implementasi","Selesai Implementasi")))))))))))))))))))))) -> Not Started | BU7: =IF(CG7=0%,"Not Started",IF(CG7<5%,"Proses RBT-RBB",IF(CG7=5%,"Selesai RBT-RBB",IF(CG7<10%,"Proses RBT-RBL",IF(CG7=10%,"Selesai RBT-RBL",IF(CG7<15%,"Proses RBT-RBTD",IF(CG7=15%,"Selesai RBT-RBTD",IF(CG7<20%,"Proses RPP",IF(CG7=20%,"Selesai RPP",IF(CG7<25%,"Proses KAK",IF(CG7=25%,"Selesai KAK",IF(CG7<30%,"Proses Pengadaan",IF(CG7=30%,"Selesai Pengadaan",IF(CG7<45%,"Proses Desain",IF(CG7=45%,"Selesai Desain",IF(CG7<80%,"Proses Pengembangan",IF(CG7=80%,"Selesai Pengembangan",IF(CG7<87.5%,"Proses SIT",IF(CG7=87.5%,"Selesai SIT",IF(CG7<95%,"Proses UAT",IF(CG7=95%,"Selesai UAT",IF(CG7<100%,"Proses Implementasi","Selesai Implementasi")))))))))))))))))))))) -> Not Started | BV7: =IF(CH7=0%,"Not Started",IF(CH7<5%,"Proses RBT-RBB",IF(CH7=5%,"Selesai RBT-RBB",IF(CH7<10%,"Proses RBT-RBL",IF(CH7=10%,"Selesai RBT-RBL",IF(CH7<15%,"Proses RBT-RBTD",IF(CH7=15%,"Selesai RBT-RBTD",IF(CH7<20%,"Proses RPP",IF(CH7=20%,"Selesai RPP",IF(CH7<25%,"Proses KAK",IF(CH7=25%,"Selesai KAK",IF(CH7<30%,"Proses Pengadaan",IF(CH7=30%,"Selesai Pengadaan",IF(CH7<45%,"Proses Desain",IF(CH7=45%,"Selesai Desain",IF(CH7<80%,"Proses Pengembangan",IF(CH7=80%,"Selesai Pengembangan",IF(CH7<87.5%,"Proses SIT",IF(CH7=87.5%,"Selesai SIT",IF(CH7<95%,"Proses UAT",IF(CH7=95%,"Selesai UAT",IF(CH7<100%,"Proses Implementasi","Selesai Implementasi")))))))))))))))))))))) -> Not Started | BW7: =IF(CI7=0%,"Not Started",IF(CI7<5%,"Proses RBT-RBB",IF(CI7=5%,"Selesai RBT-RBB",IF(CI7<10%,"Proses RBT-RBL",IF(CI7=10%,"Selesai RBT-RBL",IF(CI7<15%,"Proses RBT-RBTD",IF(CI7=15%,"Selesai RBT-RBTD",IF(CI7<20%,"Proses RPP",IF(CI7=20%,"Selesai RPP",IF(CI7<25%,"Proses KAK",IF(CI7=25%,"Selesai KAK",IF(CI7<30%,"Proses Pengadaan",IF(CI7=30%,"Selesai Pengadaan",IF(CI7<45%,"Proses Desain",IF(CI7=45%,"Selesai Desain",IF(CI7<80%,"Proses Pengembangan",IF(CI7=80%,"Selesai Pengembangan",IF(CI7<87.5%,"Proses SIT",IF(CI7=87.5%,"Selesai SIT",IF(CI7<95%,"Proses UAT",IF(CI7=95%,"Selesai UAT",IF(CI7<100%,"Proses Implementasi","Selesai Implementasi")))))))))))))))))))))) -> Not Started | BX7: =IF(CJ7=0%,"Not Started",IF(CJ7<5%,"Proses RBT-RBB",IF(CJ7=5%,"Selesai RBT-RBB",IF(CJ7<10%,"Proses RBT-RBL",IF(CJ7=10%,"Selesai RBT-RBL",IF(CJ7<15%,"Proses RBT-RBTD",IF(CJ7=15%,"Selesai RBT-RBTD",IF(CJ7<20%,"Proses RPP",IF(CJ7=20%,"Selesai RPP",IF(CJ7<25%,"Proses KAK",IF(CJ7=25%,"Selesai KAK",IF(CJ7<30%,"Proses Pengadaan",IF(CJ7=30%,"Selesai Pengadaan",IF(CJ7<45%,"Proses Desain",IF(CJ7=45%,"Selesai Desain",IF(CJ7<80%,"Proses Pengembangan",IF(CJ7=80%,"Selesai Pengembangan",IF(CJ7<87.5%,"Proses SIT",IF(CJ7=87.5%,"Selesai SIT",IF(CJ7<95%,"Proses UAT",IF(CJ7=95%,"Selesai UAT",IF(CJ7<100%,"Proses Implementasi","Selesai Implementasi")))))))))))))))))))))) -> Not Started | ... CB7: =IF(CN7=0%,"Not Started",IF(CN7<5%,"Proses RBT-RBB",IF(CN7=5%,"Selesai RBT-RBB",IF(CN7<10%,"Proses RBT-RBL",IF(CN7=10%,"Selesai RBT-RBL",IF(CN7<15%,"Proses RBT-RBTD",IF(CN7=15%,"Selesai RBT-RBTD",IF(CN7<20%,"Proses RPP",IF(CN7=20%,"Selesai RPP",IF(CN7<25%,"Proses KAK",IF(CN7=25%,"Selesai KAK",IF(CN7<30%,"Proses Pengadaan",IF(CN7=30%,"Selesai Pengadaan",IF(CN7<45%,"Proses Desain",IF(CN7=45%,"Selesai Desain",IF(CN7<80%,"Proses Pengembangan",IF(CN7=80%,"Selesai Pengembangan",IF(CN7<87.5%,"Proses SIT",IF(CN7=87.5%,"Selesai SIT",IF(CN7<95%,"Proses UAT",IF(CN7=95%,"Selesai UAT",IF(CN7<100%,"Proses Implementasi","Selesai Implementasi")))))))))))))))))))))) -> Not Started | CC7: =(($DY7/100%)*15%)+(($DZ7/100%)*5%)+(($EA7/100%)*5%)+(($EB7/100%)*5%)+(($EC7/100%)*15%)+(($ED7/100%)*35%)+(($EE7/100%)*7.5%)+(($EF7/100%)*7.5%)+(($EG7/100%)*5%) -> 0 | CO7: =IF(BE7=0%, 100%, (CC7/BE7)) -> 1 | CP7: =IF(BF7=0%, 100%, (CD7/BF7)) -> 1 | CQ7: =IF(BG7=0%, 100%, (CE7/BG7)) -> 1 | CR7: =IF(BH7=0%, 100%, (CF7/BH7)) -> 0 | CS7: =IF(BI7=0%, 100%, (CG7/BI7)) -> 0 | CT7: =IF(BJ7=0%, 100%, (CH7/BJ7)) -> 0 | CU7: =IF(BK7=0%, 100%, (CI7/BK7)) -> 0 | CV7: =IF(BL7=0%, 100%, (CJ7/BL7)) -> 0 | ... CY7: =IF(BO7=0%, 100%, (CM7/BO7)) -> 0 | DA7: =IF(BE7=0%,"NS",IF(CC7=100%,"DONE",IF(CO7>100%,"AS",IF(CO7<75%,"BS",IF(CO7<89.9%,"AR","OS"))))) -> NS | DB7: =IF(BF7=0%,"NS",IF(CD7=100%,"DONE",IF(CP7>100%,"AS",IF(CP7<75%,"BS",IF(CP7<89.9%,"AR","OS"))))) -> NS | DC7: =IF(BG7=0%,"NS",IF(CE7=100%,"DONE",IF(CQ7>100%,"AS",IF(CQ7<75%,"BS",IF(CQ7<89.9%,"AR","OS"))))) -> NS | DD7: =IF(BH7=0%,"NS",IF(CF7=100%,"DONE",IF(CR7>100%,"AS",IF(CR7<75%,"BS",IF(CR7<89.9%,"AR","OS"))))) -> BS | DE7: =IF(BI7=0%,"NS",IF(CG7=100%,"DONE",IF(CS7>100%,"AS",IF(CS7<75%,"BS",IF(CS7<89.9%,"AR","OS"))))) -> BS | DF7: =IF(BJ7=0%,"NS",IF(CH7=100%,"DONE",IF(CT7>100%,"AS",IF(CT7<75%,"BS",IF(CT7<89.9%,"AR","OS"))))) -> BS | DG7: =IF(BK7=0%,"NS",IF(CI7=100%,"DONE",IF(CU7>100%,"AS",IF(CU7<75%,"BS",IF(CU7<89.9%,"AR","OS"))))) -> BS | DH7: =IF(BL7=0%,"NS",IF(CJ7=100%,"DONE",IF(CV7>100%,"AS",IF(CV7<75%,"BS",IF(CV7<89.9%,"AR","OS"))))) -> BS | ... DL7: =IF(BP7=0%,"NS",IF(CN7=100%,"DONE",IF(CZ7>100%,"AS",IF(CZ7<75%,"BS",IF(CZ7<89.9%,"AR","OS"))))) -> BS | DM7: =CC7/$BP7 -> 0 | DN7: =CD7/$BP7 -> 0 | DO7: =CE7/$BP7 -> 0 | DP7: =CF7/$BP7 -> 0 | DQ7: =CG7/$BP7 -> 0 | DR7: =CH7/$BP7 -> 0 | DS7: =CI7/$BP7 -> 0 | DT7: =CJ7/$BP7 -> 0 | ... DX7: =CN7/$BP7 -> 0 | EJ7: =AR7 -> 46568 | FN7: Helen Desyani | FO7: Iramia Triastika | FR7: Outsource
B8: PT2, BPPU | C8: IDT | D8: Continuity Technology | E8: P-4 | F8: =F7+1 -> 3 | G8: Pengembangan Product PUVA dan Penerbitan SBN | H8: Infrastruktur Data PUVA | I8: EDP Capturing Product -Capturing transaksi FX Swap | J8: 2029 | K8: 2029 | L8: S | M8: K3 | N8: Pemimpin Satker | O8: DPPK | P8: WG-2 | Q8: Moneter, Market | R8: TBD | S8: =BQ8 -> Not Started | T8: =IF(V8=0%,"Not Started",IF(V8<100%,"On Progress",IF(V8=100%,"DONE"))) -> Not Started | U8: =FN8 -> 0 | V8: =CC8 -> 0 | W8: TW I 2029 | X8: =AR8 -> 47483 | Z8: New | AA8: 47119 | AB8: 47178 | AC8: 47222 | AD8: 47238 | AE8: 47209 | AF8: 47221 | AI8: 47239 | AJ8: 47268 | AK8: 47270 | AL8: 47391 | AM8: 47392 | AN8: 47392 | AO8: 47423 | AP8: 47452 | AQ8: 47453 | AR8: 47483 | AS8: =IF(BE8=0%,"Not Started",IF(BE8<5%,"Proses RBT-RBB",IF(BE8=5%,"Selesai RBT-RBB",IF(BE8<10%,"Proses RBT-RBL",IF(BE8=10%,"Selesai RBT-RBL",IF(BE8<15%,"Proses RBT-RBTD",IF(BE8=15%,"Selesai RBT-RBTD",IF(BE8<20%,"Proses RPP",IF(BE8=20%,"Selesai RPP",IF(BE8<25%,"Proses KAK",IF(BE8=25%,"Selesai KAK",IF(BE8<30%,"Proses Pengadaan",IF(BE8=30%,"Selesai Pengadaan",IF(BE8<45%,"Proses Desain",IF(BE8=45%,"Selesai Desain",IF(BE8<80%,"Proses Pengembangan",IF(BE8=80%,"Selesai Pengembangan",IF(BE8<87.5%,"Proses SIT",IF(BE8=87.5%,"Selesai SIT",IF(BE8<95%,"Proses UAT",IF(BE8=95%,"Selesai UAT",IF(BE8<100%,"Proses Implementasi","Selesai Implementasi")))))))))))))))))))))) -> Not Started | AT8: =IF(BF8=0%,"Not Started",IF(BF8<5%,"Proses RBT-RBB",IF(BF8=5%,"Selesai RBT-RBB",IF(BF8<10%,"Proses RBT-RBL",IF(BF8=10%,"Selesai RBT-RBL",IF(BF8<15%,"Proses RBT-RBTD",IF(BF8=15%,"Selesai RBT-RBTD",IF(BF8<20%,"Proses RPP",IF(BF8=20%,"Selesai RPP",IF(BF8<25%,"Proses KAK",IF(BF8=25%,"Selesai KAK",IF(BF8<30%,"Proses Pengadaan",IF(BF8=30%,"Selesai Pengadaan",IF(BF8<45%,"Proses Desain",IF(BF8=45%,"Selesai Desain",IF(BF8<80%,"Proses Pengembangan",IF(BF8=80%,"Selesai Pengembangan",IF(BF8<87.5%,"Proses SIT",IF(BF8=87.5%,"Selesai SIT",IF(BF8<95%,"Proses UAT",IF(BF8=95%,"Selesai UAT",IF(BF8<100%,"Proses Implementasi","Selesai Implementasi")))))))))))))))))))))) -> Not Started | AU8: =IF(BG8=0%,"Not Started",IF(BG8<5%,"Proses RBT-RBB",IF(BG8=5%,"Selesai RBT-RBB",IF(BG8<10%,"Proses RBT-RBL",IF(BG8=10%,"Selesai RBT-RBL",IF(BG8<15%,"Proses RBT-RBTD",IF(BG8=15%,"Selesai RBT-RBTD",IF(BG8<20%,"Proses RPP",IF(BG8=20%,"Selesai RPP",IF(BG8<25%,"Proses KAK",IF(BG8=25%,"Selesai KAK",IF(BG8<30%,"Proses Pengadaan",IF(BG8=30%,"Selesai Pengadaan",IF(BG8<45%,"Proses Desain",IF(BG8=45%,"Selesai Desain",IF(BG8<80%,"Proses Pengembangan",IF(BG8=80%,"Selesai Pengembangan",IF(BG8<87.5%,"Proses SIT",IF(BG8=87.5%,"Selesai SIT",IF(BG8<95%,"Proses UAT",IF(BG8=95%,"Selesai UAT",IF(BG8<100%,"Proses Implementasi","Selesai Implementasi")))))))))))))))))))))) -> Not Started | AV8: =IF(BH8=0%,"Not Started",IF(BH8<5%,"Proses RBT-RBB",IF(BH8=5%,"Selesai RBT-RBB",IF(BH8<10%,"Proses RBT-RBL",IF(BH8=10%,"Selesai RBT-RBL",IF(BH8<15%,"Proses RBT-RBTD",IF(BH8=15%,"Selesai RBT-RBTD",IF(BH8<20%,"Proses RPP",IF(BH8=20%,"Selesai RPP",IF(BH8<25%,"Proses KAK",IF(BH8=25%,"Selesai KAK",IF(BH8<30%,"Proses Pengadaan",IF(BH8=30%,"Selesai Pengadaan",IF(BH8<45%,"Proses Desain",IF(BH8=45%,"Selesai Desain",IF(BH8<80%,"Proses Pengembangan",IF(BH8=80%,"Selesai Pengembangan",IF(BH8<87.5%,"Proses SIT",IF(BH8=87.5%,"Selesai SIT",IF(BH8<95%,"Proses UAT",IF(BH8=95%,"Selesai UAT",IF(BH8<100%,"Proses Implementasi","Selesai Implementasi")))))))))))))))))))))) -> Not Started | AW8: =IF(BI8=0%,"Not Started",IF(BI8<5%,"Proses RBT-RBB",IF(BI8=5%,"Selesai RBT-RBB",IF(BI8<10%,"Proses RBT-RBL",IF(BI8=10%,"Selesai RBT-RBL",IF(BI8<15%,"Proses RBT-RBTD",IF(BI8=15%,"Selesai RBT-RBTD",IF(BI8<20%,"Proses RPP",IF(BI8=20%,"Selesai RPP",IF(BI8<25%,"Proses KAK",IF(BI8=25%,"Selesai KAK",IF(BI8<30%,"Proses Pengadaan",IF(BI8=30%,"Selesai Pengadaan",IF(BI8<45%,"Proses Desain",IF(BI8=45%,"Selesai Desain",IF(BI8<80%,"Proses Pengembangan",IF(BI8=80%,"Selesai Pengembangan",IF(BI8<87.5%,"Proses SIT",IF(BI8=87.5%,"Selesai SIT",IF(BI8<95%,"Proses UAT",IF(BI8=95%,"Selesai UAT",IF(BI8<100%,"Proses Implementasi","Selesai Implementasi")))))))))))))))))))))) -> Not Started | AX8: =IF(BJ8=0%,"Not Started",IF(BJ8<5%,"Proses RBT-RBB",IF(BJ8=5%,"Selesai RBT-RBB",IF(BJ8<10%,"Proses RBT-RBL",IF(BJ8=10%,"Selesai RBT-RBL",IF(BJ8<15%,"Proses RBT-RBTD",IF(BJ8=15%,"Selesai RBT-RBTD",IF(BJ8<20%,"Proses RPP",IF(BJ8=20%,"Selesai RPP",IF(BJ8<25%,"Proses KAK",IF(BJ8=25%,"Selesai KAK",IF(BJ8<30%,"Proses Pengadaan",IF(BJ8=30%,"Selesai Pengadaan",IF(BJ8<45%,"Proses Desain",IF(BJ8=45%,"Selesai Desain",IF(BJ8<80%,"Proses Pengembangan",IF(BJ8=80%,"Selesai Pengembangan",IF(BJ8<87.5%,"Proses SIT",IF(BJ8=87.5%,"Selesai SIT",IF(BJ8<95%,"Proses UAT",IF(BJ8=95%,"Selesai UAT",IF(BJ8<100%,"Proses Implementasi","Selesai Implementasi")))))))))))))))))))))) -> Not Started | AY8: =IF(BK8=0%,"Not Started",IF(BK8<5%,"Proses RBT-RBB",IF(BK8=5%,"Selesai RBT-RBB",IF(BK8<10%,"Proses RBT-RBL",IF(BK8=10%,"Selesai RBT-RBL",IF(BK8<15%,"Proses RBT-RBTD",IF(BK8=15%,"Selesai RBT-RBTD",IF(BK8<20%,"Proses RPP",IF(BK8=20%,"Selesai RPP",IF(BK8<25%,"Proses KAK",IF(BK8=25%,"Selesai KAK",IF(BK8<30%,"Proses Pengadaan",IF(BK8=30%,"Selesai Pengadaan",IF(BK8<45%,"Proses Desain",IF(BK8=45%,"Selesai Desain",IF(BK8<80%,"Proses Pengembangan",IF(BK8=80%,"Selesai Pengembangan",IF(BK8<87.5%,"Proses SIT",IF(BK8=87.5%,"Selesai SIT",IF(BK8<95%,"Proses UAT",IF(BK8=95%,"Selesai UAT",IF(BK8<100%,"Proses Implementasi","Selesai Implementasi")))))))))))))))))))))) -> Not Started | AZ8: =IF(BL8=0%,"Not Started",IF(BL8<5%,"Proses RBT-RBB",IF(BL8=5%,"Selesai RBT-RBB",IF(BL8<10%,"Proses RBT-RBL",IF(BL8=10%,"Selesai RBT-RBL",IF(BL8<15%,"Proses RBT-RBTD",IF(BL8=15%,"Selesai RBT-RBTD",IF(BL8<20%,"Proses RPP",IF(BL8=20%,"Selesai RPP",IF(BL8<25%,"Proses KAK",IF(BL8=25%,"Selesai KAK",IF(BL8<30%,"Proses Pengadaan",IF(BL8=30%,"Selesai Pengadaan",IF(BL8<45%,"Proses Desain",IF(BL8=45%,"Selesai Desain",IF(BL8<80%,"Proses Pengembangan",IF(BL8=80%,"Selesai Pengembangan",IF(BL8<87.5%,"Proses SIT",IF(BL8=87.5%,"Selesai SIT",IF(BL8<95%,"Proses UAT",IF(BL8=95%,"Selesai UAT",IF(BL8<100%,"Proses Implementasi","Selesai Implementasi")))))))))))))))))))))) -> Not Started | ... BD8: =IF(BP8=0%,"Not Started",IF(BP8<5%,"Proses RBT-RBB",IF(BP8=5%,"Selesai RBT-RBB",IF(BP8<10%,"Proses RBT-RBL",IF(BP8=10%,"Selesai RBT-RBL",IF(BP8<15%,"Proses RBT-RBTD",IF(BP8=15%,"Selesai RBT-RBTD",IF(BP8<20%,"Proses RPP",IF(BP8=20%,"Selesai RPP",IF(BP8<25%,"Proses KAK",IF(BP8=25%,"Selesai KAK",IF(BP8<30%,"Proses Pengadaan",IF(BP8=30%,"Selesai Pengadaan",IF(BP8<45%,"Proses Desain",IF(BP8=45%,"Selesai Desain",IF(BP8<80%,"Proses Pengembangan",IF(BP8=80%,"Selesai Pengembangan",IF(BP8<87.5%,"Proses SIT",IF(BP8=87.5%,"Selesai SIT",IF(BP8<95%,"Proses UAT",IF(BP8=95%,"Selesai UAT",IF(BP8<100%,"Proses Implementasi","Selesai Implementasi")))))))))))))))))))))) -> Not Started | BE8: 0 | BF8: 0 | BG8: 0 | BH8: 0 | BI8: 0 | BJ8: 0 | BK8: 0 | BL8: 0 | BM8: 0 | BN8: 0 | BO8: 0 | BP8: 0 | BQ8: =IF(CC8=0%,"Not Started",IF(CC8<5%,"Proses RBT-RBB",IF(CC8=5%,"Selesai RBT-RBB",IF(CC8<10%,"Proses RBT-RBL",IF(CC8=10%,"Selesai RBT-RBL",IF(CC8<15%,"Proses RBT-RBTD",IF(CC8=15%,"Selesai RBT-RBTD",IF(CC8<20%,"Proses RPP",IF(CC8=20%,"Selesai RPP",IF(CC8<25%,"Proses KAK",IF(CC8=25%,"Selesai KAK",IF(CC8<30%,"Proses Pengadaan",IF(CC8=30%,"Selesai Pengadaan",IF(CC8<45%,"Proses Desain",IF(CC8=45%,"Selesai Desain",IF(CC8<80%,"Proses Pengembangan",IF(CC8=80%,"Selesai Pengembangan",IF(CC8<87.5%,"Proses SIT",IF(CC8=87.5%,"Selesai SIT",IF(CC8<95%,"Proses UAT",IF(CC8=95%,"Selesai UAT",IF(CC8<100%,"Proses Implementasi","Selesai Implementasi")))))))))))))))))))))) -> Not Started | BR8: =IF(CD8=0%,"Not Started",IF(CD8<5%,"Proses RBT-RBB",IF(CD8=5%,"Selesai RBT-RBB",IF(CD8<10%,"Proses RBT-RBL",IF(CD8=10%,"Selesai RBT-RBL",IF(CD8<15%,"Proses RBT-RBTD",IF(CD8=15%,"Selesai RBT-RBTD",IF(CD8<20%,"Proses RPP",IF(CD8=20%,"Selesai RPP",IF(CD8<25%,"Proses KAK",IF(CD8=25%,"Selesai KAK",IF(CD8<30%,"Proses Pengadaan",IF(CD8=30%,"Selesai Pengadaan",IF(CD8<45%,"Proses Desain",IF(CD8=45%,"Selesai Desain",IF(CD8<80%,"Proses Pengembangan",IF(CD8=80%,"Selesai Pengembangan",IF(CD8<87.5%,"Proses SIT",IF(CD8=87.5%,"Selesai SIT",IF(CD8<95%,"Proses UAT",IF(CD8=95%,"Selesai UAT",IF(CD8<100%,"Proses Implementasi","Selesai Implementasi")))))))))))))))))))))) -> Not Started | BS8: =IF(CE8=0%,"Not Started",IF(CE8<5%,"Proses RBT-RBB",IF(CE8=5%,"Selesai RBT-RBB",IF(CE8<10%,"Proses RBT-RBL",IF(CE8=10%,"Selesai RBT-RBL",IF(CE8<15%,"Proses RBT-RBTD",IF(CE8=15%,"Selesai RBT-RBTD",IF(CE8<20%,"Proses RPP",IF(CE8=20%,"Selesai RPP",IF(CE8<25%,"Proses KAK",IF(CE8=25%,"Selesai KAK",IF(CE8<30%,"Proses Pengadaan",IF(CE8=30%,"Selesai Pengadaan",IF(CE8<45%,"Proses Desain",IF(CE8=45%,"Selesai Desain",IF(CE8<80%,"Proses Pengembangan",IF(CE8=80%,"Selesai Pengembangan",IF(CE8<87.5%,"Proses SIT",IF(CE8=87.5%,"Selesai SIT",IF(CE8<95%,"Proses UAT",IF(CE8=95%,"Selesai UAT",IF(CE8<100%,"Proses Implementasi","Selesai Implementasi")))))))))))))))))))))) -> Not Started | BT8: =IF(CF8=0%,"Not Started",IF(CF8<5%,"Proses RBT-RBB",IF(CF8=5%,"Selesai RBT-RBB",IF(CF8<10%,"Proses RBT-RBL",IF(CF8=10%,"Selesai RBT-RBL",IF(CF8<15%,"Proses RBT-RBTD",IF(CF8=15%,"Selesai RBT-RBTD",IF(CF8<20%,"Proses RPP",IF(CF8=20%,"Selesai RPP",IF(CF8<25%,"Proses KAK",IF(CF8=25%,"Selesai KAK",IF(CF8<30%,"Proses Pengadaan",IF(CF8=30%,"Selesai Pengadaan",IF(CF8<45%,"Proses Desain",IF(CF8=45%,"Selesai Desain",IF(CF8<80%,"Proses Pengembangan",IF(CF8=80%,"Selesai Pengembangan",IF(CF8<87.5%,"Proses SIT",IF(CF8=87.5%,"Selesai SIT",IF(CF8<95%,"Proses UAT",IF(CF8=95%,"Selesai UAT",IF(CF8<100%,"Proses Implementasi","Selesai Implementasi")))))))))))))))))))))) -> Not Started | BU8: =IF(CG8=0%,"Not Started",IF(CG8<5%,"Proses RBT-RBB",IF(CG8=5%,"Selesai RBT-RBB",IF(CG8<10%,"Proses RBT-RBL",IF(CG8=10%,"Selesai RBT-RBL",IF(CG8<15%,"Proses RBT-RBTD",IF(CG8=15%,"Selesai RBT-RBTD",IF(CG8<20%,"Proses RPP",IF(CG8=20%,"Selesai RPP",IF(CG8<25%,"Proses KAK",IF(CG8=25%,"Selesai KAK",IF(CG8<30%,"Proses Pengadaan",IF(CG8=30%,"Selesai Pengadaan",IF(CG8<45%,"Proses Desain",IF(CG8=45%,"Selesai Desain",IF(CG8<80%,"Proses Pengembangan",IF(CG8=80%,"Selesai Pengembangan",IF(CG8<87.5%,"Proses SIT",IF(CG8=87.5%,"Selesai SIT",IF(CG8<95%,"Proses UAT",IF(CG8=95%,"Selesai UAT",IF(CG8<100%,"Proses Implementasi","Selesai Implementasi")))))))))))))))))))))) -> Not Started | BV8: =IF(CH8=0%,"Not Started",IF(CH8<5%,"Proses RBT-RBB",IF(CH8=5%,"Selesai RBT-RBB",IF(CH8<10%,"Proses RBT-RBL",IF(CH8=10%,"Selesai RBT-RBL",IF(CH8<15%,"Proses RBT-RBTD",IF(CH8=15%,"Selesai RBT-RBTD",IF(CH8<20%,"Proses RPP",IF(CH8=20%,"Selesai RPP",IF(CH8<25%,"Proses KAK",IF(CH8=25%,"Selesai KAK",IF(CH8<30%,"Proses Pengadaan",IF(CH8=30%,"Selesai Pengadaan",IF(CH8<45%,"Proses Desain",IF(CH8=45%,"Selesai Desain",IF(CH8<80%,"Proses Pengembangan",IF(CH8=80%,"Selesai Pengembangan",IF(CH8<87.5%,"Proses SIT",IF(CH8=87.5%,"Selesai SIT",IF(CH8<95%,"Proses UAT",IF(CH8=95%,"Selesai UAT",IF(CH8<100%,"Proses Implementasi","Selesai Implementasi")))))))))))))))))))))) -> Not Started | BW8: =IF(CI8=0%,"Not Started",IF(CI8<5%,"Proses RBT-RBB",IF(CI8=5%,"Selesai RBT-RBB",IF(CI8<10%,"Proses RBT-RBL",IF(CI8=10%,"Selesai RBT-RBL",IF(CI8<15%,"Proses RBT-RBTD",IF(CI8=15%,"Selesai RBT-RBTD",IF(CI8<20%,"Proses RPP",IF(CI8=20%,"Selesai RPP",IF(CI8<25%,"Proses KAK",IF(CI8=25%,"Selesai KAK",IF(CI8<30%,"Proses Pengadaan",IF(CI8=30%,"Selesai Pengadaan",IF(CI8<45%,"Proses Desain",IF(CI8=45%,"Selesai Desain",IF(CI8<80%,"Proses Pengembangan",IF(CI8=80%,"Selesai Pengembangan",IF(CI8<87.5%,"Proses SIT",IF(CI8=87.5%,"Selesai SIT",IF(CI8<95%,"Proses UAT",IF(CI8=95%,"Selesai UAT",IF(CI8<100%,"Proses Implementasi","Selesai Implementasi")))))))))))))))))))))) -> Not Started | BX8: =IF(CJ8=0%,"Not Started",IF(CJ8<5%,"Proses RBT-RBB",IF(CJ8=5%,"Selesai RBT-RBB",IF(CJ8<10%,"Proses RBT-RBL",IF(CJ8=10%,"Selesai RBT-RBL",IF(CJ8<15%,"Proses RBT-RBTD",IF(CJ8=15%,"Selesai RBT-RBTD",IF(CJ8<20%,"Proses RPP",IF(CJ8=20%,"Selesai RPP",IF(CJ8<25%,"Proses KAK",IF(CJ8=25%,"Selesai KAK",IF(CJ8<30%,"Proses Pengadaan",IF(CJ8=30%,"Selesai Pengadaan",IF(CJ8<45%,"Proses Desain",IF(CJ8=45%,"Selesai Desain",IF(CJ8<80%,"Proses Pengembangan",IF(CJ8=80%,"Selesai Pengembangan",IF(CJ8<87.5%,"Proses SIT",IF(CJ8=87.5%,"Selesai SIT",IF(CJ8<95%,"Proses UAT",IF(CJ8=95%,"Selesai UAT",IF(CJ8<100%,"Proses Implementasi","Selesai Implementasi")))))))))))))))))))))) -> Not Started | ... CB8: =IF(CN8=0%,"Not Started",IF(CN8<5%,"Proses RBT-RBB",IF(CN8=5%,"Selesai RBT-RBB",IF(CN8<10%,"Proses RBT-RBL",IF(CN8=10%,"Selesai RBT-RBL",IF(CN8<15%,"Proses RBT-RBTD",IF(CN8=15%,"Selesai RBT-RBTD",IF(CN8<20%,"Proses RPP",IF(CN8=20%,"Selesai RPP",IF(CN8<25%,"Proses KAK",IF(CN8=25%,"Selesai KAK",IF(CN8<30%,"Proses Pengadaan",IF(CN8=30%,"Selesai Pengadaan",IF(CN8<45%,"Proses Desain",IF(CN8=45%,"Selesai Desain",IF(CN8<80%,"Proses Pengembangan",IF(CN8=80%,"Selesai Pengembangan",IF(CN8<87.5%,"Proses SIT",IF(CN8=87.5%,"Selesai SIT",IF(CN8<95%,"Proses UAT",IF(CN8=95%,"Selesai UAT",IF(CN8<100%,"Proses Implementasi","Selesai Implementasi")))))))))))))))))))))) -> Not Started | CL8: 0 | CM8: =(($DY8/100%)*15%)+(($DZ8/100%)*5%)+(($EA8/100%)*5%)+(($EB8/100%)*5%)+(($EC8/100%)*15%)+(($ED8/100%)*35%)+(($EE8/100%)*7.5%)+(($EF8/100%)*7.5%)+(($EG8/100%)*5%) -> 0 | CN8: =(($DY8/100%)*15%)+(($DZ8/100%)*5%)+(($EA8/100%)*5%)+(($EB8/100%)*5%)+(($EC8/100%)*15%)+(($ED8/100%)*35%)+(($EE8/100%)*7.5%)+(($EF8/100%)*7.5%)+(($EG8/100%)*5%) -> 0 | CO8: =IF(BE8=0%, 100%, (CC8/BE8)) -> 1 | CP8: =IF(BF8=0%, 100%, (CD8/BF8)) -> 1 | CQ8: =IF(BG8=0%, 100%, (CE8/BG8)) -> 1 | CR8: =IF(BH8=0%, 100%, (CF8/BH8)) -> 1 | CS8: =IF(BI8=0%, 100%, (CG8/BI8)) -> 1 | CT8: =IF(BJ8=0%, 100%, (CH8/BJ8)) -> 1 | CU8: =IF(BK8=0%, 100%, (CI8/BK8)) -> 1 | CV8: =IF(BL8=0%, 100%, (CJ8/BL8)) -> 1 | ... CY8: =IF(BO8=0%, 100%, (CM8/BO8)) -> 1 | DA8: =IF(BE8=0%,"NS",IF(CC8=100%,"DONE",IF(CO8>100%,"AS",IF(CO8<75%,"BS",IF(CO8<89.9%,"AR","OS"))))) -> NS | DB8: =IF(BF8=0%,"NS",IF(CD8=100%,"DONE",IF(CP8>100%,"AS",IF(CP8<75%,"BS",IF(CP8<89.9%,"AR","OS"))))) -> NS | DC8: =IF(BG8=0%,"NS",IF(CE8=100%,"DONE",IF(CQ8>100%,"AS",IF(CQ8<75%,"BS",IF(CQ8<89.9%,"AR","OS"))))) -> NS | DD8: =IF(BH8=0%,"NS",IF(CF8=100%,"DONE",IF(CR8>100%,"AS",IF(CR8<75%,"BS",IF(CR8<89.9%,"AR","OS"))))) -> NS | DE8: =IF(BI8=0%,"NS",IF(CG8=100%,"DONE",IF(CS8>100%,"AS",IF(CS8<75%,"BS",IF(CS8<89.9%,"AR","OS"))))) -> NS | DF8: =IF(BJ8=0%,"NS",IF(CH8=100%,"DONE",IF(CT8>100%,"AS",IF(CT8<75%,"BS",IF(CT8<89.9%,"AR","OS"))))) -> NS | DG8: =IF(BK8=0%,"NS",IF(CI8=100%,"DONE",IF(CU8>100%,"AS",IF(CU8<75%,"BS",IF(CU8<89.9%,"AR","OS"))))) -> NS | DH8: =IF(BL8=0%,"NS",IF(CJ8=100%,"DONE",IF(CV8>100%,"AS",IF(CV8<75%,"BS",IF(CV8<89.9%,"AR","OS"))))) -> NS | ... DL8: =IF(BP8=0%,"NS",IF(CN8=100%,"DONE",IF(CZ8>100%,"AS",IF(CZ8<75%,"BS",IF(CZ8<89.9%,"AR","OS"))))) -> NS | DM8: =CC8/$BP8 -> #DIV/0! | DN8: =CD8/$BP8 -> #DIV/0! | DO8: =CE8/$BP8 -> #DIV/0! | DP8: =CF8/$BP8 -> #DIV/0! | DQ8: =CG8/$BP8 -> #DIV/0! | DR8: =CH8/$BP8 -> #DIV/0! | DS8: =CI8/$BP8 -> #DIV/0! | DT8: =CJ8/$BP8 -> #DIV/0! | ... DX8: =CN8/$BP8 -> #DIV/0! | EJ8: =AR8 -> 47483 | FO8: Iramia Triastika | FR8: Outsource
B9: PT2, BPPU | C9: IDT | D9: Continuity Technology | E9: P-4 | F9: =F8+1 -> 4 | G9: Pengembangan Product PUVA dan Penerbitan SBN | H9: Infrastruktur Data PUVA | I9: DEP Capturing Product -Pelaporan: dari ETP-MO | J9: 2026 | K9: 2027 | L9: S | M9: K3 | N9: Pemimpin Satker | O9: DPPK, DSta, DPKL | P9: PPLBI | Q9: Moneter, Market | R9: TBD | S9: =BQ9 -> Not Started | T9: =IF(V9=0%,"Not Started",IF(V9<100%,"On Progress",IF(V9=100%,"DONE"))) -> Not Started | U9: =FN9 -> Helen Desyani | V9: =CC9 -> 0 | W9: TW II 2026 | X9: =AR9 -> 46477 | Z9: New | AA9: 46113 | AB9: 46203 | AC9: 46204 | AD9: 46217 | AE9: 46217 | AF9: 46234 | AI9: 46235 | AJ9: 46264 | AK9: 46266 | AL9: 46387 | AM9: 46388 | AN9: 46418 | AO9: 46419 | AP9: 46446 | AQ9: 46447 | AR9: 46477 | AS9: =IF(BE9=0%,"Not Started",IF(BE9<5%,"Proses RBT-RBB",IF(BE9=5%,"Selesai RBT-RBB",IF(BE9<10%,"Proses RBT-RBL",IF(BE9=10%,"Selesai RBT-RBL",IF(BE9<15%,"Proses RBT-RBTD",IF(BE9=15%,"Selesai RBT-RBTD",IF(BE9<20%,"Proses RPP",IF(BE9=20%,"Selesai RPP",IF(BE9<25%,"Proses KAK",IF(BE9=25%,"Selesai KAK",IF(BE9<30%,"Proses Pengadaan",IF(BE9=30%,"Selesai Pengadaan",IF(BE9<45%,"Proses Desain",IF(BE9=45%,"Selesai Desain",IF(BE9<80%,"Proses Pengembangan",IF(BE9=80%,"Selesai Pengembangan",IF(BE9<87.5%,"Proses SIT",IF(BE9=87.5%,"Selesai SIT",IF(BE9<95%,"Proses UAT",IF(BE9=95%,"Selesai UAT",IF(BE9<100%,"Proses Implementasi","Selesai Implementasi")))))))))))))))))))))) -> Not Started | AT9: =IF(BF9=0%,"Not Started",IF(BF9<5%,"Proses RBT-RBB",IF(BF9=5%,"Selesai RBT-RBB",IF(BF9<10%,"Proses RBT-RBL",IF(BF9=10%,"Selesai RBT-RBL",IF(BF9<15%,"Proses RBT-RBTD",IF(BF9=15%,"Selesai RBT-RBTD",IF(BF9<20%,"Proses RPP",IF(BF9=20%,"Selesai RPP",IF(BF9<25%,"Proses KAK",IF(BF9=25%,"Selesai KAK",IF(BF9<30%,"Proses Pengadaan",IF(BF9=30%,"Selesai Pengadaan",IF(BF9<45%,"Proses Desain",IF(BF9=45%,"Selesai Desain",IF(BF9<80%,"Proses Pengembangan",IF(BF9=80%,"Selesai Pengembangan",IF(BF9<87.5%,"Proses SIT",IF(BF9=87.5%,"Selesai SIT",IF(BF9<95%,"Proses UAT",IF(BF9=95%,"Selesai UAT",IF(BF9<100%,"Proses Implementasi","Selesai Implementasi")))))))))))))))))))))) -> Not Started | AU9: =IF(BG9=0%,"Not Started",IF(BG9<5%,"Proses RBT-RBB",IF(BG9=5%,"Selesai RBT-RBB",IF(BG9<10%,"Proses RBT-RBL",IF(BG9=10%,"Selesai RBT-RBL",IF(BG9<15%,"Proses RBT-RBTD",IF(BG9=15%,"Selesai RBT-RBTD",IF(BG9<20%,"Proses RPP",IF(BG9=20%,"Selesai RPP",IF(BG9<25%,"Proses KAK",IF(BG9=25%,"Selesai KAK",IF(BG9<30%,"Proses Pengadaan",IF(BG9=30%,"Selesai Pengadaan",IF(BG9<45%,"Proses Desain",IF(BG9=45%,"Selesai Desain",IF(BG9<80%,"Proses Pengembangan",IF(BG9=80%,"Selesai Pengembangan",IF(BG9<87.5%,"Proses SIT",IF(BG9=87.5%,"Selesai SIT",IF(BG9<95%,"Proses UAT",IF(BG9=95%,"Selesai UAT",IF(BG9<100%,"Proses Implementasi","Selesai Implementasi")))))))))))))))))))))) -> Not Started | AV9: =IF(BH9=0%,"Not Started",IF(BH9<5%,"Proses RBT-RBB",IF(BH9=5%,"Selesai RBT-RBB",IF(BH9<10%,"Proses RBT-RBL",IF(BH9=10%,"Selesai RBT-RBL",IF(BH9<15%,"Proses RBT-RBTD",IF(BH9=15%,"Selesai RBT-RBTD",IF(BH9<20%,"Proses RPP",IF(BH9=20%,"Selesai RPP",IF(BH9<25%,"Proses KAK",IF(BH9=25%,"Selesai KAK",IF(BH9<30%,"Proses Pengadaan",IF(BH9=30%,"Selesai Pengadaan",IF(BH9<45%,"Proses Desain",IF(BH9=45%,"Selesai Desain",IF(BH9<80%,"Proses Pengembangan",IF(BH9=80%,"Selesai Pengembangan",IF(BH9<87.5%,"Proses SIT",IF(BH9=87.5%,"Selesai SIT",IF(BH9<95%,"Proses UAT",IF(BH9=95%,"Selesai UAT",IF(BH9<100%,"Proses Implementasi","Selesai Implementasi")))))))))))))))))))))) -> Selesai RBT-RBB | AW9: =IF(BI9=0%,"Not Started",IF(BI9<5%,"Proses RBT-RBB",IF(BI9=5%,"Selesai RBT-RBB",IF(BI9<10%,"Proses RBT-RBL",IF(BI9=10%,"Selesai RBT-RBL",IF(BI9<15%,"Proses RBT-RBTD",IF(BI9=15%,"Selesai RBT-RBTD",IF(BI9<20%,"Proses RPP",IF(BI9=20%,"Selesai RPP",IF(BI9<25%,"Proses KAK",IF(BI9=25%,"Selesai KAK",IF(BI9<30%,"Proses Pengadaan",IF(BI9=30%,"Selesai Pengadaan",IF(BI9<45%,"Proses Desain",IF(BI9=45%,"Selesai Desain",IF(BI9<80%,"Proses Pengembangan",IF(BI9=80%,"Selesai Pengembangan",IF(BI9<87.5%,"Proses SIT",IF(BI9=87.5%,"Selesai SIT",IF(BI9<95%,"Proses UAT",IF(BI9=95%,"Selesai UAT",IF(BI9<100%,"Proses Implementasi","Selesai Implementasi")))))))))))))))))))))) -> Selesai RBT-RBL | AX9: =IF(BJ9=0%,"Not Started",IF(BJ9<5%,"Proses RBT-RBB",IF(BJ9=5%,"Selesai RBT-RBB",IF(BJ9<10%,"Proses RBT-RBL",IF(BJ9=10%,"Selesai RBT-RBL",IF(BJ9<15%,"Proses RBT-RBTD",IF(BJ9=15%,"Selesai RBT-RBTD",IF(BJ9<20%,"Proses RPP",IF(BJ9=20%,"Selesai RPP",IF(BJ9<25%,"Proses KAK",IF(BJ9=25%,"Selesai KAK",IF(BJ9<30%,"Proses Pengadaan",IF(BJ9=30%,"Selesai Pengadaan",IF(BJ9<45%,"Proses Desain",IF(BJ9=45%,"Selesai Desain",IF(BJ9<80%,"Proses Pengembangan",IF(BJ9=80%,"Selesai Pengembangan",IF(BJ9<87.5%,"Proses SIT",IF(BJ9=87.5%,"Selesai SIT",IF(BJ9<95%,"Proses UAT",IF(BJ9=95%,"Selesai UAT",IF(BJ9<100%,"Proses Implementasi","Selesai Implementasi")))))))))))))))))))))) -> Selesai RBT-RBTD | AY9: =IF(BK9=0%,"Not Started",IF(BK9<5%,"Proses RBT-RBB",IF(BK9=5%,"Selesai RBT-RBB",IF(BK9<10%,"Proses RBT-RBL",IF(BK9=10%,"Selesai RBT-RBL",IF(BK9<15%,"Proses RBT-RBTD",IF(BK9=15%,"Selesai RBT-RBTD",IF(BK9<20%,"Proses RPP",IF(BK9=20%,"Selesai RPP",IF(BK9<25%,"Proses KAK",IF(BK9=25%,"Selesai KAK",IF(BK9<30%,"Proses Pengadaan",IF(BK9=30%,"Selesai Pengadaan",IF(BK9<45%,"Proses Desain",IF(BK9=45%,"Selesai Desain",IF(BK9<80%,"Proses Pengembangan",IF(BK9=80%,"Selesai Pengembangan",IF(BK9<87.5%,"Proses SIT",IF(BK9=87.5%,"Selesai SIT",IF(BK9<95%,"Proses UAT",IF(BK9=95%,"Selesai UAT",IF(BK9<100%,"Proses Implementasi","Selesai Implementasi")))))))))))))))))))))) -> Selesai Pengadaan | AZ9: =IF(BL9=0%,"Not Started",IF(BL9<5%,"Proses RBT-RBB",IF(BL9=5%,"Selesai RBT-RBB",IF(BL9<10%,"Proses RBT-RBL",IF(BL9=10%,"Selesai RBT-RBL",IF(BL9<15%,"Proses RBT-RBTD",IF(BL9=15%,"Selesai RBT-RBTD",IF(BL9<20%,"Proses RPP",IF(BL9=20%,"Selesai RPP",IF(BL9<25%,"Proses KAK",IF(BL9=25%,"Selesai KAK",IF(BL9<30%,"Proses Pengadaan",IF(BL9=30%,"Selesai Pengadaan",IF(BL9<45%,"Proses Desain",IF(BL9=45%,"Selesai Desain",IF(BL9<80%,"Proses Pengembangan",IF(BL9=80%,"Selesai Pengembangan",IF(BL9<87.5%,"Proses SIT",IF(BL9=87.5%,"Selesai SIT",IF(BL9<95%,"Proses UAT",IF(BL9=95%,"Selesai UAT",IF(BL9<100%,"Proses Implementasi","Selesai Implementasi")))))))))))))))))))))) -> Proses Desain | ... BD9: =IF(BP9=0%,"Not Started",IF(BP9<5%,"Proses RBT-RBB",IF(BP9=5%,"Selesai RBT-RBB",IF(BP9<10%,"Proses RBT-RBL",IF(BP9=10%,"Selesai RBT-RBL",IF(BP9<15%,"Proses RBT-RBTD",IF(BP9=15%,"Selesai RBT-RBTD",IF(BP9<20%,"Proses RPP",IF(BP9=20%,"Selesai RPP",IF(BP9<25%,"Proses KAK",IF(BP9=25%,"Selesai KAK",IF(BP9<30%,"Proses Pengadaan",IF(BP9=30%,"Selesai Pengadaan",IF(BP9<45%,"Proses Desain",IF(BP9=45%,"Selesai Desain",IF(BP9<80%,"Proses Pengembangan",IF(BP9=80%,"Selesai Pengembangan",IF(BP9<87.5%,"Proses SIT",IF(BP9=87.5%,"Selesai SIT",IF(BP9<95%,"Proses UAT",IF(BP9=95%,"Selesai UAT",IF(BP9<100%,"Proses Implementasi","Selesai Implementasi")))))))))))))))))))))) -> Proses Pengembangan | BE9: 0 | BF9: 0 | BG9: 0 | BH9: 0.05 | BI9: 0.1 | BJ9: 0.15 | BK9: 0.3 | BL9: 0.4 | BM9: 0.49 | BN9: 0.57 | BO9: 0.65 | BP9: 0.73 | BQ9: =IF(CC9=0%,"Not Started",IF(CC9<5%,"Proses RBT-RBB",IF(CC9=5%,"Selesai RBT-RBB",IF(CC9<10%,"Proses RBT-RBL",IF(CC9=10%,"Selesai RBT-RBL",IF(CC9<15%,"Proses RBT-RBTD",IF(CC9=15%,"Selesai RBT-RBTD",IF(CC9<20%,"Proses RPP",IF(CC9=20%,"Selesai RPP",IF(CC9<25%,"Proses KAK",IF(CC9=25%,"Selesai KAK",IF(CC9<30%,"Proses Pengadaan",IF(CC9=30%,"Selesai Pengadaan",IF(CC9<45%,"Proses Desain",IF(CC9=45%,"Selesai Desain",IF(CC9<80%,"Proses Pengembangan",IF(CC9=80%,"Selesai Pengembangan",IF(CC9<87.5%,"Proses SIT",IF(CC9=87.5%,"Selesai SIT",IF(CC9<95%,"Proses UAT",IF(CC9=95%,"Selesai UAT",IF(CC9<100%,"Proses Implementasi","Selesai Implementasi")))))))))))))))))))))) -> Not Started | BR9: =IF(CD9=0%,"Not Started",IF(CD9<5%,"Proses RBT-RBB",IF(CD9=5%,"Selesai RBT-RBB",IF(CD9<10%,"Proses RBT-RBL",IF(CD9=10%,"Selesai RBT-RBL",IF(CD9<15%,"Proses RBT-RBTD",IF(CD9=15%,"Selesai RBT-RBTD",IF(CD9<20%,"Proses RPP",IF(CD9=20%,"Selesai RPP",IF(CD9<25%,"Proses KAK",IF(CD9=25%,"Selesai KAK",IF(CD9<30%,"Proses Pengadaan",IF(CD9=30%,"Selesai Pengadaan",IF(CD9<45%,"Proses Desain",IF(CD9=45%,"Selesai Desain",IF(CD9<80%,"Proses Pengembangan",IF(CD9=80%,"Selesai Pengembangan",IF(CD9<87.5%,"Proses SIT",IF(CD9=87.5%,"Selesai SIT",IF(CD9<95%,"Proses UAT",IF(CD9=95%,"Selesai UAT",IF(CD9<100%,"Proses Implementasi","Selesai Implementasi")))))))))))))))))))))) -> Not Started | BS9: =IF(CE9=0%,"Not Started",IF(CE9<5%,"Proses RBT-RBB",IF(CE9=5%,"Selesai RBT-RBB",IF(CE9<10%,"Proses RBT-RBL",IF(CE9=10%,"Selesai RBT-RBL",IF(CE9<15%,"Proses RBT-RBTD",IF(CE9=15%,"Selesai RBT-RBTD",IF(CE9<20%,"Proses RPP",IF(CE9=20%,"Selesai RPP",IF(CE9<25%,"Proses KAK",IF(CE9=25%,"Selesai KAK",IF(CE9<30%,"Proses Pengadaan",IF(CE9=30%,"Selesai Pengadaan",IF(CE9<45%,"Proses Desain",IF(CE9=45%,"Selesai Desain",IF(CE9<80%,"Proses Pengembangan",IF(CE9=80%,"Selesai Pengembangan",IF(CE9<87.5%,"Proses SIT",IF(CE9=87.5%,"Selesai SIT",IF(CE9<95%,"Proses UAT",IF(CE9=95%,"Selesai UAT",IF(CE9<100%,"Proses Implementasi","Selesai Implementasi")))))))))))))))))))))) -> Not Started | BT9: =IF(CF9=0%,"Not Started",IF(CF9<5%,"Proses RBT-RBB",IF(CF9=5%,"Selesai RBT-RBB",IF(CF9<10%,"Proses RBT-RBL",IF(CF9=10%,"Selesai RBT-RBL",IF(CF9<15%,"Proses RBT-RBTD",IF(CF9=15%,"Selesai RBT-RBTD",IF(CF9<20%,"Proses RPP",IF(CF9=20%,"Selesai RPP",IF(CF9<25%,"Proses KAK",IF(CF9=25%,"Selesai KAK",IF(CF9<30%,"Proses Pengadaan",IF(CF9=30%,"Selesai Pengadaan",IF(CF9<45%,"Proses Desain",IF(CF9=45%,"Selesai Desain",IF(CF9<80%,"Proses Pengembangan",IF(CF9=80%,"Selesai Pengembangan",IF(CF9<87.5%,"Proses SIT",IF(CF9=87.5%,"Selesai SIT",IF(CF9<95%,"Proses UAT",IF(CF9=95%,"Selesai UAT",IF(CF9<100%,"Proses Implementasi","Selesai Implementasi")))))))))))))))))))))) -> Not Started | BU9: =IF(CG9=0%,"Not Started",IF(CG9<5%,"Proses RBT-RBB",IF(CG9=5%,"Selesai RBT-RBB",IF(CG9<10%,"Proses RBT-RBL",IF(CG9=10%,"Selesai RBT-RBL",IF(CG9<15%,"Proses RBT-RBTD",IF(CG9=15%,"Selesai RBT-RBTD",IF(CG9<20%,"Proses RPP",IF(CG9=20%,"Selesai RPP",IF(CG9<25%,"Proses KAK",IF(CG9=25%,"Selesai KAK",IF(CG9<30%,"Proses Pengadaan",IF(CG9=30%,"Selesai Pengadaan",IF(CG9<45%,"Proses Desain",IF(CG9=45%,"Selesai Desain",IF(CG9<80%,"Proses Pengembangan",IF(CG9=80%,"Selesai Pengembangan",IF(CG9<87.5%,"Proses SIT",IF(CG9=87.5%,"Selesai SIT",IF(CG9<95%,"Proses UAT",IF(CG9=95%,"Selesai UAT",IF(CG9<100%,"Proses Implementasi","Selesai Implementasi")))))))))))))))))))))) -> Not Started | BV9: =IF(CH9=0%,"Not Started",IF(CH9<5%,"Proses RBT-RBB",IF(CH9=5%,"Selesai RBT-RBB",IF(CH9<10%,"Proses RBT-RBL",IF(CH9=10%,"Selesai RBT-RBL",IF(CH9<15%,"Proses RBT-RBTD",IF(CH9=15%,"Selesai RBT-RBTD",IF(CH9<20%,"Proses RPP",IF(CH9=20%,"Selesai RPP",IF(CH9<25%,"Proses KAK",IF(CH9=25%,"Selesai KAK",IF(CH9<30%,"Proses Pengadaan",IF(CH9=30%,"Selesai Pengadaan",IF(CH9<45%,"Proses Desain",IF(CH9=45%,"Selesai Desain",IF(CH9<80%,"Proses Pengembangan",IF(CH9=80%,"Selesai Pengembangan",IF(CH9<87.5%,"Proses SIT",IF(CH9=87.5%,"Selesai SIT",IF(CH9<95%,"Proses UAT",IF(CH9=95%,"Selesai UAT",IF(CH9<100%,"Proses Implementasi","Selesai Implementasi")))))))))))))))))))))) -> Not Started | BW9: =IF(CI9=0%,"Not Started",IF(CI9<5%,"Proses RBT-RBB",IF(CI9=5%,"Selesai RBT-RBB",IF(CI9<10%,"Proses RBT-RBL",IF(CI9=10%,"Selesai RBT-RBL",IF(CI9<15%,"Proses RBT-RBTD",IF(CI9=15%,"Selesai RBT-RBTD",IF(CI9<20%,"Proses RPP",IF(CI9=20%,"Selesai RPP",IF(CI9<25%,"Proses KAK",IF(CI9=25%,"Selesai KAK",IF(CI9<30%,"Proses Pengadaan",IF(CI9=30%,"Selesai Pengadaan",IF(CI9<45%,"Proses Desain",IF(CI9=45%,"Selesai Desain",IF(CI9<80%,"Proses Pengembangan",IF(CI9=80%,"Selesai Pengembangan",IF(CI9<87.5%,"Proses SIT",IF(CI9=87.5%,"Selesai SIT",IF(CI9<95%,"Proses UAT",IF(CI9=95%,"Selesai UAT",IF(CI9<100%,"Proses Implementasi","Selesai Implementasi")))))))))))))))))))))) -> Not Started | BX9: =IF(CJ9=0%,"Not Started",IF(CJ9<5%,"Proses RBT-RBB",IF(CJ9=5%,"Selesai RBT-RBB",IF(CJ9<10%,"Proses RBT-RBL",IF(CJ9=10%,"Selesai RBT-RBL",IF(CJ9<15%,"Proses RBT-RBTD",IF(CJ9=15%,"Selesai RBT-RBTD",IF(CJ9<20%,"Proses RPP",IF(CJ9=20%,"Selesai RPP",IF(CJ9<25%,"Proses KAK",IF(CJ9=25%,"Selesai KAK",IF(CJ9<30%,"Proses Pengadaan",IF(CJ9=30%,"Selesai Pengadaan",IF(CJ9<45%,"Proses Desain",IF(CJ9=45%,"Selesai Desain",IF(CJ9<80%,"Proses Pengembangan",IF(CJ9=80%,"Selesai Pengembangan",IF(CJ9<87.5%,"Proses SIT",IF(CJ9=87.5%,"Selesai SIT",IF(CJ9<95%,"Proses UAT",IF(CJ9=95%,"Selesai UAT",IF(CJ9<100%,"Proses Implementasi","Selesai Implementasi")))))))))))))))))))))) -> Not Started | ... CB9: =IF(CN9=0%,"Not Started",IF(CN9<5%,"Proses RBT-RBB",IF(CN9=5%,"Selesai RBT-RBB",IF(CN9<10%,"Proses RBT-RBL",IF(CN9=10%,"Selesai RBT-RBL",IF(CN9<15%,"Proses RBT-RBTD",IF(CN9=15%,"Selesai RBT-RBTD",IF(CN9<20%,"Proses RPP",IF(CN9=20%,"Selesai RPP",IF(CN9<25%,"Proses KAK",IF(CN9=25%,"Selesai KAK",IF(CN9<30%,"Proses Pengadaan",IF(CN9=30%,"Selesai Pengadaan",IF(CN9<45%,"Proses Desain",IF(CN9=45%,"Selesai Desain",IF(CN9<80%,"Proses Pengembangan",IF(CN9=80%,"Selesai Pengembangan",IF(CN9<87.5%,"Proses SIT",IF(CN9=87.5%,"Selesai SIT",IF(CN9<95%,"Proses UAT",IF(CN9=95%,"Selesai UAT",IF(CN9<100%,"Proses Implementasi","Selesai Implementasi")))))))))))))))))))))) -> Not Started | CC9: =(($DY9/100%)*15%)+(($DZ9/100%)*5%)+(($EA9/100%)*5%)+(($EB9/100%)*5%)+(($EC9/100%)*15%)+(($ED9/100%)*35%)+(($EE9/100%)*7.5%)+(($EF9/100%)*7.5%)+(($EG9/100%)*5%) -> 0 | CO9: =IF(BE9=0%, 100%, (CC9/BE9)) -> 1 | CP9: =IF(BF9=0%, 100%, (CD9/BF9)) -> 1 | CQ9: =IF(BG9=0%, 100%, (CE9/BG9)) -> 1 | CR9: =IF(BH9=0%, 100%, (CF9/BH9)) -> 0 | CS9: =IF(BI9=0%, 100%, (CG9/BI9)) -> 0 | CT9: =IF(BJ9=0%, 100%, (CH9/BJ9)) -> 0 | CU9: =IF(BK9=0%, 100%, (CI9/BK9)) -> 0 | CV9: =IF(BL9=0%, 100%, (CJ9/BL9)) -> 0 | ... CY9: =IF(BO9=0%, 100%, (CM9/BO9)) -> 0 | DA9: =IF(BE9=0%,"NS",IF(CC9=100%,"DONE",IF(CO9>100%,"AS",IF(CO9<75%,"BS",IF(CO9<89.9%,"AR","OS"))))) -> NS | DB9: =IF(BF9=0%,"NS",IF(CD9=100%,"DONE",IF(CP9>100%,"AS",IF(CP9<75%,"BS",IF(CP9<89.9%,"AR","OS"))))) -> NS | DC9: =IF(BG9=0%,"NS",IF(CE9=100%,"DONE",IF(CQ9>100%,"AS",IF(CQ9<75%,"BS",IF(CQ9<89.9%,"AR","OS"))))) -> NS | DD9: =IF(BH9=0%,"NS",IF(CF9=100%,"DONE",IF(CR9>100%,"AS",IF(CR9<75%,"BS",IF(CR9<89.9%,"AR","OS"))))) -> BS | DE9: =IF(BI9=0%,"NS",IF(CG9=100%,"DONE",IF(CS9>100%,"AS",IF(CS9<75%,"BS",IF(CS9<89.9%,"AR","OS"))))) -> BS | DF9: =IF(BJ9=0%,"NS",IF(CH9=100%,"DONE",IF(CT9>100%,"AS",IF(CT9<75%,"BS",IF(CT9<89.9%,"AR","OS"))))) -> BS | DG9: =IF(BK9=0%,"NS",IF(CI9=100%,"DONE",IF(CU9>100%,"AS",IF(CU9<75%,"BS",IF(CU9<89.9%,"AR","OS"))))) -> BS | DH9: =IF(BL9=0%,"NS",IF(CJ9=100%,"DONE",IF(CV9>100%,"AS",IF(CV9<75%,"BS",IF(CV9<89.9%,"AR","OS"))))) -> BS | ... DL9: =IF(BP9=0%,"NS",IF(CN9=100%,"DONE",IF(CZ9>100%,"AS",IF(CZ9<75%,"BS",IF(CZ9<89.9%,"AR","OS"))))) -> BS | DM9: =CC9/$BP9 -> 0 | DN9: =CD9/$BP9 -> 0 | DO9: =CE9/$BP9 -> 0 | DP9: =CF9/$BP9 -> 0 | DQ9: =CG9/$BP9 -> 0 | DR9: =CH9/$BP9 -> 0 | DS9: =CI9/$BP9 -> 0 | DT9: =CJ9/$BP9 -> 0 | ... DX9: =CN9/$BP9 -> 0 | EJ9: =AR9 -> 46477 | FN9: Helen Desyani | FO9: Iramia Triastika | FR9: Outsource
B10: PT2, BPPU | C10: IDT | D10: Continuity Technology | E10: P-4 | F10: =F9+1 -> 5 | G10: Pengembangan Product PUVA dan Penerbitan SBN | H10: Infrastruktur Data PUVA | I10: DEP Capturing Product -Pelaporan: CCP Repo | J10: 2026 | K10: 2027 | L10: S | M10: K3 | N10: Pemimpin Satker | O10: DPPK, DSta, DPKL | P10: WG-2 | Q10: Moneter, Market | R10: TBD | S10: =BQ10 -> Not Started | T10: =IF(V10=0%,"Not Started",IF(V10<100%,"On Progress",IF(V10=100%,"DONE"))) -> Not Started | U10: =FN10 -> Helen Desyani | V10: =CC10 -> 0 | W10: TW IV 2026 | X10: =AR10 -> 46660 | Z10: New | AA10: 46296 | AB10: 46386 | AC10: 46401 | AD10: 46053 | AE10: 46388 | AF10: 46401 | AI10: 46419 | AJ10: 46446 | AK10: 46447 | AL10: 46568 | AM10: 46569 | AN10: 46598 | AO10: 46600 | AP10: 46629 | AQ10: 46631 | AR10: 46660 | AS10: =IF(BE10=0%,"Not Started",IF(BE10<5%,"Proses RBT-RBB",IF(BE10=5%,"Selesai RBT-RBB",IF(BE10<10%,"Proses RBT-RBL",IF(BE10=10%,"Selesai RBT-RBL",IF(BE10<15%,"Proses RBT-RBTD",IF(BE10=15%,"Selesai RBT-RBTD",IF(BE10<20%,"Proses RPP",IF(BE10=20%,"Selesai RPP",IF(BE10<25%,"Proses KAK",IF(BE10=25%,"Selesai KAK",IF(BE10<30%,"Proses Pengadaan",IF(BE10=30%,"Selesai Pengadaan",IF(BE10<45%,"Proses Desain",IF(BE10=45%,"Selesai Desain",IF(BE10<80%,"Proses Pengembangan",IF(BE10=80%,"Selesai Pengembangan",IF(BE10<87.5%,"Proses SIT",IF(BE10=87.5%,"Selesai SIT",IF(BE10<95%,"Proses UAT",IF(BE10=95%,"Selesai UAT",IF(BE10<100%,"Proses Implementasi","Selesai Implementasi")))))))))))))))))))))) -> Not Started | AT10: =IF(BF10=0%,"Not Started",IF(BF10<5%,"Proses RBT-RBB",IF(BF10=5%,"Selesai RBT-RBB",IF(BF10<10%,"Proses RBT-RBL",IF(BF10=10%,"Selesai RBT-RBL",IF(BF10<15%,"Proses RBT-RBTD",IF(BF10=15%,"Selesai RBT-RBTD",IF(BF10<20%,"Proses RPP",IF(BF10=20%,"Selesai RPP",IF(BF10<25%,"Proses KAK",IF(BF10=25%,"Selesai KAK",IF(BF10<30%,"Proses Pengadaan",IF(BF10=30%,"Selesai Pengadaan",IF(BF10<45%,"Proses Desain",IF(BF10=45%,"Selesai Desain",IF(BF10<80%,"Proses Pengembangan",IF(BF10=80%,"Selesai Pengembangan",IF(BF10<87.5%,"Proses SIT",IF(BF10=87.5%,"Selesai SIT",IF(BF10<95%,"Proses UAT",IF(BF10=95%,"Selesai UAT",IF(BF10<100%,"Proses Implementasi","Selesai Implementasi")))))))))))))))))))))) -> Not Started | AU10: =IF(BG10=0%,"Not Started",IF(BG10<5%,"Proses RBT-RBB",IF(BG10=5%,"Selesai RBT-RBB",IF(BG10<10%,"Proses RBT-RBL",IF(BG10=10%,"Selesai RBT-RBL",IF(BG10<15%,"Proses RBT-RBTD",IF(BG10=15%,"Selesai RBT-RBTD",IF(BG10<20%,"Proses RPP",IF(BG10=20%,"Selesai RPP",IF(BG10<25%,"Proses KAK",IF(BG10=25%,"Selesai KAK",IF(BG10<30%,"Proses Pengadaan",IF(BG10=30%,"Selesai Pengadaan",IF(BG10<45%,"Proses Desain",IF(BG10=45%,"Selesai Desain",IF(BG10<80%,"Proses Pengembangan",IF(BG10=80%,"Selesai Pengembangan",IF(BG10<87.5%,"Proses SIT",IF(BG10=87.5%,"Selesai SIT",IF(BG10<95%,"Proses UAT",IF(BG10=95%,"Selesai UAT",IF(BG10<100%,"Proses Implementasi","Selesai Implementasi")))))))))))))))))))))) -> Not Started | AV10: =IF(BH10=0%,"Not Started",IF(BH10<5%,"Proses RBT-RBB",IF(BH10=5%,"Selesai RBT-RBB",IF(BH10<10%,"Proses RBT-RBL",IF(BH10=10%,"Selesai RBT-RBL",IF(BH10<15%,"Proses RBT-RBTD",IF(BH10=15%,"Selesai RBT-RBTD",IF(BH10<20%,"Proses RPP",IF(BH10=20%,"Selesai RPP",IF(BH10<25%,"Proses KAK",IF(BH10=25%,"Selesai KAK",IF(BH10<30%,"Proses Pengadaan",IF(BH10=30%,"Selesai Pengadaan",IF(BH10<45%,"Proses Desain",IF(BH10=45%,"Selesai Desain",IF(BH10<80%,"Proses Pengembangan",IF(BH10=80%,"Selesai Pengembangan",IF(BH10<87.5%,"Proses SIT",IF(BH10=87.5%,"Selesai SIT",IF(BH10<95%,"Proses UAT",IF(BH10=95%,"Selesai UAT",IF(BH10<100%,"Proses Implementasi","Selesai Implementasi")))))))))))))))))))))) -> Not Started | AW10: =IF(BI10=0%,"Not Started",IF(BI10<5%,"Proses RBT-RBB",IF(BI10=5%,"Selesai RBT-RBB",IF(BI10<10%,"Proses RBT-RBL",IF(BI10=10%,"Selesai RBT-RBL",IF(BI10<15%,"Proses RBT-RBTD",IF(BI10=15%,"Selesai RBT-RBTD",IF(BI10<20%,"Proses RPP",IF(BI10=20%,"Selesai RPP",IF(BI10<25%,"Proses KAK",IF(BI10=25%,"Selesai KAK",IF(BI10<30%,"Proses Pengadaan",IF(BI10=30%,"Selesai Pengadaan",IF(BI10<45%,"Proses Desain",IF(BI10=45%,"Selesai Desain",IF(BI10<80%,"Proses Pengembangan",IF(BI10=80%,"Selesai Pengembangan",IF(BI10<87.5%,"Proses SIT",IF(BI10=87.5%,"Selesai SIT",IF(BI10<95%,"Proses UAT",IF(BI10=95%,"Selesai UAT",IF(BI10<100%,"Proses Implementasi","Selesai Implementasi")))))))))))))))))))))) -> Not Started | AX10: =IF(BJ10=0%,"Not Started",IF(BJ10<5%,"Proses RBT-RBB",IF(BJ10=5%,"Selesai RBT-RBB",IF(BJ10<10%,"Proses RBT-RBL",IF(BJ10=10%,"Selesai RBT-RBL",IF(BJ10<15%,"Proses RBT-RBTD",IF(BJ10=15%,"Selesai RBT-RBTD",IF(BJ10<20%,"Proses RPP",IF(BJ10=20%,"Selesai RPP",IF(BJ10<25%,"Proses KAK",IF(BJ10=25%,"Selesai KAK",IF(BJ10<30%,"Proses Pengadaan",IF(BJ10=30%,"Selesai Pengadaan",IF(BJ10<45%,"Proses Desain",IF(BJ10=45%,"Selesai Desain",IF(BJ10<80%,"Proses Pengembangan",IF(BJ10=80%,"Selesai Pengembangan",IF(BJ10<87.5%,"Proses SIT",IF(BJ10=87.5%,"Selesai SIT",IF(BJ10<95%,"Proses UAT",IF(BJ10=95%,"Selesai UAT",IF(BJ10<100%,"Proses Implementasi","Selesai Implementasi")))))))))))))))))))))) -> Not Started | AY10: =IF(BK10=0%,"Not Started",IF(BK10<5%,"Proses RBT-RBB",IF(BK10=5%,"Selesai RBT-RBB",IF(BK10<10%,"Proses RBT-RBL",IF(BK10=10%,"Selesai RBT-RBL",IF(BK10<15%,"Proses RBT-RBTD",IF(BK10=15%,"Selesai RBT-RBTD",IF(BK10<20%,"Proses RPP",IF(BK10=20%,"Selesai RPP",IF(BK10<25%,"Proses KAK",IF(BK10=25%,"Selesai KAK",IF(BK10<30%,"Proses Pengadaan",IF(BK10=30%,"Selesai Pengadaan",IF(BK10<45%,"Proses Desain",IF(BK10=45%,"Selesai Desain",IF(BK10<80%,"Proses Pengembangan",IF(BK10=80%,"Selesai Pengembangan",IF(BK10<87.5%,"Proses SIT",IF(BK10=87.5%,"Selesai SIT",IF(BK10<95%,"Proses UAT",IF(BK10=95%,"Selesai UAT",IF(BK10<100%,"Proses Implementasi","Selesai Implementasi")))))))))))))))))))))) -> Not Started | AZ10: =IF(BL10=0%,"Not Started",IF(BL10<5%,"Proses RBT-RBB",IF(BL10=5%,"Selesai RBT-RBB",IF(BL10<10%,"Proses RBT-RBL",IF(BL10=10%,"Selesai RBT-RBL",IF(BL10<15%,"Proses RBT-RBTD",IF(BL10=15%,"Selesai RBT-RBTD",IF(BL10<20%,"Proses RPP",IF(BL10=20%,"Selesai RPP",IF(BL10<25%,"Proses KAK",IF(BL10=25%,"Selesai KAK",IF(BL10<30%,"Proses Pengadaan",IF(BL10=30%,"Selesai Pengadaan",IF(BL10<45%,"Proses Desain",IF(BL10=45%,"Selesai Desain",IF(BL10<80%,"Proses Pengembangan",IF(BL10=80%,"Selesai Pengembangan",IF(BL10<87.5%,"Proses SIT",IF(BL10=87.5%,"Selesai SIT",IF(BL10<95%,"Proses UAT",IF(BL10=95%,"Selesai UAT",IF(BL10<100%,"Proses Implementasi","Selesai Implementasi")))))))))))))))))))))) -> Not Started | ... BD10: =IF(BP10=0%,"Not Started",IF(BP10<5%,"Proses RBT-RBB",IF(BP10=5%,"Selesai RBT-RBB",IF(BP10<10%,"Proses RBT-RBL",IF(BP10=10%,"Selesai RBT-RBL",IF(BP10<15%,"Proses RBT-RBTD",IF(BP10=15%,"Selesai RBT-RBTD",IF(BP10<20%,"Proses RPP",IF(BP10=20%,"Selesai RPP",IF(BP10<25%,"Proses KAK",IF(BP10=25%,"Selesai KAK",IF(BP10<30%,"Proses Pengadaan",IF(BP10=30%,"Selesai Pengadaan",IF(BP10<45%,"Proses Desain",IF(BP10=45%,"Selesai Desain",IF(BP10<80%,"Proses Pengembangan",IF(BP10=80%,"Selesai Pengembangan",IF(BP10<87.5%,"Proses SIT",IF(BP10=87.5%,"Selesai SIT",IF(BP10<95%,"Proses UAT",IF(BP10=95%,"Selesai UAT",IF(BP10<100%,"Proses Implementasi","Selesai Implementasi")))))))))))))))))))))) -> Selesai RBT-RBTD | BE10: 0 | BF10: 0 | BG10: 0 | BH10: 0 | BI10: 0 | BJ10: 0 | BK10: 0 | BL10: 0 | BM10: 0 | BN10: 0.05 | BO10: 0.1 | BP10: 0.15 | BQ10: =IF(CC10=0%,"Not Started",IF(CC10<5%,"Proses RBT-RBB",IF(CC10=5%,"Selesai RBT-RBB",IF(CC10<10%,"Proses RBT-RBL",IF(CC10=10%,"Selesai RBT-RBL",IF(CC10<15%,"Proses RBT-RBTD",IF(CC10=15%,"Selesai RBT-RBTD",IF(CC10<20%,"Proses RPP",IF(CC10=20%,"Selesai RPP",IF(CC10<25%,"Proses KAK",IF(CC10=25%,"Selesai KAK",IF(CC10<30%,"Proses Pengadaan",IF(CC10=30%,"Selesai Pengadaan",IF(CC10<45%,"Proses Desain",IF(CC10=45%,"Selesai Desain",IF(CC10<80%,"Proses Pengembangan",IF(CC10=80%,"Selesai Pengembangan",IF(CC10<87.5%,"Proses SIT",IF(CC10=87.5%,"Selesai SIT",IF(CC10<95%,"Proses UAT",IF(CC10=95%,"Selesai UAT",IF(CC10<100%,"Proses Implementasi","Selesai Implementasi")))))))))))))))))))))) -> Not Started | BR10: =IF(CD10=0%,"Not Started",IF(CD10<5%,"Proses RBT-RBB",IF(CD10=5%,"Selesai RBT-RBB",IF(CD10<10%,"Proses RBT-RBL",IF(CD10=10%,"Selesai RBT-RBL",IF(CD10<15%,"Proses RBT-RBTD",IF(CD10=15%,"Selesai RBT-RBTD",IF(CD10<20%,"Proses RPP",IF(CD10=20%,"Selesai RPP",IF(CD10<25%,"Proses KAK",IF(CD10=25%,"Selesai KAK",IF(CD10<30%,"Proses Pengadaan",IF(CD10=30%,"Selesai Pengadaan",IF(CD10<45%,"Proses Desain",IF(CD10=45%,"Selesai Desain",IF(CD10<80%,"Proses Pengembangan",IF(CD10=80%,"Selesai Pengembangan",IF(CD10<87.5%,"Proses SIT",IF(CD10=87.5%,"Selesai SIT",IF(CD10<95%,"Proses UAT",IF(CD10=95%,"Selesai UAT",IF(CD10<100%,"Proses Implementasi","Selesai Implementasi")))))))))))))))))))))) -> Not Started | BS10: =IF(CE10=0%,"Not Started",IF(CE10<5%,"Proses RBT-RBB",IF(CE10=5%,"Selesai RBT-RBB",IF(CE10<10%,"Proses RBT-RBL",IF(CE10=10%,"Selesai RBT-RBL",IF(CE10<15%,"Proses RBT-RBTD",IF(CE10=15%,"Selesai RBT-RBTD",IF(CE10<20%,"Proses RPP",IF(CE10=20%,"Selesai RPP",IF(CE10<25%,"Proses KAK",IF(CE10=25%,"Selesai KAK",IF(CE10<30%,"Proses Pengadaan",IF(CE10=30%,"Selesai Pengadaan",IF(CE10<45%,"Proses Desain",IF(CE10=45%,"Selesai Desain",IF(CE10<80%,"Proses Pengembangan",IF(CE10=80%,"Selesai Pengembangan",IF(CE10<87.5%,"Proses SIT",IF(CE10=87.5%,"Selesai SIT",IF(CE10<95%,"Proses UAT",IF(CE10=95%,"Selesai UAT",IF(CE10<100%,"Proses Implementasi","Selesai Implementasi")))))))))))))))))))))) -> Not Started | BT10: =IF(CF10=0%,"Not Started",IF(CF10<5%,"Proses RBT-RBB",IF(CF10=5%,"Selesai RBT-RBB",IF(CF10<10%,"Proses RBT-RBL",IF(CF10=10%,"Selesai RBT-RBL",IF(CF10<15%,"Proses RBT-RBTD",IF(CF10=15%,"Selesai RBT-RBTD",IF(CF10<20%,"Proses RPP",IF(CF10=20%,"Selesai RPP",IF(CF10<25%,"Proses KAK",IF(CF10=25%,"Selesai KAK",IF(CF10<30%,"Proses Pengadaan",IF(CF10=30%,"Selesai Pengadaan",IF(CF10<45%,"Proses Desain",IF(CF10=45%,"Selesai Desain",IF(CF10<80%,"Proses Pengembangan",IF(CF10=80%,"Selesai Pengembangan",IF(CF10<87.5%,"Proses SIT",IF(CF10=87.5%,"Selesai SIT",IF(CF10<95%,"Proses UAT",IF(CF10=95%,"Selesai UAT",IF(CF10<100%,"Proses Implementasi","Selesai Implementasi")))))))))))))))))))))) -> Not Started | BU10: =IF(CG10=0%,"Not Started",IF(CG10<5%,"Proses RBT-RBB",IF(CG10=5%,"Selesai RBT-RBB",IF(CG10<10%,"Proses RBT-RBL",IF(CG10=10%,"Selesai RBT-RBL",IF(CG10<15%,"Proses RBT-RBTD",IF(CG10=15%,"Selesai RBT-RBTD",IF(CG10<20%,"Proses RPP",IF(CG10=20%,"Selesai RPP",IF(CG10<25%,"Proses KAK",IF(CG10=25%,"Selesai KAK",IF(CG10<30%,"Proses Pengadaan",IF(CG10=30%,"Selesai Pengadaan",IF(CG10<45%,"Proses Desain",IF(CG10=45%,"Selesai Desain",IF(CG10<80%,"Proses Pengembangan",IF(CG10=80%,"Selesai Pengembangan",IF(CG10<87.5%,"Proses SIT",IF(CG10=87.5%,"Selesai SIT",IF(CG10<95%,"Proses UAT",IF(CG10=95%,"Selesai UAT",IF(CG10<100%,"Proses Implementasi","Selesai Implementasi")))))))))))))))))))))) -> Not Started | BV10: =IF(CH10=0%,"Not Started",IF(CH10<5%,"Proses RBT-RBB",IF(CH10=5%,"Selesai RBT-RBB",IF(CH10<10%,"Proses RBT-RBL",IF(CH10=10%,"Selesai RBT-RBL",IF(CH10<15%,"Proses RBT-RBTD",IF(CH10=15%,"Selesai RBT-RBTD",IF(CH10<20%,"Proses RPP",IF(CH10=20%,"Selesai RPP",IF(CH10<25%,"Proses KAK",IF(CH10=25%,"Selesai KAK",IF(CH10<30%,"Proses Pengadaan",IF(CH10=30%,"Selesai Pengadaan",IF(CH10<45%,"Proses Desain",IF(CH10=45%,"Selesai Desain",IF(CH10<80%,"Proses Pengembangan",IF(CH10=80%,"Selesai Pengembangan",IF(CH10<87.5%,"Proses SIT",IF(CH10=87.5%,"Selesai SIT",IF(CH10<95%,"Proses UAT",IF(CH10=95%,"Selesai UAT",IF(CH10<100%,"Proses Implementasi","Selesai Implementasi")))))))))))))))))))))) -> Not Started | BW10: =IF(CI10=0%,"Not Started",IF(CI10<5%,"Proses RBT-RBB",IF(CI10=5%,"Selesai RBT-RBB",IF(CI10<10%,"Proses RBT-RBL",IF(CI10=10%,"Selesai RBT-RBL",IF(CI10<15%,"Proses RBT-RBTD",IF(CI10=15%,"Selesai RBT-RBTD",IF(CI10<20%,"Proses RPP",IF(CI10=20%,"Selesai RPP",IF(CI10<25%,"Proses KAK",IF(CI10=25%,"Selesai KAK",IF(CI10<30%,"Proses Pengadaan",IF(CI10=30%,"Selesai Pengadaan",IF(CI10<45%,"Proses Desain",IF(CI10=45%,"Selesai Desain",IF(CI10<80%,"Proses Pengembangan",IF(CI10=80%,"Selesai Pengembangan",IF(CI10<87.5%,"Proses SIT",IF(CI10=87.5%,"Selesai SIT",IF(CI10<95%,"Proses UAT",IF(CI10=95%,"Selesai UAT",IF(CI10<100%,"Proses Implementasi","Selesai Implementasi")))))))))))))))))))))) -> Not Started | BX10: =IF(CJ10=0%,"Not Started",IF(CJ10<5%,"Proses RBT-RBB",IF(CJ10=5%,"Selesai RBT-RBB",IF(CJ10<10%,"Proses RBT-RBL",IF(CJ10=10%,"Selesai RBT-RBL",IF(CJ10<15%,"Proses RBT-RBTD",IF(CJ10=15%,"Selesai RBT-RBTD",IF(CJ10<20%,"Proses RPP",IF(CJ10=20%,"Selesai RPP",IF(CJ10<25%,"Proses KAK",IF(CJ10=25%,"Selesai KAK",IF(CJ10<30%,"Proses Pengadaan",IF(CJ10=30%,"Selesai Pengadaan",IF(CJ10<45%,"Proses Desain",IF(CJ10=45%,"Selesai Desain",IF(CJ10<80%,"Proses Pengembangan",IF(CJ10=80%,"Selesai Pengembangan",IF(CJ10<87.5%,"Proses SIT",IF(CJ10=87.5%,"Selesai SIT",IF(CJ10<95%,"Proses UAT",IF(CJ10=95%,"Selesai UAT",IF(CJ10<100%,"Proses Implementasi","Selesai Implementasi")))))))))))))))))))))) -> Not Started | ... CB10: =IF(CN10=0%,"Not Started",IF(CN10<5%,"Proses RBT-RBB",IF(CN10=5%,"Selesai RBT-RBB",IF(CN10<10%,"Proses RBT-RBL",IF(CN10=10%,"Selesai RBT-RBL",IF(CN10<15%,"Proses RBT-RBTD",IF(CN10=15%,"Selesai RBT-RBTD",IF(CN10<20%,"Proses RPP",IF(CN10=20%,"Selesai RPP",IF(CN10<25%,"Proses KAK",IF(CN10=25%,"Selesai KAK",IF(CN10<30%,"Proses Pengadaan",IF(CN10=30%,"Selesai Pengadaan",IF(CN10<45%,"Proses Desain",IF(CN10=45%,"Selesai Desain",IF(CN10<80%,"Proses Pengembangan",IF(CN10=80%,"Selesai Pengembangan",IF(CN10<87.5%,"Proses SIT",IF(CN10=87.5%,"Selesai SIT",IF(CN10<95%,"Proses UAT",IF(CN10=95%,"Selesai UAT",IF(CN10<100%,"Proses Implementasi","Selesai Implementasi")))))))))))))))))))))) -> Not Started | CC10: =(($DY10/100%)*15%)+(($DZ10/100%)*5%)+(($EA10/100%)*5%)+(($EB10/100%)*5%)+(($EC10/100%)*15%)+(($ED10/100%)*35%)+(($EE10/100%)*7.5%)+(($EF10/100%)*7.5%)+(($EG10/100%)*5%) -> 0 | CO10: =IF(BE10=0%, 100%, (CC10/BE10)) -> 1 | CP10: =IF(BF10=0%, 100%, (CD10/BF10)) -> 1 | CQ10: =IF(BG10=0%, 100%, (CE10/BG10)) -> 1 | CR10: =IF(BH10=0%, 100%, (CF10/BH10)) -> 1 | CS10: =IF(BI10=0%, 100%, (CG10/BI10)) -> 1 | CT10: =IF(BJ10=0%, 100%, (CH10/BJ10)) -> 1 | CU10: =IF(BK10=0%, 100%, (CI10/BK10)) -> 1 | CV10: =IF(BL10=0%, 100%, (CJ10/BL10)) -> 1 | ... CY10: =IF(BO10=0%, 100%, (CM10/BO10)) -> 0 | DA10: =IF(BE10=0%,"NS",IF(CC10=100%,"DONE",IF(CO10>100%,"AS",IF(CO10<75%,"BS",IF(CO10<89.9%,"AR","OS"))))) -> NS | DB10: =IF(BF10=0%,"NS",IF(CD10=100%,"DONE",IF(CP10>100%,"AS",IF(CP10<75%,"BS",IF(CP10<89.9%,"AR","OS"))))) -> NS | DC10: =IF(BG10=0%,"NS",IF(CE10=100%,"DONE",IF(CQ10>100%,"AS",IF(CQ10<75%,"BS",IF(CQ10<89.9%,"AR","OS"))))) -> NS | DD10: =IF(BH10=0%,"NS",IF(CF10=100%,"DONE",IF(CR10>100%,"AS",IF(CR10<75%,"BS",IF(CR10<89.9%,"AR","OS"))))) -> NS | DE10: =IF(BI10=0%,"NS",IF(CG10=100%,"DONE",IF(CS10>100%,"AS",IF(CS10<75%,"BS",IF(CS10<89.9%,"AR","OS"))))) -> NS | DF10: =IF(BJ10=0%,"NS",IF(CH10=100%,"DONE",IF(CT10>100%,"AS",IF(CT10<75%,"BS",IF(CT10<89.9%,"AR","OS"))))) -> NS | DG10: =IF(BK10=0%,"NS",IF(CI10=100%,"DONE",IF(CU10>100%,"AS",IF(CU10<75%,"BS",IF(CU10<89.9%,"AR","OS"))))) -> NS | DH10: =IF(BL10=0%,"NS",IF(CJ10=100%,"DONE",IF(CV10>100%,"AS",IF(CV10<75%,"BS",IF(CV10<89.9%,"AR","OS"))))) -> NS | ... DL10: =IF(BP10=0%,"NS",IF(CN10=100%,"DONE",IF(CZ10>100%,"AS",IF(CZ10<75%,"BS",IF(CZ10<89.9%,"AR","OS"))))) -> BS | DM10: =CC10/$BP10 -> 0 | DN10: =CD10/$BP10 -> 0 | DO10: =CE10/$BP10 -> 0 | DP10: =CF10/$BP10 -> 0 | DQ10: =CG10/$BP10 -> 0 | DR10: =CH10/$BP10 -> 0 | DS10: =CI10/$BP10 -> 0 | DT10: =CJ10/$BP10 -> 0 | ... DX10: =CN10/$BP10 -> 0 | EJ10: =AR10 -> 46660 | FN10: Helen Desyani | FO10: Iramia Triastika | FR10: Outsource
B11: PT2, BPPU | C11: IDT | D11: Continuity Technology | E11: P-4 | F11: =F10+1 -> 6 | G11: Pengembangan Product PUVA dan Penerbitan SBN | H11: Infrastruktur Data PUVA | I11: EDP Capturing Product -Pelaporan: CCP OIS | J11: 2028 | K11: 2028 | L11: S | M11: K3 | N11: Pemimpin Satker | O11: DPPK, DSta, DPKL | P11: WG-2 | Q11: Moneter, Market | R11: TBD | S11: =BQ11 -> Not Started | T11: =IF(V11=0%,"Not Started",IF(V11<100%,"On Progress",IF(V11=100%,"DONE"))) -> Not Started | U11: =FN11 -> 0 | V11: =CC11 -> 0 | W11: TW I 2028 | X11: =AR11 -> 47118 | Z11: New | AA11: 46753 | AB11: 46842 | AC11: 46857 | AD11: 46873 | AE11: 46844 | AF11: 46857 | AI11: 46874 | AJ11: 46903 | AK11: 46905 | AL11: 47026 | AM11: 47027 | AN11: 47056 | AO11: 47058 | AP11: 47087 | AQ11: 47088 | AR11: 47118 | AS11: =IF(BE11=0%,"Not Started",IF(BE11<5%,"Proses RBT-RBB",IF(BE11=5%,"Selesai RBT-RBB",IF(BE11<10%,"Proses RBT-RBL",IF(BE11=10%,"Selesai RBT-RBL",IF(BE11<15%,"Proses RBT-RBTD",IF(BE11=15%,"Selesai RBT-RBTD",IF(BE11<20%,"Proses RPP",IF(BE11=20%,"Selesai RPP",IF(BE11<25%,"Proses KAK",IF(BE11=25%,"Selesai KAK",IF(BE11<30%,"Proses Pengadaan",IF(BE11=30%,"Selesai Pengadaan",IF(BE11<45%,"Proses Desain",IF(BE11=45%,"Selesai Desain",IF(BE11<80%,"Proses Pengembangan",IF(BE11=80%,"Selesai Pengembangan",IF(BE11<87.5%,"Proses SIT",IF(BE11=87.5%,"Selesai SIT",IF(BE11<95%,"Proses UAT",IF(BE11=95%,"Selesai UAT",IF(BE11<100%,"Proses Implementasi","Selesai Implementasi")))))))))))))))))))))) -> Not Started | AT11: =IF(BF11=0%,"Not Started",IF(BF11<5%,"Proses RBT-RBB",IF(BF11=5%,"Selesai RBT-RBB",IF(BF11<10%,"Proses RBT-RBL",IF(BF11=10%,"Selesai RBT-RBL",IF(BF11<15%,"Proses RBT-RBTD",IF(BF11=15%,"Selesai RBT-RBTD",IF(BF11<20%,"Proses RPP",IF(BF11=20%,"Selesai RPP",IF(BF11<25%,"Proses KAK",IF(BF11=25%,"Selesai KAK",IF(BF11<30%,"Proses Pengadaan",IF(BF11=30%,"Selesai Pengadaan",IF(BF11<45%,"Proses Desain",IF(BF11=45%,"Selesai Desain",IF(BF11<80%,"Proses Pengembangan",IF(BF11=80%,"Selesai Pengembangan",IF(BF11<87.5%,"Proses SIT",IF(BF11=87.5%,"Selesai SIT",IF(BF11<95%,"Proses UAT",IF(BF11=95%,"Selesai UAT",IF(BF11<100%,"Proses Implementasi","Selesai Implementasi")))))))))))))))))))))) -> Not Started | AU11: =IF(BG11=0%,"Not Started",IF(BG11<5%,"Proses RBT-RBB",IF(BG11=5%,"Selesai RBT-RBB",IF(BG11<10%,"Proses RBT-RBL",IF(BG11=10%,"Selesai RBT-RBL",IF(BG11<15%,"Proses RBT-RBTD",IF(BG11=15%,"Selesai RBT-RBTD",IF(BG11<20%,"Proses RPP",IF(BG11=20%,"Selesai RPP",IF(BG11<25%,"Proses KAK",IF(BG11=25%,"Selesai KAK",IF(BG11<30%,"Proses Pengadaan",IF(BG11=30%,"Selesai Pengadaan",IF(BG11<45%,"Proses Desain",IF(BG11=45%,"Selesai Desain",IF(BG11<80%,"Proses Pengembangan",IF(BG11=80%,"Selesai Pengembangan",IF(BG11<87.5%,"Proses SIT",IF(BG11=87.5%,"Selesai SIT",IF(BG11<95%,"Proses UAT",IF(BG11=95%,"Selesai UAT",IF(BG11<100%,"Proses Implementasi","Selesai Implementasi")))))))))))))))))))))) -> Not Started | AV11: =IF(BH11=0%,"Not Started",IF(BH11<5%,"Proses RBT-RBB",IF(BH11=5%,"Selesai RBT-RBB",IF(BH11<10%,"Proses RBT-RBL",IF(BH11=10%,"Selesai RBT-RBL",IF(BH11<15%,"Proses RBT-RBTD",IF(BH11=15%,"Selesai RBT-RBTD",IF(BH11<20%,"Proses RPP",IF(BH11=20%,"Selesai RPP",IF(BH11<25%,"Proses KAK",IF(BH11=25%,"Selesai KAK",IF(BH11<30%,"Proses Pengadaan",IF(BH11=30%,"Selesai Pengadaan",IF(BH11<45%,"Proses Desain",IF(BH11=45%,"Selesai Desain",IF(BH11<80%,"Proses Pengembangan",IF(BH11=80%,"Selesai Pengembangan",IF(BH11<87.5%,"Proses SIT",IF(BH11=87.5%,"Selesai SIT",IF(BH11<95%,"Proses UAT",IF(BH11=95%,"Selesai UAT",IF(BH11<100%,"Proses Implementasi","Selesai Implementasi")))))))))))))))))))))) -> Not Started | AW11: =IF(BI11=0%,"Not Started",IF(BI11<5%,"Proses RBT-RBB",IF(BI11=5%,"Selesai RBT-RBB",IF(BI11<10%,"Proses RBT-RBL",IF(BI11=10%,"Selesai RBT-RBL",IF(BI11<15%,"Proses RBT-RBTD",IF(BI11=15%,"Selesai RBT-RBTD",IF(BI11<20%,"Proses RPP",IF(BI11=20%,"Selesai RPP",IF(BI11<25%,"Proses KAK",IF(BI11=25%,"Selesai KAK",IF(BI11<30%,"Proses Pengadaan",IF(BI11=30%,"Selesai Pengadaan",IF(BI11<45%,"Proses Desain",IF(BI11=45%,"Selesai Desain",IF(BI11<80%,"Proses Pengembangan",IF(BI11=80%,"Selesai Pengembangan",IF(BI11<87.5%,"Proses SIT",IF(BI11=87.5%,"Selesai SIT",IF(BI11<95%,"Proses UAT",IF(BI11=95%,"Selesai UAT",IF(BI11<100%,"Proses Implementasi","Selesai Implementasi")))))))))))))))))))))) -> Not Started | AX11: =IF(BJ11=0%,"Not Started",IF(BJ11<5%,"Proses RBT-RBB",IF(BJ11=5%,"Selesai RBT-RBB",IF(BJ11<10%,"Proses RBT-RBL",IF(BJ11=10%,"Selesai RBT-RBL",IF(BJ11<15%,"Proses RBT-RBTD",IF(BJ11=15%,"Selesai RBT-RBTD",IF(BJ11<20%,"Proses RPP",IF(BJ11=20%,"Selesai RPP",IF(BJ11<25%,"Proses KAK",IF(BJ11=25%,"Selesai KAK",IF(BJ11<30%,"Proses Pengadaan",IF(BJ11=30%,"Selesai Pengadaan",IF(BJ11<45%,"Proses Desain",IF(BJ11=45%,"Selesai Desain",IF(BJ11<80%,"Proses Pengembangan",IF(BJ11=80%,"Selesai Pengembangan",IF(BJ11<87.5%,"Proses SIT",IF(BJ11=87.5%,"Selesai SIT",IF(BJ11<95%,"Proses UAT",IF(BJ11=95%,"Selesai UAT",IF(BJ11<100%,"Proses Implementasi","Selesai Implementasi")))))))))))))))))))))) -> Not Started | AY11: =IF(BK11=0%,"Not Started",IF(BK11<5%,"Proses RBT-RBB",IF(BK11=5%,"Selesai RBT-RBB",IF(BK11<10%,"Proses RBT-RBL",IF(BK11=10%,"Selesai RBT-RBL",IF(BK11<15%,"Proses RBT-RBTD",IF(BK11=15%,"Selesai RBT-RBTD",IF(BK11<20%,"Proses RPP",IF(BK11=20%,"Selesai RPP",IF(BK11<25%,"Proses KAK",IF(BK11=25%,"Selesai KAK",IF(BK11<30%,"Proses Pengadaan",IF(BK11=30%,"Selesai Pengadaan",IF(BK11<45%,"Proses Desain",IF(BK11=45%,"Selesai Desain",IF(BK11<80%,"Proses Pengembangan",IF(BK11=80%,"Selesai Pengembangan",IF(BK11<87.5%,"Proses SIT",IF(BK11=87.5%,"Selesai SIT",IF(BK11<95%,"Proses UAT",IF(BK11=95%,"Selesai UAT",IF(BK11<100%,"Proses Implementasi","Selesai Implementasi")))))))))))))))))))))) -> Not Started | AZ11: =IF(BL11=0%,"Not Started",IF(BL11<5%,"Proses RBT-RBB",IF(BL11=5%,"Selesai RBT-RBB",IF(BL11<10%,"Proses RBT-RBL",IF(BL11=10%,"Selesai RBT-RBL",IF(BL11<15%,"Proses RBT-RBTD",IF(BL11=15%,"Selesai RBT-RBTD",IF(BL11<20%,"Proses RPP",IF(BL11=20%,"Selesai RPP",IF(BL11<25%,"Proses KAK",IF(BL11=25%,"Selesai KAK",IF(BL11<30%,"Proses Pengadaan",IF(BL11=30%,"Selesai Pengadaan",IF(BL11<45%,"Proses Desain",IF(BL11=45%,"Selesai Desain",IF(BL11<80%,"Proses Pengembangan",IF(BL11=80%,"Selesai Pengembangan",IF(BL11<87.5%,"Proses SIT",IF(BL11=87.5%,"Selesai SIT",IF(BL11<95%,"Proses UAT",IF(BL11=95%,"Selesai UAT",IF(BL11<100%,"Proses Implementasi","Selesai Implementasi")))))))))))))))))))))) -> Not Started | ... BD11: =IF(BP11=0%,"Not Started",IF(BP11<5%,"Proses RBT-RBB",IF(BP11=5%,"Selesai RBT-RBB",IF(BP11<10%,"Proses RBT-RBL",IF(BP11=10%,"Selesai RBT-RBL",IF(BP11<15%,"Proses RBT-RBTD",IF(BP11=15%,"Selesai RBT-RBTD",IF(BP11<20%,"Proses RPP",IF(BP11=20%,"Selesai RPP",IF(BP11<25%,"Proses KAK",IF(BP11=25%,"Selesai KAK",IF(BP11<30%,"Proses Pengadaan",IF(BP11=30%,"Selesai Pengadaan",IF(BP11<45%,"Proses Desain",IF(BP11=45%,"Selesai Desain",IF(BP11<80%,"Proses Pengembangan",IF(BP11=80%,"Selesai Pengembangan",IF(BP11<87.5%,"Proses SIT",IF(BP11=87.5%,"Selesai SIT",IF(BP11<95%,"Proses UAT",IF(BP11=95%,"Selesai UAT",IF(BP11<100%,"Proses Implementasi","Selesai Implementasi")))))))))))))))))))))) -> Not Started | BE11: 0 | BF11: 0 | BG11: 0 | BH11: 0 | BI11: 0 | BJ11: 0 | BK11: 0 | BL11: 0 | BM11: 0 | BN11: 0 | BO11: 0 | BP11: 0 | BQ11: =IF(CC11=0%,"Not Started",IF(CC11<5%,"Proses RBT-RBB",IF(CC11=5%,"Selesai RBT-RBB",IF(CC11<10%,"Proses RBT-RBL",IF(CC11=10%,"Selesai RBT-RBL",IF(CC11<15%,"Proses RBT-RBTD",IF(CC11=15%,"Selesai RBT-RBTD",IF(CC11<20%,"Proses RPP",IF(CC11=20%,"Selesai RPP",IF(CC11<25%,"Proses KAK",IF(CC11=25%,"Selesai KAK",IF(CC11<30%,"Proses Pengadaan",IF(CC11=30%,"Selesai Pengadaan",IF(CC11<45%,"Proses Desain",IF(CC11=45%,"Selesai Desain",IF(CC11<80%,"Proses Pengembangan",IF(CC11=80%,"Selesai Pengembangan",IF(CC11<87.5%,"Proses SIT",IF(CC11=87.5%,"Selesai SIT",IF(CC11<95%,"Proses UAT",IF(CC11=95%,"Selesai UAT",IF(CC11<100%,"Proses Implementasi","Selesai Implementasi")))))))))))))))))))))) -> Not Started | BR11: =IF(CD11=0%,"Not Started",IF(CD11<5%,"Proses RBT-RBB",IF(CD11=5%,"Selesai RBT-RBB",IF(CD11<10%,"Proses RBT-RBL",IF(CD11=10%,"Selesai RBT-RBL",IF(CD11<15%,"Proses RBT-RBTD",IF(CD11=15%,"Selesai RBT-RBTD",IF(CD11<20%,"Proses RPP",IF(CD11=20%,"Selesai RPP",IF(CD11<25%,"Proses KAK",IF(CD11=25%,"Selesai KAK",IF(CD11<30%,"Proses Pengadaan",IF(CD11=30%,"Selesai Pengadaan",IF(CD11<45%,"Proses Desain",IF(CD11=45%,"Selesai Desain",IF(CD11<80%,"Proses Pengembangan",IF(CD11=80%,"Selesai Pengembangan",IF(CD11<87.5%,"Proses SIT",IF(CD11=87.5%,"Selesai SIT",IF(CD11<95%,"Proses UAT",IF(CD11=95%,"Selesai UAT",IF(CD11<100%,"Proses Implementasi","Selesai Implementasi")))))))))))))))))))))) -> Not Started | BS11: =IF(CE11=0%,"Not Started",IF(CE11<5%,"Proses RBT-RBB",IF(CE11=5%,"Selesai RBT-RBB",IF(CE11<10%,"Proses RBT-RBL",IF(CE11=10%,"Selesai RBT-RBL",IF(CE11<15%,"Proses RBT-RBTD",IF(CE11=15%,"Selesai RBT-RBTD",IF(CE11<20%,"Proses RPP",IF(CE11=20%,"Selesai RPP",IF(CE11<25%,"Proses KAK",IF(CE11=25%,"Selesai KAK",IF(CE11<30%,"Proses Pengadaan",IF(CE11=30%,"Selesai Pengadaan",IF(CE11<45%,"Proses Desain",IF(CE11=45%,"Selesai Desain",IF(CE11<80%,"Proses Pengembangan",IF(CE11=80%,"Selesai Pengembangan",IF(CE11<87.5%,"Proses SIT",IF(CE11=87.5%,"Selesai SIT",IF(CE11<95%,"Proses UAT",IF(CE11=95%,"Selesai UAT",IF(CE11<100%,"Proses Implementasi","Selesai Implementasi")))))))))))))))))))))) -> Not Started | BT11: =IF(CF11=0%,"Not Started",IF(CF11<5%,"Proses RBT-RBB",IF(CF11=5%,"Selesai RBT-RBB",IF(CF11<10%,"Proses RBT-RBL",IF(CF11=10%,"Selesai RBT-RBL",IF(CF11<15%,"Proses RBT-RBTD",IF(CF11=15%,"Selesai RBT-RBTD",IF(CF11<20%,"Proses RPP",IF(CF11=20%,"Selesai RPP",IF(CF11<25%,"Proses KAK",IF(CF11=25%,"Selesai KAK",IF(CF11<30%,"Proses Pengadaan",IF(CF11=30%,"Selesai Pengadaan",IF(CF11<45%,"Proses Desain",IF(CF11=45%,"Selesai Desain",IF(CF11<80%,"Proses Pengembangan",IF(CF11=80%,"Selesai Pengembangan",IF(CF11<87.5%,"Proses SIT",IF(CF11=87.5%,"Selesai SIT",IF(CF11<95%,"Proses UAT",IF(CF11=95%,"Selesai UAT",IF(CF11<100%,"Proses Implementasi","Selesai Implementasi")))))))))))))))))))))) -> Not Started | BU11: =IF(CG11=0%,"Not Started",IF(CG11<5%,"Proses RBT-RBB",IF(CG11=5%,"Selesai RBT-RBB",IF(CG11<10%,"Proses RBT-RBL",IF(CG11=10%,"Selesai RBT-RBL",IF(CG11<15%,"Proses RBT-RBTD",IF(CG11=15%,"Selesai RBT-RBTD",IF(CG11<20%,"Proses RPP",IF(CG11=20%,"Selesai RPP",IF(CG11<25%,"Proses KAK",IF(CG11=25%,"Selesai KAK",IF(CG11<30%,"Proses Pengadaan",IF(CG11=30%,"Selesai Pengadaan",IF(CG11<45%,"Proses Desain",IF(CG11=45%,"Selesai Desain",IF(CG11<80%,"Proses Pengembangan",IF(CG11=80%,"Selesai Pengembangan",IF(CG11<87.5%,"Proses SIT",IF(CG11=87.5%,"Selesai SIT",IF(CG11<95%,"Proses UAT",IF(CG11=95%,"Selesai UAT",IF(CG11<100%,"Proses Implementasi","Selesai Implementasi")))))))))))))))))))))) -> Not Started | BV11: =IF(CH11=0%,"Not Started",IF(CH11<5%,"Proses RBT-RBB",IF(CH11=5%,"Selesai RBT-RBB",IF(CH11<10%,"Proses RBT-RBL",IF(CH11=10%,"Selesai RBT-RBL",IF(CH11<15%,"Proses RBT-RBTD",IF(CH11=15%,"Selesai RBT-RBTD",IF(CH11<20%,"Proses RPP",IF(CH11=20%,"Selesai RPP",IF(CH11<25%,"Proses KAK",IF(CH11=25%,"Selesai KAK",IF(CH11<30%,"Proses Pengadaan",IF(CH11=30%,"Selesai Pengadaan",IF(CH11<45%,"Proses Desain",IF(CH11=45%,"Selesai Desain",IF(CH11<80%,"Proses Pengembangan",IF(CH11=80%,"Selesai Pengembangan",IF(CH11<87.5%,"Proses SIT",IF(CH11=87.5%,"Selesai SIT",IF(CH11<95%,"Proses UAT",IF(CH11=95%,"Selesai UAT",IF(CH11<100%,"Proses Implementasi","Selesai Implementasi")))))))))))))))))))))) -> Not Started | BW11: =IF(CI11=0%,"Not Started",IF(CI11<5%,"Proses RBT-RBB",IF(CI11=5%,"Selesai RBT-RBB",IF(CI11<10%,"Proses RBT-RBL",IF(CI11=10%,"Selesai RBT-RBL",IF(CI11<15%,"Proses RBT-RBTD",IF(CI11=15%,"Selesai RBT-RBTD",IF(CI11<20%,"Proses RPP",IF(CI11=20%,"Selesai RPP",IF(CI11<25%,"Proses KAK",IF(CI11=25%,"Selesai KAK",IF(CI11<30%,"Proses Pengadaan",IF(CI11=30%,"Selesai Pengadaan",IF(CI11<45%,"Proses Desain",IF(CI11=45%,"Selesai Desain",IF(CI11<80%,"Proses Pengembangan",IF(CI11=80%,"Selesai Pengembangan",IF(CI11<87.5%,"Proses SIT",IF(CI11=87.5%,"Selesai SIT",IF(CI11<95%,"Proses UAT",IF(CI11=95%,"Selesai UAT",IF(CI11<100%,"Proses Implementasi","Selesai Implementasi")))))))))))))))))))))) -> Not Started | BX11: =IF(CJ11=0%,"Not Started",IF(CJ11<5%,"Proses RBT-RBB",IF(CJ11=5%,"Selesai RBT-RBB",IF(CJ11<10%,"Proses RBT-RBL",IF(CJ11=10%,"Selesai RBT-RBL",IF(CJ11<15%,"Proses RBT-RBTD",IF(CJ11=15%,"Selesai RBT-RBTD",IF(CJ11<20%,"Proses RPP",IF(CJ11=20%,"Selesai RPP",IF(CJ11<25%,"Proses KAK",IF(CJ11=25%,"Selesai KAK",IF(CJ11<30%,"Proses Pengadaan",IF(CJ11=30%,"Selesai Pengadaan",IF(CJ11<45%,"Proses Desain",IF(CJ11=45%,"Selesai Desain",IF(CJ11<80%,"Proses Pengembangan",IF(CJ11=80%,"Selesai Pengembangan",IF(CJ11<87.5%,"Proses SIT",IF(CJ11=87.5%,"Selesai SIT",IF(CJ11<95%,"Proses UAT",IF(CJ11=95%,"Selesai UAT",IF(CJ11<100%,"Proses Implementasi","Selesai Implementasi")))))))))))))))))))))) -> Not Started | ... CB11: =IF(CN11=0%,"Not Started",IF(CN11<5%,"Proses RBT-RBB",IF(CN11=5%,"Selesai RBT-RBB",IF(CN11<10%,"Proses RBT-RBL",IF(CN11=10%,"Selesai RBT-RBL",IF(CN11<15%,"Proses RBT-RBTD",IF(CN11=15%,"Selesai RBT-RBTD",IF(CN11<20%,"Proses RPP",IF(CN11=20%,"Selesai RPP",IF(CN11<25%,"Proses KAK",IF(CN11=25%,"Selesai KAK",IF(CN11<30%,"Proses Pengadaan",IF(CN11=30%,"Selesai Pengadaan",IF(CN11<45%,"Proses Desain",IF(CN11=45%,"Selesai Desain",IF(CN11<80%,"Proses Pengembangan",IF(CN11=80%,"Selesai Pengembangan",IF(CN11<87.5%,"Proses SIT",IF(CN11=87.5%,"Selesai SIT",IF(CN11<95%,"Proses UAT",IF(CN11=95%,"Selesai UAT",IF(CN11<100%,"Proses Implementasi","Selesai Implementasi")))))))))))))))))))))) -> Not Started | CL11: 0 | CM11: =(($DY11/100%)*15%)+(($DZ11/100%)*5%)+(($EA11/100%)*5%)+(($EB11/100%)*5%)+(($EC11/100%)*15%)+(($ED11/100%)*35%)+(($EE11/100%)*7.5%)+(($EF11/100%)*7.5%)+(($EG11/100%)*5%) -> 0 | CN11: =(($DY11/100%)*15%)+(($DZ11/100%)*5%)+(($EA11/100%)*5%)+(($EB11/100%)*5%)+(($EC11/100%)*15%)+(($ED11/100%)*35%)+(($EE11/100%)*7.5%)+(($EF11/100%)*7.5%)+(($EG11/100%)*5%) -> 0 | CO11: =IF(BE11=0%, 100%, (CC11/BE11)) -> 1 | CP11: =IF(BF11=0%, 100%, (CD11/BF11)) -> 1 | CQ11: =IF(BG11=0%, 100%, (CE11/BG11)) -> 1 | CR11: =IF(BH11=0%, 100%, (CF11/BH11)) -> 1 | CS11: =IF(BI11=0%, 100%, (CG11/BI11)) -> 1 | CT11: =IF(BJ11=0%, 100%, (CH11/BJ11)) -> 1 | CU11: =IF(BK11=0%, 100%, (CI11/BK11)) -> 1 | CV11: =IF(BL11=0%, 100%, (CJ11/BL11)) -> 1 | ... CY11: =IF(BO11=0%, 100%, (CM11/BO11)) -> 1 | DA11: =IF(BE11=0%,"NS",IF(CC11=100%,"DONE",IF(CO11>100%,"AS",IF(CO11<75%,"BS",IF(CO11<89.9%,"AR","OS"))))) -> NS | DB11: =IF(BF11=0%,"NS",IF(CD11=100%,"DONE",IF(CP11>100%,"AS",IF(CP11<75%,"BS",IF(CP11<89.9%,"AR","OS"))))) -> NS | DC11: =IF(BG11=0%,"NS",IF(CE11=100%,"DONE",IF(CQ11>100%,"AS",IF(CQ11<75%,"BS",IF(CQ11<89.9%,"AR","OS"))))) -> NS | DD11: =IF(BH11=0%,"NS",IF(CF11=100%,"DONE",IF(CR11>100%,"AS",IF(CR11<75%,"BS",IF(CR11<89.9%,"AR","OS"))))) -> NS | DE11: =IF(BI11=0%,"NS",IF(CG11=100%,"DONE",IF(CS11>100%,"AS",IF(CS11<75%,"BS",IF(CS11<89.9%,"AR","OS"))))) -> NS | DF11: =IF(BJ11=0%,"NS",IF(CH11=100%,"DONE",IF(CT11>100%,"AS",IF(CT11<75%,"BS",IF(CT11<89.9%,"AR","OS"))))) -> NS | DG11: =IF(BK11=0%,"NS",IF(CI11=100%,"DONE",IF(CU11>100%,"AS",IF(CU11<75%,"BS",IF(CU11<89.9%,"AR","OS"))))) -> NS | DH11: =IF(BL11=0%,"NS",IF(CJ11=100%,"DONE",IF(CV11>100%,"AS",IF(CV11<75%,"BS",IF(CV11<89.9%,"AR","OS"))))) -> NS | ... DL11: =IF(BP11=0%,"NS",IF(CN11=100%,"DONE",IF(CZ11>100%,"AS",IF(CZ11<75%,"BS",IF(CZ11<89.9%,"AR","OS"))))) -> NS | DM11: =CC11/$BP11 -> #DIV/0! | DN11: =CD11/$BP11 -> #DIV/0! | DO11: =CE11/$BP11 -> #DIV/0! | DP11: =CF11/$BP11 -> #DIV/0! | DQ11: =CG11/$BP11 -> #DIV/0! | DR11: =CH11/$BP11 -> #DIV/0! | DS11: =CI11/$BP11 -> #DIV/0! | DT11: =CJ11/$BP11 -> #DIV/0! | ... DX11: =CN11/$BP11 -> #DIV/0! | EJ11: =AR11 -> 47118 | FO11: Iramia Triastika | FR11: Outsource
A12: RIVIBI-PPA-P6-1-DLDS | B12: PT2, BPPU | C12: IDT | D12: Continuity Technology | E12: P-4 | F12: =F11+1 -> 7 | G12: Pengembangan Pricing untuk OM Pro Market dan PUVA | H12: Infrastruktur Data PUVA | I12: EDP Capturing Pricing - Pricing Calculation & Dissemination: Perluasan kurs acuan non-USD/IDR (AED/IDR) | J12: 2025 | K12: 2025 | L12: S | M12: K3 | N12: Pemimpin Satker | O12: DPPK | P12: PPLBI | Q12: Market | R12: FOMOBO, SOA | S12: =BQ12 -> Selesai Implementasi | T12: =IF(V12=0%,"Not Started",IF(V12<100%,"On Progress",IF(V12=100%,"DONE"))) -> DONE | U12: =FN12 -> Helen Desyani | V12: =CC12 -> 1 | W12: TW II 2025 | X12: =AR12 -> 45930 | Y12: Inhouse | AA12: 45689 | AB12: 45791 | AC12: 45778 | AD12: 45791 | AI12: 45784 | AJ12: 45808 | AK12: 45809 | AL12: 45852 | AM12: 45853 | AN12: 45869 | AO12: 45870 | AP12: 45899 | AQ12: 45901 | AR12: 45930 | AS12: =IF(BE12=0%,"Not Started",IF(BE12<5%,"Proses RBT-RBB",IF(BE12=5%,"Selesai RBT-RBB",IF(BE12<10%,"Proses RBT-RBL",IF(BE12=10%,"Selesai RBT-RBL",IF(BE12<15%,"Proses RBT-RBTD",IF(BE12=15%,"Selesai RBT-RBTD",IF(BE12<20%,"Proses RPP",IF(BE12=20%,"Selesai RPP",IF(BE12<25%,"Proses KAK",IF(BE12=25%,"Selesai KAK",IF(BE12<30%,"Proses Pengadaan",IF(BE12=30%,"Selesai Pengadaan",IF(BE12<45%,"Proses Desain",IF(BE12=45%,"Selesai Desain",IF(BE12<80%,"Proses Pengembangan",IF(BE12=80%,"Selesai Pengembangan",IF(BE12<87.5%,"Proses SIT",IF(BE12=87.5%,"Selesai SIT",IF(BE12<95%,"Proses UAT",IF(BE12=95%,"Selesai UAT",IF(BE12<100%,"Proses Implementasi","Selesai Implementasi")))))))))))))))))))))) -> Selesai Implementasi | AT12: =IF(BF12=0%,"Not Started",IF(BF12<5%,"Proses RBT-RBB",IF(BF12=5%,"Selesai RBT-RBB",IF(BF12<10%,"Proses RBT-RBL",IF(BF12=10%,"Selesai RBT-RBL",IF(BF12<15%,"Proses RBT-RBTD",IF(BF12=15%,"Selesai RBT-RBTD",IF(BF12<20%,"Proses RPP",IF(BF12=20%,"Selesai RPP",IF(BF12<25%,"Proses KAK",IF(BF12=25%,"Selesai KAK",IF(BF12<30%,"Proses Pengadaan",IF(BF12=30%,"Selesai Pengadaan",IF(BF12<45%,"Proses Desain",IF(BF12=45%,"Selesai Desain",IF(BF12<80%,"Proses Pengembangan",IF(BF12=80%,"Selesai Pengembangan",IF(BF12<87.5%,"Proses SIT",IF(BF12=87.5%,"Selesai SIT",IF(BF12<95%,"Proses UAT",IF(BF12=95%,"Selesai UAT",IF(BF12<100%,"Proses Implementasi","Selesai Implementasi")))))))))))))))))))))) -> Selesai Implementasi | AU12: =IF(BG12=0%,"Not Started",IF(BG12<5%,"Proses RBT-RBB",IF(BG12=5%,"Selesai RBT-RBB",IF(BG12<10%,"Proses RBT-RBL",IF(BG12=10%,"Selesai RBT-RBL",IF(BG12<15%,"Proses RBT-RBTD",IF(BG12=15%,"Selesai RBT-RBTD",IF(BG12<20%,"Proses RPP",IF(BG12=20%,"Selesai RPP",IF(BG12<25%,"Proses KAK",IF(BG12=25%,"Selesai KAK",IF(BG12<30%,"Proses Pengadaan",IF(BG12=30%,"Selesai Pengadaan",IF(BG12<45%,"Proses Desain",IF(BG12=45%,"Selesai Desain",IF(BG12<80%,"Proses Pengembangan",IF(BG12=80%,"Selesai Pengembangan",IF(BG12<87.5%,"Proses SIT",IF(BG12=87.5%,"Selesai SIT",IF(BG12<95%,"Proses UAT",IF(BG12=95%,"Selesai UAT",IF(BG12<100%,"Proses Implementasi","Selesai Implementasi")))))))))))))))))))))) -> Selesai Implementasi | AV12: =IF(BH12=0%,"Not Started",IF(BH12<5%,"Proses RBT-RBB",IF(BH12=5%,"Selesai RBT-RBB",IF(BH12<10%,"Proses RBT-RBL",IF(BH12=10%,"Selesai RBT-RBL",IF(BH12<15%,"Proses RBT-RBTD",IF(BH12=15%,"Selesai RBT-RBTD",IF(BH12<20%,"Proses RPP",IF(BH12=20%,"Selesai RPP",IF(BH12<25%,"Proses KAK",IF(BH12=25%,"Selesai KAK",IF(BH12<30%,"Proses Pengadaan",IF(BH12=30%,"Selesai Pengadaan",IF(BH12<45%,"Proses Desain",IF(BH12=45%,"Selesai Desain",IF(BH12<80%,"Proses Pengembangan",IF(BH12=80%,"Selesai Pengembangan",IF(BH12<87.5%,"Proses SIT",IF(BH12=87.5%,"Selesai SIT",IF(BH12<95%,"Proses UAT",IF(BH12=95%,"Selesai UAT",IF(BH12<100%,"Proses Implementasi","Selesai Implementasi")))))))))))))))))))))) -> Selesai Implementasi | AW12: =IF(BI12=0%,"Not Started",IF(BI12<5%,"Proses RBT-RBB",IF(BI12=5%,"Selesai RBT-RBB",IF(BI12<10%,"Proses RBT-RBL",IF(BI12=10%,"Selesai RBT-RBL",IF(BI12<15%,"Proses RBT-RBTD",IF(BI12=15%,"Selesai RBT-RBTD",IF(BI12<20%,"Proses RPP",IF(BI12=20%,"Selesai RPP",IF(BI12<25%,"Proses KAK",IF(BI12=25%,"Selesai KAK",IF(BI12<30%,"Proses Pengadaan",IF(BI12=30%,"Selesai Pengadaan",IF(BI12<45%,"Proses Desain",IF(BI12=45%,"Selesai Desain",IF(BI12<80%,"Proses Pengembangan",IF(BI12=80%,"Selesai Pengembangan",IF(BI12<87.5%,"Proses SIT",IF(BI12=87.5%,"Selesai SIT",IF(BI12<95%,"Proses UAT",IF(BI12=95%,"Selesai UAT",IF(BI12<100%,"Proses Implementasi","Selesai Implementasi")))))))))))))))))))))) -> Selesai Implementasi | AX12: =IF(BJ12=0%,"Not Started",IF(BJ12<5%,"Proses RBT-RBB",IF(BJ12=5%,"Selesai RBT-RBB",IF(BJ12<10%,"Proses RBT-RBL",IF(BJ12=10%,"Selesai RBT-RBL",IF(BJ12<15%,"Proses RBT-RBTD",IF(BJ12=15%,"Selesai RBT-RBTD",IF(BJ12<20%,"Proses RPP",IF(BJ12=20%,"Selesai RPP",IF(BJ12<25%,"Proses KAK",IF(BJ12=25%,"Selesai KAK",IF(BJ12<30%,"Proses Pengadaan",IF(BJ12=30%,"Selesai Pengadaan",IF(BJ12<45%,"Proses Desain",IF(BJ12=45%,"Selesai Desain",IF(BJ12<80%,"Proses Pengembangan",IF(BJ12=80%,"Selesai Pengembangan",IF(BJ12<87.5%,"Proses SIT",IF(BJ12=87.5%,"Selesai SIT",IF(BJ12<95%,"Proses UAT",IF(BJ12=95%,"Selesai UAT",IF(BJ12<100%,"Proses Implementasi","Selesai Implementasi")))))))))))))))))))))) -> Selesai Implementasi | AY12: =IF(BK12=0%,"Not Started",IF(BK12<5%,"Proses RBT-RBB",IF(BK12=5%,"Selesai RBT-RBB",IF(BK12<10%,"Proses RBT-RBL",IF(BK12=10%,"Selesai RBT-RBL",IF(BK12<15%,"Proses RBT-RBTD",IF(BK12=15%,"Selesai RBT-RBTD",IF(BK12<20%,"Proses RPP",IF(BK12=20%,"Selesai RPP",IF(BK12<25%,"Proses KAK",IF(BK12=25%,"Selesai KAK",IF(BK12<30%,"Proses Pengadaan",IF(BK12=30%,"Selesai Pengadaan",IF(BK12<45%,"Proses Desain",IF(BK12=45%,"Selesai Desain",IF(BK12<80%,"Proses Pengembangan",IF(BK12=80%,"Selesai Pengembangan",IF(BK12<87.5%,"Proses SIT",IF(BK12=87.5%,"Selesai SIT",IF(BK12<95%,"Proses UAT",IF(BK12=95%,"Selesai UAT",IF(BK12<100%,"Proses Implementasi","Selesai Implementasi")))))))))))))))))))))) -> Selesai Implementasi | AZ12: =IF(BL12=0%,"Not Started",IF(BL12<5%,"Proses RBT-RBB",IF(BL12=5%,"Selesai RBT-RBB",IF(BL12<10%,"Proses RBT-RBL",IF(BL12=10%,"Selesai RBT-RBL",IF(BL12<15%,"Proses RBT-RBTD",IF(BL12=15%,"Selesai RBT-RBTD",IF(BL12<20%,"Proses RPP",IF(BL12=20%,"Selesai RPP",IF(BL12<25%,"Proses KAK",IF(BL12=25%,"Selesai KAK",IF(BL12<30%,"Proses Pengadaan",IF(BL12=30%,"Selesai Pengadaan",IF(BL12<45%,"Proses Desain",IF(BL12=45%,"Selesai Desain",IF(BL12<80%,"Proses Pengembangan",IF(BL12=80%,"Selesai Pengembangan",IF(BL12<87.5%,"Proses SIT",IF(BL12=87.5%,"Selesai SIT",IF(BL12<95%,"Proses UAT",IF(BL12=95%,"Selesai UAT",IF(BL12<100%,"Proses Implementasi","Selesai Implementasi")))))))))))))))))))))) -> Selesai Implementasi | ... BD12: =IF(BP12=0%,"Not Started",IF(BP12<5%,"Proses RBT-RBB",IF(BP12=5%,"Selesai RBT-RBB",IF(BP12<10%,"Proses RBT-RBL",IF(BP12=10%,"Selesai RBT-RBL",IF(BP12<15%,"Proses RBT-RBTD",IF(BP12=15%,"Selesai RBT-RBTD",IF(BP12<20%,"Proses RPP",IF(BP12=20%,"Selesai RPP",IF(BP12<25%,"Proses KAK",IF(BP12=25%,"Selesai KAK",IF(BP12<30%,"Proses Pengadaan",IF(BP12=30%,"Selesai Pengadaan",IF(BP12<45%,"Proses Desain",IF(BP12=45%,"Selesai Desain",IF(BP12<80%,"Proses Pengembangan",IF(BP12=80%,"Selesai Pengembangan",IF(BP12<87.5%,"Proses SIT",IF(BP12=87.5%,"Selesai SIT",IF(BP12<95%,"Proses UAT",IF(BP12=95%,"Selesai UAT",IF(BP12<100%,"Proses Implementasi","Selesai Implementasi")))))))))))))))))))))) -> Selesai Implementasi | BE12: 1 | BF12: 1 | BG12: 1 | BH12: 1 | BI12: 1 | BJ12: 1 | BK12: 1 | BL12: 1 | BM12: 1 | BN12: 1 | BO12: 1 | BP12: 1 | BQ12: =IF(CC12=0%,"Not Started",IF(CC12<5%,"Proses RBT-RBB",IF(CC12=5%,"Selesai RBT-RBB",IF(CC12<10%,"Proses RBT-RBL",IF(CC12=10%,"Selesai RBT-RBL",IF(CC12<15%,"Proses RBT-RBTD",IF(CC12=15%,"Selesai RBT-RBTD",IF(CC12<20%,"Proses RPP",IF(CC12=20%,"Selesai RPP",IF(CC12<25%,"Proses KAK",IF(CC12=25%,"Selesai KAK",IF(CC12<30%,"Proses Pengadaan",IF(CC12=30%,"Selesai Pengadaan",IF(CC12<45%,"Proses Desain",IF(CC12=45%,"Selesai Desain",IF(CC12<80%,"Proses Pengembangan",IF(CC12=80%,"Selesai Pengembangan",IF(CC12<87.5%,"Proses SIT",IF(CC12=87.5%,"Selesai SIT",IF(CC12<95%,"Proses UAT",IF(CC12=95%,"Selesai UAT",IF(CC12<100%,"Proses Implementasi","Selesai Implementasi")))))))))))))))))))))) -> Selesai Implementasi | BR12: =IF(CD12=0%,"Not Started",IF(CD12<5%,"Proses RBT-RBB",IF(CD12=5%,"Selesai RBT-RBB",IF(CD12<10%,"Proses RBT-RBL",IF(CD12=10%,"Selesai RBT-RBL",IF(CD12<15%,"Proses RBT-RBTD",IF(CD12=15%,"Selesai RBT-RBTD",IF(CD12<20%,"Proses RPP",IF(CD12=20%,"Selesai RPP",IF(CD12<25%,"Proses KAK",IF(CD12=25%,"Selesai KAK",IF(CD12<30%,"Proses Pengadaan",IF(CD12=30%,"Selesai Pengadaan",IF(CD12<45%,"Proses Desain",IF(CD12=45%,"Selesai Desain",IF(CD12<80%,"Proses Pengembangan",IF(CD12=80%,"Selesai Pengembangan",IF(CD12<87.5%,"Proses SIT",IF(CD12=87.5%,"Selesai SIT",IF(CD12<95%,"Proses UAT",IF(CD12=95%,"Selesai UAT",IF(CD12<100%,"Proses Implementasi","Selesai Implementasi")))))))))))))))))))))) -> Not Started | BS12: =IF(CE12=0%,"Not Started",IF(CE12<5%,"Proses RBT-RBB",IF(CE12=5%,"Selesai RBT-RBB",IF(CE12<10%,"Proses RBT-RBL",IF(CE12=10%,"Selesai RBT-RBL",IF(CE12<15%,"Proses RBT-RBTD",IF(CE12=15%,"Selesai RBT-RBTD",IF(CE12<20%,"Proses RPP",IF(CE12=20%,"Selesai RPP",IF(CE12<25%,"Proses KAK",IF(CE12=25%,"Selesai KAK",IF(CE12<30%,"Proses Pengadaan",IF(CE12=30%,"Selesai Pengadaan",IF(CE12<45%,"Proses Desain",IF(CE12=45%,"Selesai Desain",IF(CE12<80%,"Proses Pengembangan",IF(CE12=80%,"Selesai Pengembangan",IF(CE12<87.5%,"Proses SIT",IF(CE12=87.5%,"Selesai SIT",IF(CE12<95%,"Proses UAT",IF(CE12=95%,"Selesai UAT",IF(CE12<100%,"Proses Implementasi","Selesai Implementasi")))))))))))))))))))))) -> Not Started | BT12: =IF(CF12=0%,"Not Started",IF(CF12<5%,"Proses RBT-RBB",IF(CF12=5%,"Selesai RBT-RBB",IF(CF12<10%,"Proses RBT-RBL",IF(CF12=10%,"Selesai RBT-RBL",IF(CF12<15%,"Proses RBT-RBTD",IF(CF12=15%,"Selesai RBT-RBTD",IF(CF12<20%,"Proses RPP",IF(CF12=20%,"Selesai RPP",IF(CF12<25%,"Proses KAK",IF(CF12=25%,"Selesai KAK",IF(CF12<30%,"Proses Pengadaan",IF(CF12=30%,"Selesai Pengadaan",IF(CF12<45%,"Proses Desain",IF(CF12=45%,"Selesai Desain",IF(CF12<80%,"Proses Pengembangan",IF(CF12=80%,"Selesai Pengembangan",IF(CF12<87.5%,"Proses SIT",IF(CF12=87.5%,"Selesai SIT",IF(CF12<95%,"Proses UAT",IF(CF12=95%,"Selesai UAT",IF(CF12<100%,"Proses Implementasi","Selesai Implementasi")))))))))))))))))))))) -> Not Started | BU12: =IF(CG12=0%,"Not Started",IF(CG12<5%,"Proses RBT-RBB",IF(CG12=5%,"Selesai RBT-RBB",IF(CG12<10%,"Proses RBT-RBL",IF(CG12=10%,"Selesai RBT-RBL",IF(CG12<15%,"Proses RBT-RBTD",IF(CG12=15%,"Selesai RBT-RBTD",IF(CG12<20%,"Proses RPP",IF(CG12=20%,"Selesai RPP",IF(CG12<25%,"Proses KAK",IF(CG12=25%,"Selesai KAK",IF(CG12<30%,"Proses Pengadaan",IF(CG12=30%,"Selesai Pengadaan",IF(CG12<45%,"Proses Desain",IF(CG12=45%,"Selesai Desain",IF(CG12<80%,"Proses Pengembangan",IF(CG12=80%,"Selesai Pengembangan",IF(CG12<87.5%,"Proses SIT",IF(CG12=87.5%,"Selesai SIT",IF(CG12<95%,"Proses UAT",IF(CG12=95%,"Selesai UAT",IF(CG12<100%,"Proses Implementasi","Selesai Implementasi")))))))))))))))))))))) -> Not Started | BV12: =IF(CH12=0%,"Not Started",IF(CH12<5%,"Proses RBT-RBB",IF(CH12=5%,"Selesai RBT-RBB",IF(CH12<10%,"Proses RBT-RBL",IF(CH12=10%,"Selesai RBT-RBL",IF(CH12<15%,"Proses RBT-RBTD",IF(CH12=15%,"Selesai RBT-RBTD",IF(CH12<20%,"Proses RPP",IF(CH12=20%,"Selesai RPP",IF(CH12<25%,"Proses KAK",IF(CH12=25%,"Selesai KAK",IF(CH12<30%,"Proses Pengadaan",IF(CH12=30%,"Selesai Pengadaan",IF(CH12<45%,"Proses Desain",IF(CH12=45%,"Selesai Desain",IF(CH12<80%,"Proses Pengembangan",IF(CH12=80%,"Selesai Pengembangan",IF(CH12<87.5%,"Proses SIT",IF(CH12=87.5%,"Selesai SIT",IF(CH12<95%,"Proses UAT",IF(CH12=95%,"Selesai UAT",IF(CH12<100%,"Proses Implementasi","Selesai Implementasi")))))))))))))))))))))) -> Not Started | BW12: =IF(CI12=0%,"Not Started",IF(CI12<5%,"Proses RBT-RBB",IF(CI12=5%,"Selesai RBT-RBB",IF(CI12<10%,"Proses RBT-RBL",IF(CI12=10%,"Selesai RBT-RBL",IF(CI12<15%,"Proses RBT-RBTD",IF(CI12=15%,"Selesai RBT-RBTD",IF(CI12<20%,"Proses RPP",IF(CI12=20%,"Selesai RPP",IF(CI12<25%,"Proses KAK",IF(CI12=25%,"Selesai KAK",IF(CI12<30%,"Proses Pengadaan",IF(CI12=30%,"Selesai Pengadaan",IF(CI12<45%,"Proses Desain",IF(CI12=45%,"Selesai Desain",IF(CI12<80%,"Proses Pengembangan",IF(CI12=80%,"Selesai Pengembangan",IF(CI12<87.5%,"Proses SIT",IF(CI12=87.5%,"Selesai SIT",IF(CI12<95%,"Proses UAT",IF(CI12=95%,"Selesai UAT",IF(CI12<100%,"Proses Implementasi","Selesai Implementasi")))))))))))))))))))))) -> Not Started | BX12: =IF(CJ12=0%,"Not Started",IF(CJ12<5%,"Proses RBT-RBB",IF(CJ12=5%,"Selesai RBT-RBB",IF(CJ12<10%,"Proses RBT-RBL",IF(CJ12=10%,"Selesai RBT-RBL",IF(CJ12<15%,"Proses RBT-RBTD",IF(CJ12=15%,"Selesai RBT-RBTD",IF(CJ12<20%,"Proses RPP",IF(CJ12=20%,"Selesai RPP",IF(CJ12<25%,"Proses KAK",IF(CJ12=25%,"Selesai KAK",IF(CJ12<30%,"Proses Pengadaan",IF(CJ12=30%,"Selesai Pengadaan",IF(CJ12<45%,"Proses Desain",IF(CJ12=45%,"Selesai Desain",IF(CJ12<80%,"Proses Pengembangan",IF(CJ12=80%,"Selesai Pengembangan",IF(CJ12<87.5%,"Proses SIT",IF(CJ12=87.5%,"Selesai SIT",IF(CJ12<95%,"Proses UAT",IF(CJ12=95%,"Selesai UAT",IF(CJ12<100%,"Proses Implementasi","Selesai Implementasi")))))))))))))))))))))) -> Not Started | ... CB12: =IF(CN12=0%,"Not Started",IF(CN12<5%,"Proses RBT-RBB",IF(CN12=5%,"Selesai RBT-RBB",IF(CN12<10%,"Proses RBT-RBL",IF(CN12=10%,"Selesai RBT-RBL",IF(CN12<15%,"Proses RBT-RBTD",IF(CN12=15%,"Selesai RBT-RBTD",IF(CN12<20%,"Proses RPP",IF(CN12=20%,"Selesai RPP",IF(CN12<25%,"Proses KAK",IF(CN12=25%,"Selesai KAK",IF(CN12<30%,"Proses Pengadaan",IF(CN12=30%,"Selesai Pengadaan",IF(CN12<45%,"Proses Desain",IF(CN12=45%,"Selesai Desain",IF(CN12<80%,"Proses Pengembangan",IF(CN12=80%,"Selesai Pengembangan",IF(CN12<87.5%,"Proses SIT",IF(CN12=87.5%,"Selesai SIT",IF(CN12<95%,"Proses UAT",IF(CN12=95%,"Selesai UAT",IF(CN12<100%,"Proses Implementasi","Selesai Implementasi")))))))))))))))))))))) -> Not Started | CC12: =(($DY12/100%)*15%)+(($DZ12/100%)*5%)+(($EA12/100%)*5%)+(($EB12/100%)*5%)+(($EC12/100%)*15%)+(($ED12/100%)*35%)+(($EE12/100%)*7.5%)+(($EF12/100%)*7.5%)+(($EG12/100%)*5%) -> 1 | CO12: =IF(BE12=0%, 100%, (CC12/BE12)) -> 1 | CP12: =IF(BF12=0%, 100%, (CD12/BF12)) -> 0 | CQ12: =IF(BG12=0%, 100%, (CE12/BG12)) -> 0 | CR12: =IF(BH12=0%, 100%, (CF12/BH12)) -> 0 | CS12: =IF(BI12=0%, 100%, (CG12/BI12)) -> 0 | CT12: =IF(BJ12=0%, 100%, (CH12/BJ12)) -> 0 | CU12: =IF(BK12=0%, 100%, (CI12/BK12)) -> 0 | CV12: =IF(BL12=0%, 100%, (CJ12/BL12)) -> 0 | ... CY12: =IF(BO12=0%, 100%, (CM12/BO12)) -> 0 | DA12: =IF(BE12=0%,"NS",IF(CC12=100%,"DONE",IF(CO12>100%,"AS",IF(CO12<75%,"BS",IF(CO12<89.9%,"AR","OS"))))) -> DONE | DB12: =IF(BF12=0%,"NS",IF(CD12=100%,"DONE",IF(CP12>100%,"AS",IF(CP12<75%,"BS",IF(CP12<89.9%,"AR","OS"))))) -> BS | DC12: =IF(BG12=0%,"NS",IF(CE12=100%,"DONE",IF(CQ12>100%,"AS",IF(CQ12<75%,"BS",IF(CQ12<89.9%,"AR","OS"))))) -> BS | DD12: =IF(BH12=0%,"NS",IF(CF12=100%,"DONE",IF(CR12>100%,"AS",IF(CR12<75%,"BS",IF(CR12<89.9%,"AR","OS"))))) -> BS | DE12: =IF(BI12=0%,"NS",IF(CG12=100%,"DONE",IF(CS12>100%,"AS",IF(CS12<75%,"BS",IF(CS12<89.9%,"AR","OS"))))) -> BS | DF12: =IF(BJ12=0%,"NS",IF(CH12=100%,"DONE",IF(CT12>100%,"AS",IF(CT12<75%,"BS",IF(CT12<89.9%,"AR","OS"))))) -> BS | DG12: =IF(BK12=0%,"NS",IF(CI12=100%,"DONE",IF(CU12>100%,"AS",IF(CU12<75%,"BS",IF(CU12<89.9%,"AR","OS"))))) -> BS | DH12: =IF(BL12=0%,"NS",IF(CJ12=100%,"DONE",IF(CV12>100%,"AS",IF(CV12<75%,"BS",IF(CV12<89.9%,"AR","OS"))))) -> BS | ... DL12: =IF(BP12=0%,"NS",IF(CN12=100%,"DONE",IF(CZ12>100%,"AS",IF(CZ12<75%,"BS",IF(CZ12<89.9%,"AR","OS"))))) -> BS | DM12: =CC12/$BP12 -> 1 | DN12: =CD12/$BP12 -> 0 | DO12: =CE12/$BP12 -> 0 | DP12: =CF12/$BP12 -> 0 | DQ12: =CG12/$BP12 -> 0 | DR12: =CH12/$BP12 -> 0 | DS12: =CI12/$BP12 -> 0 | DT12: =CJ12/$BP12 -> 0 | ... DX12: =CN12/$BP12 -> 0 | DY12: 1 | DZ12: 1 | EA12: 1 | EB12: 1 | EC12: 1 | ED12: 1 | EE12: 1 | EF12: 1 | EG12: 1 | EH12: 1. On progres pengujian SIT, tersisa 3 skenario lagi, target pengujian akan di selesaikan minggu ini berikut dengan doc laporan SIT 2. Jumat, 25 July Kick Off UAT dan Minggu ini akan di mulai pengujian UAT 3. UAT sudah selesai, proses dokumentasi dan digisign T.4.3 dan T.4.4 4. Rencana Implementasi di tanggal 8 Agustus 5. Telah di lakukan implementasi 8 Agustus dan Sedang dalam tahap monitoring Paskah Go Live 6. FINISH | EI12: 45877 | EJ12: =AR12 -> 45930 | FM12: 1. Farah Fadhillah W | FN12: Helen Desyani | FO12: Iramia Triastika | FP12: 1. Ahmad Maimunif 2. Yohana Wida 3. Dody Sulaiman 4. Ahmad Muhajir 5. Anton Sucipto | FQ12: Agung | FR12: Inhouse | FS12: N/A | FT12: Novita | FU12: 7
